Workbook
Name Country: '[1]Country Data'!$A$6:$A$52
Name NPV_Country: '[1]User Inputs'!$F$11

Sheet Instructions
A1: INSTRUCTIONS
A3: Step 1: In the "User Inputs" tab, select the country you are interested in estimating costs and benefits of implementing the Roadmap
A4: Step 2: Data is already pre-populated from the Roadmap Global Investment Case completed in 2019; Adjust as needed any cells in yellow in the "User inputs" tab by revising any values
A5: Step 3: See tab "Summary" for adjusted outputs and estimates on costs and benefits of implementing the Roadmap (note that this tab does not require any adjustments)
A9: OBJECTIVE OF TOOL
A11: This tool was developed using the methodology from the GTFCC Global Investment Case (completed in 2019) to estimate the potential costs and benefits of implementing the Roadmap. The tool has been simplified for country use to provide key inputs into their Country Investment Case to advocate for implementing the interventions of Ending Cholera: A roadmap to 2030. The Country Invesment Case can be used to assist countries to fundraise for different interventions.

Sheet User Inputs
B3: COUNTRY DATA VERIFICATION
C5: Step 1: SELECT COUNTRY --> | F5: Malawi
C7: Step 2: ENTER COUNTRY DATA- Please validate and replace default values with country data if available | I7: ROADMAP DATA SOURCE /COMMENT
C8: OVERVIEW AND TIME | F8: Start | G8: End
E9: Roadmap start and end year | F9: 2026 | G9: 2030 | J9: MMCCP
E10: Time period for Country investment case (in years) | F10: 5
C11: Social discount rate for valuing future costs and benefits in present values (2019) | F11: =INDIRECT("'Country Data'!"&ADDRESS(MATCH($F$5,'Country Data'!$A:$A,FALSE),MATCH(ADDRESS(ROW(),COLUMN(),4),'Country Model'!$9:$9,FALSE),4))+F2 -> 0.05
E12: WASH Target in elimination year | F12: 0.9
C13: BASELINE DATA | F13: Urban | G13: Rural
D14: National population size ('000) | F14: 3234 | G14: 17499 | J14: National Statistic Office 2025 projections (20,270,568) (Applying distribution of population by area of residence for 2020 Integrated Household Survey - 84.4 Rural & 15.6 Urban)
D15: Average population growth until 2030 (% annual) | F15: =INDIRECT("'Country Data'!"&ADDRESS(MATCH($F$5,'Country Data'!$A:$A,FALSE),MATCH(ADDRESS(ROW(),COLUMN(),4),'Country Model'!$9:$9,FALSE),4)) -> 4.2208078 | G15: =INDIRECT("'Country Data'!"&ADDRESS(MATCH($F$5,'Country Data'!$A:$A,FALSE),MATCH(ADDRESS(ROW(),COLUMN(),4),'Country Model'!$9:$9,FALSE),4)) -> 2.3622412
D16: Population age breakdown (3 age groups must add to 100%) | F16: =F17+F18+F19 -> 1 | G16: =G17+G18+G19 -> 1
E17: 0-4 years | F17: 0.13 | G17: 0.15 | J17: Calculations based on the 2018 census National Population tables
E18: 5-14 years | F18: 0.25 | G18: 0.3
E19: 15+ years | F19: 0.62 | G19: 0.55
D20: Average household size (number of members) | F20: 4 | G20: 4.5
D21: Population living in cholera hotspots in Year 0 | F21: 1215861 | G21: 7036077 | J21: PAMI
D22: Water Basic Coverage - Year 0 | F22: 0.52 | G22: 0.58 | J22: 2024/2025 Malawi WASH Budget Brief by UNICEF (Investing in climate-resilient WASH services amidst recurring climatic shocks and vulnerabilities in Malawi)
D23: Sanitation Basic Coverage - Year 0 | F23: 0.07 | G23: 0.02 | J23: The WHO/UNICEF Joint Monitoring Programme (JMP) 2022 Data
D24: Hygiene Basic Coverage - Year 0 | F24: 0.28 | G24: 0.13 | J24: The WHO/UNICEF Joint Monitoring Programme (JMP) 2022 Data
C25: UNIT COSTS - TUBEWELLS
D26: New facility cost (initial cost per person in USD) | F26: 65 | G26: 50 | J26: Expert opinion, Dept. of Water development
D27: New facility life (number of years before replacement) | F27: =INDIRECT("'Country Data'!"&ADDRESS(MATCH($F$5,'Country Data'!$A:$A,FALSE),MATCH(ADDRESS(ROW(),COLUMN(),4),'Country Model'!$9:$9,FALSE),4)) -> 20 | G27: =INDIRECT("'Country Data'!"&ADDRESS(MATCH($F$5,'Country Data'!$A:$A,FALSE),MATCH(ADDRESS(ROW(),COLUMN(),4),'Country Model'!$9:$9,FALSE),4)) -> 20
D28: Water treatment (cost per person per year in USD) | F28: 5 | G28: 5
D29: Water source O&M cost (cost per person per year in USD) | F29: 2.5 | G29: 3
C30: UNIT COSTS - PIT LATRINES
D31: New facility cost (initial cost per person in USD) | F31: 40 | G31: 40
D32: New facility life (number of years before replacement) | F32: =INDIRECT("'Country Data'!"&ADDRESS(MATCH($F$5,'Country Data'!$A:$A,FALSE),MATCH(ADDRESS(ROW(),COLUMN(),4),'Country Model'!$9:$9,FALSE),4)) -> 10 | G32: =INDIRECT("'Country Data'!"&ADDRESS(MATCH($F$5,'Country Data'!$A:$A,FALSE),MATCH(ADDRESS(ROW(),COLUMN(),4),'Country Model'!$9:$9,FALSE),4)) -> 10
D33: O&M cost (cost per person per year in USD) | F33: 5.5 | G33: 5.5
C34: UNIT COSTS - HYGIENE
D35: New handwashing station cost (initial cost per person, US$ 2018 prices) | F35: =INDIRECT("'Country Data'!"&ADDRESS(MATCH($F$5,'Country Data'!$A:$A,FALSE),MATCH(ADDRESS(ROW(),COLUMN(),4),'Country Model'!$9:$9,FALSE),4)) -> 17.499201 | G35: =INDIRECT("'Country Data'!"&ADDRESS(MATCH($F$5,'Country Data'!$A:$A,FALSE),MATCH(ADDRESS(ROW(),COLUMN(),4),'Country Model'!$9:$9,FALSE),4)) -> 3.1001201
D36: New facility life (number of years before replacement) | F36: =INDIRECT("'Country Data'!"&ADDRESS(MATCH($F$5,'Country Data'!$A:$A,FALSE),MATCH(ADDRESS(ROW(),COLUMN(),4),'Country Model'!$9:$9,FALSE),4)) -> 5 | G36: =INDIRECT("'Country Data'!"&ADDRESS(MATCH($F$5,'Country Data'!$A:$A,FALSE),MATCH(ADDRESS(ROW(),COLUMN(),4),'Country Model'!$9:$9,FALSE),4)) -> 5
D37: O&M cost, including soap (cost per person per year, US$ 2018 prices) | F37: =INDIRECT("'Country Data'!"&ADDRESS(MATCH($F$5,'Country Data'!$A:$A,FALSE),MATCH(ADDRESS(ROW(),COLUMN(),4),'Country Model'!$9:$9,FALSE),4)) -> 11.114799 | G37: =INDIRECT("'Country Data'!"&ADDRESS(MATCH($F$5,'Country Data'!$A:$A,FALSE),MATCH(ADDRESS(ROW(),COLUMN(),4),'Country Model'!$9:$9,FALSE),4)) -> 5.3609712
C38: UNIT COSTS - OTHER
D39: Emergency WASH (cost per person receiving emergency WASH) | F39: 10 | G39: 10
D40: National Surveillance Costs (average annual cost from start of roadmap) | F40: 482124 | G40: =INDIRECT("'Country Data'!"&ADDRESS(MATCH($F$5,'Country Data'!$A:$A,FALSE),MATCH(ADDRESS(ROW(),COLUMN(),4),'Country Model'!$9:$9,FALSE),4)) -> #N/A
C41: UNIT COSTS - OCV CAMPAIGNS (Preventive)
D42: Vaccine unit price per dose, after 2025 (in USD) | F42: 2.5 | G42: =INDIRECT("'Country Data'!"&ADDRESS(MATCH($F$5,'Country Data'!$A:$A,FALSE),MATCH(ADDRESS(ROW(),COLUMN(),4),'Country Model'!$9:$9,FALSE),4)) -> #N/A
D43: Doses per person vaccinated | F43: 2 | G43: =INDIRECT("'Country Data'!"&ADDRESS(MATCH($F$5,'Country Data'!$A:$A,FALSE),MATCH(ADDRESS(ROW(),COLUMN(),4),'Country Model'!$9:$9,FALSE),4)) -> #N/A
D44: Vaccine delivery (cost per person receiving required doses, US$ 2025) | F44: 1.25 | G44: 1.25
C45: CHOLERA EPIDEMIOLOGY
D46: Total number of cholera cases (last year of data or average last 3 years) | F46: 12110 | G46: 42384
D47: Total number of cholera deaths (last year of data or average last 3 years) | F47: 319 | G47: 1275
D48: Percentage of hotspots (population) with outbreaks per year | F48: 0.8 | G48: 0.3
C49: CHOLERA HEALTH OUTCOMES FROM ELEMENTS OF ROADMAP
D50: Protective effect (proportion reduction in risk) - WASH alone | F50: =INDIRECT("'Country Data'!"&ADDRESS(MATCH($F$5,'Country Data'!$A:$A,FALSE),MATCH(ADDRESS(ROW(),COLUMN(),4),'Country Model'!$9:$9,FALSE),4)) -> 0.5 | G50: =INDIRECT("'Country Data'!"&ADDRESS(MATCH($F$5,'Country Data'!$A:$A,FALSE),MATCH(ADDRESS(ROW(),COLUMN(),4),'Country Model'!$9:$9,FALSE),4)) -> #N/A
D51: Protective effect (proportion reduction in risk) - OCV alone | F51: =INDIRECT("'Country Data'!"&ADDRESS(MATCH($F$5,'Country Data'!$A:$A,FALSE),MATCH(ADDRESS(ROW(),COLUMN(),4),'Country Model'!$9:$9,FALSE),4)) -> 0.76 | G51: =INDIRECT("'Country Data'!"&ADDRESS(MATCH($F$5,'Country Data'!$A:$A,FALSE),MATCH(ADDRESS(ROW(),COLUMN(),4),'Country Model'!$9:$9,FALSE),4)) -> #N/A
D52: Protective effect (proportion reduction in risk) - WASH & OCV together | F52: =INDIRECT("'Country Data'!"&ADDRESS(MATCH($F$5,'Country Data'!$A:$A,FALSE),MATCH(ADDRESS(ROW(),COLUMN(),4),'Country Model'!$9:$9,FALSE),4)) -> 0.76
D53: Protective effect (proportion reduction in risk) - WASH & OCV & CM | F53: =INDIRECT("'Country Data'!"&ADDRESS(MATCH($F$5,'Country Data'!$A:$A,FALSE),MATCH(ADDRESS(ROW(),COLUMN(),4),'Country Model'!$9:$9,FALSE),4)) -> 0
C54: RESPONSE TO CHOLERA OUTBREAKS
D55: Average number of OCV doses given per person in outbreak | F55: 1 | G55: =INDIRECT("'Country Data'!"&ADDRESS(MATCH($F$5,'Country Data'!$A:$A,FALSE),MATCH(ADDRESS(ROW(),COLUMN(),4),'Country Model'!$9:$9,FALSE),4)) -> #N/A
D56: % population in outbreak covered with emergency WASH | F56: =INDIRECT("'Country Data'!"&ADDRESS(MATCH($F$5,'Country Data'!$A:$A,FALSE),MATCH(ADDRESS(ROW(),COLUMN(),4),'Country Model'!$9:$9,FALSE),4)) -> 0.9 | G56: =INDIRECT("'Country Data'!"&ADDRESS(MATCH($F$5,'Country Data'!$A:$A,FALSE),MATCH(ADDRESS(ROW(),COLUMN(),4),'Country Model'!$9:$9,FALSE),4)) -> 0.9
D57: % population in outbreak hotspot receiving emergency OCV during outbreak | F57: =INDIRECT("'Country Data'!"&ADDRESS(MATCH($F$5,'Country Data'!$A:$A,FALSE),MATCH(ADDRESS(ROW(),COLUMN(),4),'Country Model'!$9:$9,FALSE),4)) -> 0.714 | G57: =INDIRECT("'Country Data'!"&ADDRESS(MATCH($F$5,'Country Data'!$A:$A,FALSE),MATCH(ADDRESS(ROW(),COLUMN(),4),'Country Model'!$9:$9,FALSE),4)) -> 0.714
D58: % cases in outbreak needing intensive medical care (e.g. hospital admission) | F58: 0.2 | G58: 0.2
D59: % cases in outbreak covered with ORS case management | F59: =INDIRECT("'Country Data'!"&ADDRESS(MATCH($F$5,'Country Data'!$A:$A,FALSE),MATCH(ADDRESS(ROW(),COLUMN(),4),'Country Model'!$9:$9,FALSE),4)) -> 0.8 | G59: =INDIRECT("'Country Data'!"&ADDRESS(MATCH($F$5,'Country Data'!$A:$A,FALSE),MATCH(ADDRESS(ROW(),COLUMN(),4),'Country Model'!$9:$9,FALSE),4)) -> 0.8
D60: % cases in outbreak covered with intensive case management | F60: =INDIRECT("'Country Data'!"&ADDRESS(MATCH($F$5,'Country Data'!$A:$A,FALSE),MATCH(ADDRESS(ROW(),COLUMN(),4),'Country Model'!$9:$9,FALSE),4)) -> 0.8 | G60: =INDIRECT("'Country Data'!"&ADDRESS(MATCH($F$5,'Country Data'!$A:$A,FALSE),MATCH(ADDRESS(ROW(),COLUMN(),4),'Country Model'!$9:$9,FALSE),4)) -> 0.8
D61: Under CM strengthening, % population in outbreak receiving needed CM | F61: =INDIRECT("'Country Data'!"&ADDRESS(MATCH($F$5,'Country Data'!$A:$A,FALSE),MATCH(ADDRESS(ROW(),COLUMN(),4),'Country Model'!$9:$9,FALSE),4)) -> 1 | G61: =INDIRECT("'Country Data'!"&ADDRESS(MATCH($F$5,'Country Data'!$A:$A,FALSE),MATCH(ADDRESS(ROW(),COLUMN(),4),'Country Model'!$9:$9,FALSE),4)) -> 1
D62: ORS (oral rehydration salts) costs per cholera case (US$ in 2025 prices) | F62: 2.5 | G62: 2.5
D63: Cholera Case Management costs (routine) (USD in 2025 prices) | F63: 50 | G63: 50
D64: Cholera Case Management costs (intensive) (USD in 2025 prices) | F64: 150 | G64: 150
D65: Days of productive time lost per adult cholera case | F65: =INDIRECT("'Country Data'!"&ADDRESS(MATCH($F$5,'Country Data'!$A:$A,FALSE),MATCH(ADDRESS(ROW(),COLUMN(),4),'Country Model'!$9:$9,FALSE),4)) -> 4 | G65: =INDIRECT("'Country Data'!"&ADDRESS(MATCH($F$5,'Country Data'!$A:$A,FALSE),MATCH(ADDRESS(ROW(),COLUMN(),4),'Country Model'!$9:$9,FALSE),4)) -> 4
C66: HEALTH ASSUMPTIONS FOR DIARRHEAL DISEASE
D67: % attribution of diarrhea cases to poor WASH | F67: =INDIRECT("'Country Data'!"&ADDRESS(MATCH($F$5,'Country Data'!$A:$A,FALSE),MATCH(ADDRESS(ROW(),COLUMN(),4),'Country Model'!$9:$9,FALSE),4)) -> 0.56 | G67: =INDIRECT("'Country Data'!"&ADDRESS(MATCH($F$5,'Country Data'!$A:$A,FALSE),MATCH(ADDRESS(ROW(),COLUMN(),4),'Country Model'!$9:$9,FALSE),4)) -> #N/A
D68: % reduction of WASH-related diarrhea cases from implementing basic WASH | F68: =INDIRECT("'Country Data'!"&ADDRESS(MATCH($F$5,'Country Data'!$A:$A,FALSE),MATCH(ADDRESS(ROW(),COLUMN(),4),'Country Model'!$9:$9,FALSE),4)) -> 0.5 | G68: =INDIRECT("'Country Data'!"&ADDRESS(MATCH($F$5,'Country Data'!$A:$A,FALSE),MATCH(ADDRESS(ROW(),COLUMN(),4),'Country Model'!$9:$9,FALSE),4)) -> #N/A
D69: Diarrhea prevalence rate, per population age group
E70: 0-4 yr | F70: =INDIRECT("'Country Data'!"&ADDRESS(MATCH($F$5,'Country Data'!$A:$A,FALSE),MATCH(ADDRESS(ROW(),COLUMN(),4),'Country Model'!$9:$9,FALSE),4)) -> 0.19 | G70: =INDIRECT("'Country Data'!"&ADDRESS(MATCH($F$5,'Country Data'!$A:$A,FALSE),MATCH(ADDRESS(ROW(),COLUMN(),4),'Country Model'!$9:$9,FALSE),4)) -> 0.19
E71: 5-14 yr | F71: =INDIRECT("'Country Data'!"&ADDRESS(MATCH($F$5,'Country Data'!$A:$A,FALSE),MATCH(ADDRESS(ROW(),COLUMN(),4),'Country Model'!$9:$9,FALSE),4)) -> 0.095 | G71: =INDIRECT("'Country Data'!"&ADDRESS(MATCH($F$5,'Country Data'!$A:$A,FALSE),MATCH(ADDRESS(ROW(),COLUMN(),4),'Country Model'!$9:$9,FALSE),4)) -> 0.095
E72: 15+ yr | F72: =INDIRECT("'Country Data'!"&ADDRESS(MATCH($F$5,'Country Data'!$A:$A,FALSE),MATCH(ADDRESS(ROW(),COLUMN(),4),'Country Model'!$9:$9,FALSE),4)) -> 0.0475 | G72: =INDIRECT("'Country Data'!"&ADDRESS(MATCH($F$5,'Country Data'!$A:$A,FALSE),MATCH(ADDRESS(ROW(),COLUMN(),4),'Country Model'!$9:$9,FALSE),4)) -> 0.0475
D73: Treatment seeking rate (% diarrhea cases to any formal health facility) | F73: =INDIRECT("'Country Data'!"&ADDRESS(MATCH($F$5,'Country Data'!$A:$A,FALSE),MATCH(ADDRESS(ROW(),COLUMN(),4),'Country Model'!$9:$9,FALSE),4)) -> 0.552 | G73: =INDIRECT("'Country Data'!"&ADDRESS(MATCH($F$5,'Country Data'!$A:$A,FALSE),MATCH(ADDRESS(ROW(),COLUMN(),4),'Country Model'!$9:$9,FALSE),4)) -> 0.633
D74: Average cost per case seeking treatment for diarrhea (US$ in 2018 prices) | F74: =INDIRECT("'Country Data'!"&ADDRESS(MATCH($F$5,'Country Data'!$A:$A,FALSE),MATCH(ADDRESS(ROW(),COLUMN(),4),'Country Model'!$9:$9,FALSE),4)) -> 1.8860797 | G74: =INDIRECT("'Country Data'!"&ADDRESS(MATCH($F$5,'Country Data'!$A:$A,FALSE),MATCH(ADDRESS(ROW(),COLUMN(),4),'Country Model'!$9:$9,FALSE),4)) -> 1.8860797
D75: % diarrhea cases treated with ORS | F75: =INDIRECT("'Country Data'!"&ADDRESS(MATCH($F$5,'Country Data'!$A:$A,FALSE),MATCH(ADDRESS(ROW(),COLUMN(),4),'Country Model'!$9:$9,FALSE),4)) -> 0.8 | G75: =INDIRECT("'Country Data'!"&ADDRESS(MATCH($F$5,'Country Data'!$A:$A,FALSE),MATCH(ADDRESS(ROW(),COLUMN(),4),'Country Model'!$9:$9,FALSE),4)) -> 0.8
D76: Average no. of days off work for adults with diarrhea | F76: =INDIRECT("'Country Data'!"&ADDRESS(MATCH($F$5,'Country Data'!$A:$A,FALSE),MATCH(ADDRESS(ROW(),COLUMN(),4),'Country Model'!$9:$9,FALSE),4)) -> 2 | G76: =INDIRECT("'Country Data'!"&ADDRESS(MATCH($F$5,'Country Data'!$A:$A,FALSE),MATCH(ADDRESS(ROW(),COLUMN(),4),'Country Model'!$9:$9,FALSE),4)) -> 2
D77: Number of diarrhea deaths nationally | F77: 580 | G77: =INDIRECT("'Country Data'!"&ADDRESS(MATCH($F$5,'Country Data'!$A:$A,FALSE),MATCH(ADDRESS(ROW(),COLUMN(),4),'Country Model'!$9:$9,FALSE),4)) -> 3525.9638
C78: WASH COVERAGE - Additional details for estimating time savings
D79: Water - percent (%) with 'limited' coverage - Year 0 | F79: 0.34 | G79: 0.23 | J79: 2024/2025 Malawi WASH Budget Brief - UNICEF
D80: Water - percent (%) with unimproved coverage - Year 0 | F80: =INDIRECT("'Country Data'!"&ADDRESS(MATCH($F$5,'Country Data'!$A:$A,FALSE),MATCH(ADDRESS(ROW(),COLUMN(),4),'Country Model'!$9:$9,FALSE),4)) -> 0.04 | G80: 0.06 | J80: 2024/2025 Malawi WASH Budget Brief - UNICEF
D81: Water - percent (%) using surface water - Year 0 | F81: =INDIRECT("'Country Data'!"&ADDRESS(MATCH($F$5,'Country Data'!$A:$A,FALSE),MATCH(ADDRESS(ROW(),COLUMN(),4),'Country Model'!$9:$9,FALSE),4)) -> 0 | G81: 0.02 | J81: 2024/2025 Malawi WASH Budget Brief - UNICEF
D82: Sanitation - percent (%) using open defecation - Year 0 | F82: 0.02 | G82: 0.07 | J82: The WHO/UNICEF Joint Monitoring Programme (JMP) 2022 Data
D83: Sanitation - percent (%) using shared facility - Year 0 | F83: 0.39 | G83: 0.24 | J83: The WHO/UNICEF Joint Monitoring Programme (JMP) 2022 Data
C84: TIME SAVINGS AFTER RECEIVING BASIC WATER OR SANITATION SERVICE
D85: Water - from limited coverage to basic - hours saved per HH per day | F85: =INDIRECT("'Country Data'!"&ADDRESS(MATCH($F$5,'Country Data'!$A:$A,FALSE),MATCH(ADDRESS(ROW(),COLUMN(),4),'Country Model'!$9:$9,FALSE),4)) -> 0.67 | G85: =INDIRECT("'Country Data'!"&ADDRESS(MATCH($F$5,'Country Data'!$A:$A,FALSE),MATCH(ADDRESS(ROW(),COLUMN(),4),'Country Model'!$9:$9,FALSE),4)) -> 1
D86: Water - from unimproved coverage to basic - hours saved per HH per day | F86: =INDIRECT("'Country Data'!"&ADDRESS(MATCH($F$5,'Country Data'!$A:$A,FALSE),MATCH(ADDRESS(ROW(),COLUMN(),4),'Country Model'!$9:$9,FALSE),4)) -> 0.33 | G86: =INDIRECT("'Country Data'!"&ADDRESS(MATCH($F$5,'Country Data'!$A:$A,FALSE),MATCH(ADDRESS(ROW(),COLUMN(),4),'Country Model'!$9:$9,FALSE),4)) -> 0.5
D87: Water - from surface sources to basic - hours saved per HH per day | F87: =INDIRECT("'Country Data'!"&ADDRESS(MATCH($F$5,'Country Data'!$A:$A,FALSE),MATCH(ADDRESS(ROW(),COLUMN(),4),'Country Model'!$9:$9,FALSE),4)) -> 0.33 | G87: =INDIRECT("'Country Data'!"&ADDRESS(MATCH($F$5,'Country Data'!$A:$A,FALSE),MATCH(ADDRESS(ROW(),COLUMN(),4),'Country Model'!$9:$9,FALSE),4)) -> 0.33
D88: Sanitation - from OD to basic - hours saved per person per day | F88: =INDIRECT("'Country Data'!"&ADDRESS(MATCH($F$5,'Country Data'!$A:$A,FALSE),MATCH(ADDRESS(ROW(),COLUMN(),4),'Country Model'!$9:$9,FALSE),4)) -> 0.33 | G88: =INDIRECT("'Country Data'!"&ADDRESS(MATCH($F$5,'Country Data'!$A:$A,FALSE),MATCH(ADDRESS(ROW(),COLUMN(),4),'Country Model'!$9:$9,FALSE),4)) -> 0.5
D89: Sanitation - from shared facility to basic - hours saved per person per day | F89: =INDIRECT("'Country Data'!"&ADDRESS(MATCH($F$5,'Country Data'!$A:$A,FALSE),MATCH(ADDRESS(ROW(),COLUMN(),4),'Country Model'!$9:$9,FALSE),4)) -> 0.17 | G89: =INDIRECT("'Country Data'!"&ADDRESS(MATCH($F$5,'Country Data'!$A:$A,FALSE),MATCH(ADDRESS(ROW(),COLUMN(),4),'Country Model'!$9:$9,FALSE),4)) -> 0.17
C94: Abbreviations
C95: CM | E95: Case management
C96: GDP | E96: Gross Domestic Product
C97: HH | E97: Household
C98: O&M | E98: Operations and maintenance
C99: OCV | E99: Oral cholera vaccine
C100: ORS | E100: Oral rehydration salts
C101: USD | E101: United States Dollars

Sheet Summary
A1: Step 3: Summary of the outcomes
A3: =UPPER('User Inputs'!F5 & " CHOLERA INVESTMENT REPORT") -> MALAWI CHOLERA INVESTMENT REPORT
B4: From | C4: ='User Inputs'!$F$9 -> 2026 | D4: to | E4: ='User Inputs'!$F$10+$C$4-1 -> 2030
A6: In USD
A7: All values are rounded | B7: Total | C7: =C4 -> 2026 | D7: =IF(AND(C7+1<=$E$4,C7+1>$C$4),C7+1,0) -> 2027 | E7: =IF(AND(D7+1<=$E$4,D7+1>$C$4),D7+1,0) -> 2028 | F7: =IF(AND(E7+1<=$E$4,E7+1>$C$4),E7+1,0) -> 2029 | G7: =IF(AND(F7+1<=$E$4,F7+1>$C$4),F7+1,0) -> 2030 | H7: =IF(AND(G7+1<=$E$4,G7+1>$C$4),G7+1,0) -> 0 | I7: =IF(AND(H7+1<=$E$4,H7+1>$C$4),H7+1,0) -> 0 | J7: =IF(AND(I7+1<=$E$4,I7+1>$C$4),I7+1,0) -> 0 | K7: =IF(AND(J7+1<=$E$4,J7+1>$C$4),J7+1,0) -> 0 | ... T7: =IF(AND(S7+1<=$E$4,S7+1>$C$4),S7+1,0) -> 0
A8: Estimated costs from implementing the Roadmap (USD) | B8: =ROUND(SUM(C8:U8),-6) -> 335000000 | C8: =IF(C7>2021,HLOOKUP(C$7,Tables!$L$5:$AD$10,Tables!$AG9,FALSE)*-1,"") -> 0 | D8: =IF(D7>2021,HLOOKUP(D$7,Tables!$L$5:$AD$10,Tables!$AG9,FALSE)*-1,"") -> 0 | E8: =IF(E7>2021,HLOOKUP(E$7,Tables!$L$5:$AD$10,Tables!$AG9,FALSE)*-1,"") -> 0 | F8: =IF(F7>2021,HLOOKUP(F$7,Tables!$L$5:$AD$10,Tables!$AG10,FALSE)*-1,"") -> 1.65241e+08 | G8: =IF(G7>2021,HLOOKUP(G$7,Tables!$L$5:$AD$10,Tables!$AG10,FALSE)*-1,"") -> 1.6977448e+08 | H8: =IF(H7>2021,HLOOKUP(H$7,Tables!$L$5:$AD$10,Tables!$AG10,FALSE)*-1,"") | I8: =IF(I7>2021,HLOOKUP(I$7,Tables!$L$5:$AD$10,Tables!$AG10,FALSE)*-1,"") | J8: =IF(J7>2021,HLOOKUP(J$7,Tables!$L$5:$AD$10,Tables!$AG10,FALSE)*-1,"") | K8: =IF(K7>2021,HLOOKUP(K$7,Tables!$L$5:$AD$10,Tables!$AG10,FALSE)*-1,"") | L8: =IF(L7>2021,HLOOKUP(L$7,Tables!$L$5:$AD$10,Tables!$AG10,FALSE)*-1,"") | M8: =IF(M7>2021,HLOOKUP(M$7,Tables!$L$5:$AD$10,Tables!$AG10,FALSE)*-1,"") | ... T8: =IF(T7>2021,HLOOKUP(T$7,Tables!$L$5:$AD$10,Tables!$AG10,FALSE)*-1,"")
A9: Estimated benefits from implementing the Roadmap | B9: =ROUND(SUM(C9:U9),-6) -> 1697000000 | C9: =IF(C7>2021,HLOOKUP(C$7,Tables!$L$5:$AD$20,Tables!$AG20,FALSE),"") -> 82659769 | D9: =IF(D7>2021,HLOOKUP(D$7,Tables!$L$5:$AD$20,Tables!$AG20,FALSE),"") -> 85001360 | E9: =IF(E7>2021,HLOOKUP(E$7,Tables!$L$5:$AD$20,Tables!$AG20,FALSE),"") -> 87414683 | F9: =IF(F7>2021,HLOOKUP(F$7,Tables!$L$5:$AD$22,Tables!$AG22,FALSE),"") -> 7.1265253e+08 | G9: =IF(G7>2021,HLOOKUP(G$7,Tables!$L$5:$AD$22,Tables!$AG22,FALSE),"") -> 7.2934666e+08 | H9: =IF(H7>2021,HLOOKUP(H$7,Tables!$L$5:$AD$22,Tables!$AG22,FALSE),"") | I9: =IF(I7>2021,HLOOKUP(I$7,Tables!$L$5:$AD$22,Tables!$AG22,FALSE),"") | J9: =IF(J7>2021,HLOOKUP(J$7,Tables!$L$5:$AD$22,Tables!$AG22,FALSE),"") | K9: =IF(K7>2021,HLOOKUP(K$7,Tables!$L$5:$AD$22,Tables!$AG22,FALSE),"") | L9: =IF(L7>2021,HLOOKUP(L$7,Tables!$L$5:$AD$22,Tables!$AG22,FALSE),"") | M9: =IF(M7>2021,HLOOKUP(M$7,Tables!$L$5:$AD$22,Tables!$AG22,FALSE),"") | ... T9: =IF(T7>2021,HLOOKUP(T$7,Tables!$L$5:$AD$22,Tables!$AG22,FALSE),"")
A10: Estimated population benefiting from Roadmap interventions | B10: =ROUND(SUM(C10:U10),-6) -> 19000000 | C10: =IF(C7>2021,HLOOKUP(C$7,Tables!$L$5:$AD$31,Tables!$AG30,FALSE),"") -> 0 | D10: =IF(D7>2021,HLOOKUP(D$7,Tables!$L$5:$AD$31,Tables!$AG30,FALSE),"") -> 8878485.7 | E10: =IF(E7>2021,HLOOKUP(E$7,Tables!$L$5:$AD$31,Tables!$AG30,FALSE),"") -> 0 | F10: =IF(F7>2021,HLOOKUP(F$7,Tables!$L$5:$AD$31,Tables!$AG31,FALSE),"") -> 287512.68 | G10: =IF(G7>2021,HLOOKUP(G$7,Tables!$L$5:$AD$31,Tables!$AG31,FALSE),"") -> 9907599.7 | H10: =IF(H7>2021,HLOOKUP(H$7,Tables!$L$5:$AD$31,Tables!$AG31,FALSE),"") | I10: =IF(I7>2021,HLOOKUP(I$7,Tables!$L$5:$AD$31,Tables!$AG31,FALSE),"") | J10: =IF(J7>2021,HLOOKUP(J$7,Tables!$L$5:$AD$31,Tables!$AG31,FALSE),"") | K10: =IF(K7>2021,HLOOKUP(K$7,Tables!$L$5:$AD$31,Tables!$AG31,FALSE),"") | L10: =IF(L7>2021,HLOOKUP(L$7,Tables!$L$5:$AD$31,Tables!$AG31,FALSE),"") | M10: =IF(M7>2021,HLOOKUP(M$7,Tables!$L$5:$AD$31,Tables!$AG31,FALSE),"") | ... T10: =IF(T7>2021,HLOOKUP(T$7,Tables!$L$5:$AD$31,Tables!$AG31,FALSE),"")
A11: Estimated cholera cases averted | B11: =SUM(C11:U11) -> 300309.09 | C11: =IF(C$7>2021,HLOOKUP(C$7,Tables!$L$5:$AD$103,Tables!$AG50,FALSE)-HLOOKUP(C$7,Tables!$L$5:$AD$103,Tables!$AG53,FALSE),"") -> 48760.623 | D11: =IF(D$7>2021,HLOOKUP(D$7,Tables!$L$5:$AD$103,Tables!$AG50,FALSE)-HLOOKUP(D$7,Tables!$L$5:$AD$103,Tables!$AG53,FALSE),"") -> 50137.304 | E11: =IF(E$7>2021,HLOOKUP(E$7,Tables!$L$5:$AD$103,Tables!$AG50,FALSE)-HLOOKUP(E$7,Tables!$L$5:$AD$103,Tables!$AG53,FALSE),"") -> 51555.995 | F11: =IF(F$7>2021,HLOOKUP(F$7,Tables!$L$5:$AD$103,Tables!$AG50,FALSE)-HLOOKUP(F$7,Tables!$L$5:$AD$103,Tables!$AG51,FALSE),"") -> 73877.667 | G11: =IF(G$7>2021,HLOOKUP(G$7,Tables!$L$5:$AD$103,Tables!$AG50,FALSE)-HLOOKUP(G$7,Tables!$L$5:$AD$103,Tables!$AG51,FALSE),"") -> 75977.503 | H11: =IF(H$7>2021,HLOOKUP(H$7,Tables!$L$5:$AD$103,Tables!$AG50,FALSE)-HLOOKUP(H$7,Tables!$L$5:$AD$103,Tables!$AG51,FALSE),"") | I11: =IF(I$7>2021,HLOOKUP(I$7,Tables!$L$5:$AD$103,Tables!$AG50,FALSE)-HLOOKUP(I$7,Tables!$L$5:$AD$103,Tables!$AG51,FALSE),"") | J11: =IF(J$7>2021,HLOOKUP(J$7,Tables!$L$5:$AD$103,Tables!$AG50,FALSE)-HLOOKUP(J$7,Tables!$L$5:$AD$103,Tables!$AG51,FALSE),"") | K11: =IF(K$7>2021,HLOOKUP(K$7,Tables!$L$5:$AD$103,Tables!$AG50,FALSE)-HLOOKUP(K$7,Tables!$L$5:$AD$103,Tables!$AG51,FALSE),"") | L11: =IF(L$7>2021,HLOOKUP(L$7,Tables!$L$5:$AD$103,Tables!$AG50,FALSE)-HLOOKUP(L$7,Tables!$L$5:$AD$103,Tables!$AG51,FALSE),"") | M11: =IF(M$7>2021,HLOOKUP(M$7,Tables!$L$5:$AD$103,Tables!$AG50,FALSE)-HLOOKUP(M$7,Tables!$L$5:$AD$103,Tables!$AG51,FALSE),"") | ... T11: =IF(T$7>2021,HLOOKUP(T$7,Tables!$L$5:$AD$103,Tables!$AG50,FALSE)-HLOOKUP(T$7,Tables!$L$5:$AD$103,Tables!$AG51,FALSE),"")
A12: Estimated cholera deaths averted | B12: =SUM(C12:U12) -> 8746.6177 | C12: =IF(C$7>2021,HLOOKUP(C$7,Tables!$L$5:$AD$103,Tables!$AG57,FALSE)-HLOOKUP(C$7,Tables!$L$5:$AD$103,Tables!$AG60,FALSE),"") -> 1421.5752 | D12: =IF(D$7>2021,HLOOKUP(D$7,Tables!$L$5:$AD$103,Tables!$AG57,FALSE)-HLOOKUP(D$7,Tables!$L$5:$AD$103,Tables!$AG60,FALSE),"") -> 1461.0789 | E12: =IF(E$7>2021,HLOOKUP(E$7,Tables!$L$5:$AD$103,Tables!$AG57,FALSE)-HLOOKUP(E$7,Tables!$L$5:$AD$103,Tables!$AG60,FALSE),"") -> 1501.7657 | F12: =IF(F$7>2021,HLOOKUP(F$7,Tables!$L$5:$AD$103,Tables!$AG57,FALSE)-HLOOKUP(F$7,Tables!$L$5:$AD$103,Tables!$AG58,FALSE),"") -> 2151.0214 | G12: =IF(G$7>2021,HLOOKUP(G$7,Tables!$L$5:$AD$103,Tables!$AG57,FALSE)-HLOOKUP(G$7,Tables!$L$5:$AD$103,Tables!$AG58,FALSE),"") -> 2211.1764 | H12: =IF(H$7>2021,HLOOKUP(H$7,Tables!$L$5:$AD$103,Tables!$AG57,FALSE)-HLOOKUP(H$7,Tables!$L$5:$AD$103,Tables!$AG58,FALSE),"") | I12: =IF(I$7>2021,HLOOKUP(I$7,Tables!$L$5:$AD$103,Tables!$AG57,FALSE)-HLOOKUP(I$7,Tables!$L$5:$AD$103,Tables!$AG58,FALSE),"") | J12: =IF(J$7>2021,HLOOKUP(J$7,Tables!$L$5:$AD$103,Tables!$AG57,FALSE)-HLOOKUP(J$7,Tables!$L$5:$AD$103,Tables!$AG58,FALSE),"") | K12: =IF(K$7>2021,HLOOKUP(K$7,Tables!$L$5:$AD$103,Tables!$AG57,FALSE)-HLOOKUP(K$7,Tables!$L$5:$AD$103,Tables!$AG58,FALSE),"") | L12: =IF(L$7>2021,HLOOKUP(L$7,Tables!$L$5:$AD$103,Tables!$AG57,FALSE)-HLOOKUP(L$7,Tables!$L$5:$AD$103,Tables!$AG58,FALSE),"") | M12: =IF(M$7>2021,HLOOKUP(M$7,Tables!$L$5:$AD$103,Tables!$AG57,FALSE)-HLOOKUP(M$7,Tables!$L$5:$AD$103,Tables!$AG58,FALSE),"") | ... T12: =IF(T$7>2021,HLOOKUP(T$7,Tables!$L$5:$AD$103,Tables!$AG57,FALSE)-HLOOKUP(T$7,Tables!$L$5:$AD$103,Tables!$AG58,FALSE),"")
A13: Estimated diarrhea cases averted | B13: =SUM(C13:U13) -> 1.4083616e+08 | C13: 0 | D13: 0 | E13: 0 | F13: =IF(F$7>2021,HLOOKUP(F$7,Tables!$L$5:$AD$103,Tables!$AG64,FALSE)-HLOOKUP(F$7,Tables!$L$5:$AD$103,Tables!$AG65,FALSE),"") -> 70344951 | G13: =IF(G$7>2021,HLOOKUP(G$7,Tables!$L$5:$AD$103,Tables!$AG64,FALSE)-HLOOKUP(G$7,Tables!$L$5:$AD$103,Tables!$AG65,FALSE),"") -> 70491211 | H13: =IF(H$7>2021,HLOOKUP(H$7,Tables!$L$5:$AD$103,Tables!$AG64,FALSE)-HLOOKUP(H$7,Tables!$L$5:$AD$103,Tables!$AG65,FALSE),"") | I13: =IF(I$7>2021,HLOOKUP(I$7,Tables!$L$5:$AD$103,Tables!$AG64,FALSE)-HLOOKUP(I$7,Tables!$L$5:$AD$103,Tables!$AG65,FALSE),"") | J13: =IF(J$7>2021,HLOOKUP(J$7,Tables!$L$5:$AD$103,Tables!$AG64,FALSE)-HLOOKUP(J$7,Tables!$L$5:$AD$103,Tables!$AG65,FALSE),"") | K13: =IF(K$7>2021,HLOOKUP(K$7,Tables!$L$5:$AD$103,Tables!$AG64,FALSE)-HLOOKUP(K$7,Tables!$L$5:$AD$103,Tables!$AG65,FALSE),"") | L13: =IF(L$7>2021,HLOOKUP(L$7,Tables!$L$5:$AD$103,Tables!$AG64,FALSE)-HLOOKUP(L$7,Tables!$L$5:$AD$103,Tables!$AG65,FALSE),"") | M13: =IF(M$7>2021,HLOOKUP(M$7,Tables!$L$5:$AD$103,Tables!$AG64,FALSE)-HLOOKUP(M$7,Tables!$L$5:$AD$103,Tables!$AG65,FALSE),"") | ... T13: =IF(T$7>2021,HLOOKUP(T$7,Tables!$L$5:$AD$103,Tables!$AG64,FALSE)-HLOOKUP(T$7,Tables!$L$5:$AD$103,Tables!$AG65,FALSE),"")
A14: Estimated diarrhea deaths averted | B14: =SUM(C14:U14) -> 4219.5633 | C14: 0 | D14: 0 | E14: 0 | F14: =IF(F$7>2021,HLOOKUP(F$7,Tables!$L$5:$AD$103,Tables!$AG68,FALSE)-HLOOKUP(F$7,Tables!$L$5:$AD$103,Tables!$AG69,FALSE),"") -> 2079.5574 | G14: =IF(G$7>2021,HLOOKUP(G$7,Tables!$L$5:$AD$103,Tables!$AG68,FALSE)-HLOOKUP(G$7,Tables!$L$5:$AD$103,Tables!$AG69,FALSE),"") -> 2140.0059 | H14: =IF(H$7>2021,HLOOKUP(H$7,Tables!$L$5:$AD$103,Tables!$AG68,FALSE)-HLOOKUP(H$7,Tables!$L$5:$AD$103,Tables!$AG69,FALSE),"") | I14: =IF(I$7>2021,HLOOKUP(I$7,Tables!$L$5:$AD$103,Tables!$AG68,FALSE)-HLOOKUP(I$7,Tables!$L$5:$AD$103,Tables!$AG69,FALSE),"") | J14: =IF(J$7>2021,HLOOKUP(J$7,Tables!$L$5:$AD$103,Tables!$AG68,FALSE)-HLOOKUP(J$7,Tables!$L$5:$AD$103,Tables!$AG69,FALSE),"") | K14: =IF(K$7>2021,HLOOKUP(K$7,Tables!$L$5:$AD$103,Tables!$AG68,FALSE)-HLOOKUP(K$7,Tables!$L$5:$AD$103,Tables!$AG69,FALSE),"") | L14: =IF(L$7>2021,HLOOKUP(L$7,Tables!$L$5:$AD$103,Tables!$AG68,FALSE)-HLOOKUP(L$7,Tables!$L$5:$AD$103,Tables!$AG69,FALSE),"") | M14: =IF(M$7>2021,HLOOKUP(M$7,Tables!$L$5:$AD$103,Tables!$AG68,FALSE)-HLOOKUP(M$7,Tables!$L$5:$AD$103,Tables!$AG69,FALSE),"") | ... T14: =IF(T$7>2021,HLOOKUP(T$7,Tables!$L$5:$AD$103,Tables!$AG68,FALSE)-HLOOKUP(T$7,Tables!$L$5:$AD$103,Tables!$AG69,FALSE),"")
A16: Overall estimated benefit per US dollar invested of implementing Roadmap for the full time period:
A17: ="US$1 invested in the Roadmap results in US$"& ROUND(Tables!AE22/Tables!AE10*-1,0) &" in benefits" -> US$1 invested in the Roadmap results in US$4 in benefits | C17: FIXED TIME PERIOD 2022-2040 ---> Total Benefits / Total Costs (WASH included in all years)
A18: ="US$1 invested in the Roadmap results in US$"& ROUND(B9/B8,0) &" in benefits" -> US$1 invested in the Roadmap results in US$5 in benefits | C18: VARIABLE TIME PERIOD (based on user input) --> Total Benefits / Total Costs time period selected [WASH benefits & costs only included from 2026 onwards]
A20: Assumption
A21: First 3 years, key intervention is OCV to give time to plan and implement WASH

Sheet Tables
D2: -1 | L2: Year 1 | M2: Year 2 | N2: Year 3 | O2: Year 4 | P2: Year 5
D3: WASH Ramp up | L3: 0.1 | M3: 0.3 | N3: 0.5 | O3: 0.75 | P3: 1 | AG3: Hlookup
E5: 2015 | F5: 2016 | G5: 2017 | H5: 2018 | I5: 2019 | J5: 2020 | K5: 2021 | L5: 2022 | M5: 2023 | N5: 2024 | O5: 2025 | P5: 2026 | Q5: 2027 | R5: 2028 | S5: 2029 | T5: 2030 | U5: 2031 | V5: 2032 | W5: 2033 | X5: 2034 | Y5: 2035 | Z5: 2036 | AA5: 2037 | AB5: 2038 | AC5: 2039 | AD5: 2040 | AE5: TOTAL | AG5: 1
B6: 1. Cost - Benefit (NOTE DOES NOT INCLDUE SURVEILLANCE) | AG6: =AG5+1 -> 2
D7: Cost: WASH Capital | E7: =(SUM('Country Model'!E34:E36)+SUM('Country Model'!AE34:AE36))*-1 -> 0 | F7: =(SUM('Country Model'!F34:F36)+SUM('Country Model'!AF34:AF36))*-1 -> 0 | G7: =(SUM('Country Model'!G34:G36)+SUM('Country Model'!AG34:AG36))*-1 -> 0 | H7: =(SUM('Country Model'!H34:H36)+SUM('Country Model'!AH34:AH36))*-1 -> -91852303 | I7: =(SUM('Country Model'!I34:I36)+SUM('Country Model'!AI34:AI36))*-1 -> -91852303 | J7: =(SUM('Country Model'!J34:J36)+SUM('Country Model'!AJ34:AJ36))*-1 -> -91852303 | K7: =(SUM('Country Model'!K34:K36)+SUM('Country Model'!AK34:AK36))*-1 -> -91852303 | L7: =(SUM('Country Model'!L34:L36)+SUM('Country Model'!AL34:AL36))*-1 -> -91852303 | ... AD7: =(SUM('Country Model'!AD34:AD36)+SUM('Country Model'!BD34:BD36))*-1 -> -40244309 | AE7: =SUM(E7:AD7) -> -1.163225e+09 | AG7: =AG6+1 -> 3
D8: Cost: WASH O&M | E8: =(SUM('Country Model'!E38:E40)+SUM('Country Model'!AE38:AE40))*-1 -> 0 | F8: =(SUM('Country Model'!F38:F40)+SUM('Country Model'!AF38:AF40))*-1 -> 0 | G8: =(SUM('Country Model'!G38:G40)+SUM('Country Model'!AG38:AG40))*-1 -> 0 | H8: =(SUM('Country Model'!H38:H40)+SUM('Country Model'!AH38:AH40))*-1 -> -29650577 | I8: =(SUM('Country Model'!I38:I40)+SUM('Country Model'!AI38:AI40))*-1 -> -36866230 | J8: =(SUM('Country Model'!J38:J40)+SUM('Country Model'!AJ38:AJ40))*-1 -> -51761203 | K8: =(SUM('Country Model'!K38:K40)+SUM('Country Model'!AK38:AK40))*-1 -> -67421233 | L8: =(SUM('Country Model'!L38:L40)+SUM('Country Model'!AL38:AL40))*-1 -> -83878351 | ... AD8: =(SUM('Country Model'!AD38:AD40)+SUM('Country Model'!BD38:BD40))*-1 -> -1.8297577e+08 | AE8: =SUM(E8:AD8) -> -2.901719e+09 | AG8: =AG7+1 -> 4
D9: Cost: OCV Campaigns, Surveillance | E9: =('Country Model'!E42+'Country Model'!AE42)*-1 -> 0 | F9: =('Country Model'!F42+'Country Model'!AF42)*-1 -> 0 | G9: =('Country Model'!G42+'Country Model'!AG42)*-1 -> 0 | H9: =('Country Model'!H42+'Country Model'!AH42)*-1 -> -41243186 | I9: =('Country Model'!I42+'Country Model'!AI42)*-1 -> 0 | J9: =('Country Model'!J42+'Country Model'!AJ42)*-1 -> 0 | K9: =('Country Model'!K42+'Country Model'!AK42)*-1 -> -44597074 | L9: =('Country Model'!L42+'Country Model'!AL42)*-1 -> 0 | ... AD9: =('Country Model'!AD42+'Country Model'!BD42)*-1 -> 0 | AE9: =SUM(E9:AD9) -> -85840260 | AG9: =AG8+1 -> 5
C10: Total costs | E10: =SUM(E7:E9) -> 0 | F10: =SUM(F7:F9) -> 0 | G10: =SUM(G7:G9) -> 0 | H10: =SUM(H7:H9) -> -1.6274607e+08 | I10: =SUM(I7:I9) -> -1.2871853e+08 | J10: =SUM(J7:J9) -> -1.4361351e+08 | K10: =SUM(K7:K9) -> -2.0387061e+08 | L10: =SUM(L7:L9) -> -1.7573065e+08 | ... AD10: =SUM(AD7:AD9) -> -2.2322008e+08 | AE10: =SUM(E10:AD10) -> -4.1507842e+09 | AG10: =AG9+1 -> 6
D11: Benefit: Emergency WASH costs averted | E11: =('Country Model'!E61- 'Country Model'!E81) + ('Country Model'!AE61-'Country Model'!AE81) -> 0 | F11: =('Country Model'!F61- 'Country Model'!F81) + ('Country Model'!AF61-'Country Model'!AF81) -> 0 | G11: =('Country Model'!G61- 'Country Model'!G81) + ('Country Model'!AG61-'Country Model'!AG81) -> 0 | H11: =('Country Model'!H61- 'Country Model'!H81) + ('Country Model'!AH61-'Country Model'!AH81) -> 20916221 | I11: =('Country Model'!I61- 'Country Model'!I81) + ('Country Model'!AI61-'Country Model'!AI81) -> 22026787 | J11: =('Country Model'!J61- 'Country Model'!J81) + ('Country Model'!AJ61-'Country Model'!AJ81) -> 23185116 | K11: =('Country Model'!K61- 'Country Model'!K81) + ('Country Model'!AK61-'Country Model'!AK81) -> 24393181 | L11: =('Country Model'!L61- 'Country Model'!L81) + ('Country Model'!AL61-'Country Model'!AL81) -> 25653038 | ... AD11: =('Country Model'!AD61- 'Country Model'!AD81) + ('Country Model'!BD61-'Country Model'!BD81) -> 48140653 | AE11: =SUM(E11:AD11) -> 7.9267779e+08 | AG11: =AG10+1 -> 7
D12: Benefit: Emergency OCV costs averted | E12: =('Country Model'!E62-'Country Model'!E82)-('Country Model'!AE62-'Country Model'!AE82) -> 0 | F12: =('Country Model'!F62-'Country Model'!F82)-('Country Model'!AF62-'Country Model'!AF82) -> 0 | G12: =('Country Model'!G62-'Country Model'!G82)-('Country Model'!AG62-'Country Model'!AG82) -> 0 | H12: =('Country Model'!H62-'Country Model'!H82)-('Country Model'!AH62-'Country Model'!AH82) -> -1901549.3 | I12: =('Country Model'!I62-'Country Model'!I82)-('Country Model'!AI62-'Country Model'!AI82) -> -1813899.8 | J12: =('Country Model'!J62-'Country Model'!J82)-('Country Model'!AJ62-'Country Model'!AJ82) -> -1826951.1 | K12: =('Country Model'!K62-'Country Model'!K82)-('Country Model'!AK62-'Country Model'!AK82) -> -1721154.3 | L12: =('Country Model'!L62-'Country Model'!L82)-('Country Model'!AL62-'Country Model'!AL82) -> -1731521.2 | ... AD12: =('Country Model'!AD62-'Country Model'!AD82)-('Country Model'!BD62-'Country Model'!BD82) -> -1646911 | AE12: =SUM(E12:AD12) -> -40304848 | AG12: =AG11+1 -> 8
D13: Benefit: Emergency CM costs averted | E13: ='Country Model'!E63-'Country Model'!E83 -> 0 | F13: ='Country Model'!F63-'Country Model'!F83 -> 0 | G13: ='Country Model'!G63-'Country Model'!G83 -> 0 | H13: ='Country Model'!H63-'Country Model'!H83 -> 85930.118 | I13: ='Country Model'!I63-'Country Model'!I83 -> 95666.119 | J13: ='Country Model'!J63-'Country Model'!J83 -> 106070.91 | K13: ='Country Model'!K63-'Country Model'!K83 -> 117183.6 | L13: ='Country Model'!L63-'Country Model'!L83 -> 129045.42 | ... AD13: ='Country Model'!AD63-'Country Model'!AD83 -> 300705.74 | AE13: =SUM(E13:AD13) -> 4423822.5 | AG13: =AG12+1 -> 9
D14: Benefit: Cholera productive time gained | E14: =('Country Model'!E64-'Country Model'!E84)+('Country Model'!AE64-'Country Model'!AE84) -> 0 | F14: =('Country Model'!F64-'Country Model'!F84)+('Country Model'!AF64-'Country Model'!AF84) -> 0 | G14: =('Country Model'!G64-'Country Model'!G84)+('Country Model'!AG64-'Country Model'!AG84) -> 0 | H14: =('Country Model'!H64-'Country Model'!H84)+('Country Model'!AH64-'Country Model'!AH84) -> 197148.82 | I14: =('Country Model'!I64-'Country Model'!I84)+('Country Model'!AI64-'Country Model'!AI84) -> 213329.58 | J14: =('Country Model'!J64-'Country Model'!J84)+('Country Model'!AJ64-'Country Model'!AJ84) -> 230498.96 | K14: =('Country Model'!K64-'Country Model'!K84)+('Country Model'!AK64-'Country Model'!AK84) -> 248711.93 | L14: =('Country Model'!L64-'Country Model'!L84)+('Country Model'!AL64-'Country Model'!AL84) -> 268026.37 | ... AD14: =('Country Model'!AD64-'Country Model'!AD84)+('Country Model'!BD64-'Country Model'!BD84) -> 489017.91 | AE14: =SUM(E14:AD14) -> 8123273.3 | AG14: =AG13+1 -> 10
D15: Benefit: Cholera value of life gained | E15: =('Country Model'!E86-'Country Model'!E90)+('Country Model'!AE86-'Country Model'!AE90) -> 0 | F15: =('Country Model'!F86-'Country Model'!F90)+('Country Model'!AF86-'Country Model'!AF90) -> 0 | G15: =('Country Model'!G86-'Country Model'!G90)+('Country Model'!AG86-'Country Model'!AG90) -> 0 | H15: =('Country Model'!H86-'Country Model'!H90)+('Country Model'!AH86-'Country Model'!AH90) -> 71751620 | I15: =('Country Model'!I86-'Country Model'!I90)+('Country Model'!AI86-'Country Model'!AI90) -> 77636111 | J15: =('Country Model'!J86-'Country Model'!J90)+('Country Model'!AJ86-'Country Model'!AJ90) -> 83793137 | K15: =('Country Model'!K86-'Country Model'!K90)+('Country Model'!AK86-'Country Model'!AK90) -> 90234025 | L15: =('Country Model'!L86-'Country Model'!L90)+('Country Model'!AL86-'Country Model'!AL90) -> 96970570 | ... AD15: =('Country Model'!AD86-'Country Model'!AD90)+('Country Model'!BD86-'Country Model'!BD90) -> 1.735926e+08 | AE15: =SUM(E15:AD15) -> 2.9072903e+09 | AG15: =AG14+1 -> 11
D16: Benefit: Diarrhea treatment costs averted | E16: =('Country Model'!E92-'Country Model'!E93)+('Country Model'!AE92-'Country Model'!AE93) -> 0 | F16: =('Country Model'!F92-'Country Model'!F93)+('Country Model'!AF92-'Country Model'!AF93) -> 0 | G16: =('Country Model'!G92-'Country Model'!G93)+('Country Model'!AG92-'Country Model'!AG93) -> 0 | H16: =('Country Model'!H92-'Country Model'!H93)+('Country Model'!AH92-'Country Model'!AH93) -> 27229869 | I16: =('Country Model'!I92-'Country Model'!I93)+('Country Model'!AI92-'Country Model'!AI93) -> 55762116 | J16: =('Country Model'!J92-'Country Model'!J93)+('Country Model'!AJ92-'Country Model'!AJ93) -> 85643895 | K16: =('Country Model'!K92-'Country Model'!K93)+('Country Model'!AK92-'Country Model'!AK93) -> 1.169239e+08 | L16: =('Country Model'!L92-'Country Model'!L93)+('Country Model'!AL92-'Country Model'!AL93) -> 1.4965243e+08 | ... AD16: =('Country Model'!AD92-'Country Model'!AD93)+('Country Model'!BD92-'Country Model'!BD93) -> 2.1639537e+08 | AE16: =SUM(E16:AD16) -> 4.4021863e+09 | AG16: =AG15+1 -> 12
D17: Benefit: Diarrhea productive time gained | E17: =('Country Model'!E97-'Country Model'!E98)+('Country Model'!AE97-'Country Model'!AE98) -> 0 | F17: =('Country Model'!F97-'Country Model'!F98)+('Country Model'!AF97-'Country Model'!AF98) -> 0 | G17: =('Country Model'!G97-'Country Model'!G98)+('Country Model'!AG97-'Country Model'!AG98) -> 0 | H17: =('Country Model'!H97-'Country Model'!H98)+('Country Model'!AH97-'Country Model'!AH98) -> 947969.75 | I17: =('Country Model'!I97-'Country Model'!I98)+('Country Model'!AI97-'Country Model'!AI98) -> 1966596.5 | J17: =('Country Model'!J97-'Country Model'!J98)+('Country Model'!AJ97-'Country Model'!AJ98) -> 3059979 | K17: =('Country Model'!K97-'Country Model'!K98)+('Country Model'!AK97-'Country Model'!AK98) -> 4232436.8 | L17: =('Country Model'!L97-'Country Model'!L98)+('Country Model'!AL97-'Country Model'!AL98) -> 5488522.2 | ... AD17: =('Country Model'!AD97-'Country Model'!AD98)+('Country Model'!BD97-'Country Model'!BD98) -> 14019061 | AE17: =SUM(E17:AD17) -> 2.076901e+08 | AG17: =AG16+1 -> 13
D18: Benefit: Diarrhea value of life gained | E18: =('Country Model'!E102-'Country Model'!E103)+('Country Model'!AE102-'Country Model'!AE103) -> 0 | F18: =('Country Model'!F102-'Country Model'!F103)+('Country Model'!AF102-'Country Model'!AF103) -> 0 | G18: =('Country Model'!G102-'Country Model'!G103)+('Country Model'!AG102-'Country Model'!AG103) -> 0 | H18: =('Country Model'!H102-'Country Model'!H103)+('Country Model'!AH102-'Country Model'!AH103) -> 1.5424741e+08 | I18: =('Country Model'!I102-'Country Model'!I103)+('Country Model'!AI102-'Country Model'!AI103) -> 1.6064502e+08 | J18: =('Country Model'!J102-'Country Model'!J103)+('Country Model'!AJ102-'Country Model'!AJ103) -> 1.6734276e+08 | K18: =('Country Model'!K102-'Country Model'!K103)+('Country Model'!AK102-'Country Model'!AK103) -> 1.7435633e+08 | L18: =('Country Model'!L102-'Country Model'!L103)+('Country Model'!AL102-'Country Model'!AL103) -> 1.8170229e+08 | ... AD18: =('Country Model'!AD102-'Country Model'!AD103)+('Country Model'!BD102-'Country Model'!BD103) -> 3.4583357e+08 | AE18: =SUM(E18:AD18) -> 5.5329363e+09 | AG18: =AG17+1 -> 14
D19: Benefit: WASH access time savings | E19: =('Country Model'!E107+'Country Model'!E109)+('Country Model'!AE107+'Country Model'!AE109) -> 0 | F19: =('Country Model'!F107+'Country Model'!F109)+('Country Model'!AF107+'Country Model'!AF109) -> 0 | G19: =('Country Model'!G107+'Country Model'!G109)+('Country Model'!AG107+'Country Model'!AG109) -> 0 | H19: =('Country Model'!H107+'Country Model'!H109)+('Country Model'!AH107+'Country Model'!AH109) -> 8039644.6 | I19: =('Country Model'!I107+'Country Model'!I109)+('Country Model'!AI107+'Country Model'!AI109) -> 16644500 | J19: =('Country Model'!J107+'Country Model'!J109)+('Country Model'!AJ107+'Country Model'!AJ109) -> 25844912 | K19: =('Country Model'!K107+'Country Model'!K109)+('Country Model'!AK107+'Country Model'!AK109) -> 35672714 | L19: =('Country Model'!L107+'Country Model'!L109)+('Country Model'!AL107+'Country Model'!AL109) -> 46161294 | ... AD19: =('Country Model'!AD107+'Country Model'!AD109)+('Country Model'!BD107+'Country Model'!BD109) -> 1.2099554e+08 | AE19: =SUM(E19:AD19) -> 1.767964e+09 | AG19: =AG18+1 -> 15
D20: Benefits of OCV Only | L20: =('Country Model'!L86-'Country Model'!L88)+('Country Model'!AL86-'Country Model'!AL88)+L12 -> 73965797 | M20: =('Country Model'!M86-'Country Model'!M88)+('Country Model'!AM86-'Country Model'!AM88)+M12 -> 76042731 | N20: =('Country Model'!N86-'Country Model'!N88)+('Country Model'!AN86-'Country Model'!AN88)+N12 -> 78182641 | O20: =('Country Model'!O86-'Country Model'!O88)+('Country Model'!AO86-'Country Model'!AO88)+O12 -> 80387604 | P20: =('Country Model'!P86-'Country Model'!P88)+('Country Model'!AP86-'Country Model'!AP88)+P12 -> 82659769 | Q20: =('Country Model'!Q86-'Country Model'!Q88)+('Country Model'!AQ86-'Country Model'!AQ88)+Q12 -> 85001360 | R20: =('Country Model'!R86-'Country Model'!R88)+('Country Model'!AR86-'Country Model'!AR88)+R12 -> 87414683 | S20: =('Country Model'!S86-'Country Model'!S88)+('Country Model'!AS86-'Country Model'!AS88)+S12 -> 89902125 | ... AE20: =('Country Model'!AE86-'Country Model'!AE88)+('Country Model'!BE86-'Country Model'!BE88)+AE12 -> 2.3440258e+08 | AG20: =AG19+1 -> 16
D21: Benefits for ramp up of WASH | L21: =IF(Tables!L$5='User Inputs'!$F$9,Tables!L$22*Tables!$L$3,IF(Tables!L5='User Inputs'!$F$9+1,Tables!L22*Tables!$M$3,IF(Tables!L5='User Inputs'!$F$9+2,Tables!L22*Tables!$N$3,IF(Tables!L5='User Inputs'!$F$9+3,Tables!L22*Tables!$O$3,IF(Tables!L5='User Inputs'!$F$9+4,Tables!L22*Tables!$P$3,L22))))) -> 5.042937e+08 | M21: =IF(Tables!M$5='User Inputs'!$F$9,Tables!M$22*Tables!$L$3,IF(Tables!M5='User Inputs'!$F$9+1,Tables!M22*Tables!$M$3,IF(Tables!M5='User Inputs'!$F$9+2,Tables!M22*Tables!$N$3,IF(Tables!M5='User Inputs'!$F$9+3,Tables!M22*Tables!$O$3,IF(Tables!M5='User Inputs'!$F$9+4,Tables!M22*Tables!$P$3,M22))))) -> 5.6712951e+08 | N21: =IF(Tables!N$5='User Inputs'!$F$9,Tables!N$22*Tables!$L$3,IF(Tables!N5='User Inputs'!$F$9+1,Tables!N22*Tables!$M$3,IF(Tables!N5='User Inputs'!$F$9+2,Tables!N22*Tables!$N$3,IF(Tables!N5='User Inputs'!$F$9+3,Tables!N22*Tables!$O$3,IF(Tables!N5='User Inputs'!$F$9+4,Tables!N22*Tables!$P$3,N22))))) -> 6.3452263e+08 | O21: =IF(Tables!O$5='User Inputs'!$F$9,Tables!O$22*Tables!$L$3,IF(Tables!O5='User Inputs'!$F$9+1,Tables!O22*Tables!$M$3,IF(Tables!O5='User Inputs'!$F$9+2,Tables!O22*Tables!$N$3,IF(Tables!O5='User Inputs'!$F$9+3,Tables!O22*Tables!$O$3,IF(Tables!O5='User Inputs'!$F$9+4,Tables!O22*Tables!$P$3,O22))))) -> 6.4946045e+08 | P21: =IF(Tables!P$5='User Inputs'!$F$9,Tables!P$22*Tables!$L$3,IF(Tables!P5='User Inputs'!$F$9+1,Tables!P22*Tables!$M$3,IF(Tables!P5='User Inputs'!$F$9+2,Tables!P22*Tables!$N$3,IF(Tables!P5='User Inputs'!$F$9+3,Tables!P22*Tables!$O$3,IF(Tables!P5='User Inputs'!$F$9+4,Tables!P22*Tables!$P$3,P22))))) -> 66473529 | Q21: =IF(Tables!Q$5='User Inputs'!$F$9,Tables!Q$22*Tables!$L$3,IF(Tables!Q5='User Inputs'!$F$9+1,Tables!Q22*Tables!$M$3,IF(Tables!Q5='User Inputs'!$F$9+2,Tables!Q22*Tables!$N$3,IF(Tables!Q5='User Inputs'!$F$9+3,Tables!Q22*Tables!$O$3,IF(Tables!Q5='User Inputs'!$F$9+4,Tables!Q22*Tables!$P$3,Q22))))) -> 2.0410624e+08 | R21: =IF(Tables!R$5='User Inputs'!$F$9,Tables!R$22*Tables!$L$3,IF(Tables!R5='User Inputs'!$F$9+1,Tables!R22*Tables!$M$3,IF(Tables!R5='User Inputs'!$F$9+2,Tables!R22*Tables!$N$3,IF(Tables!R5='User Inputs'!$F$9+3,Tables!R22*Tables!$O$3,IF(Tables!R5='User Inputs'!$F$9+4,Tables!R22*Tables!$P$3,R22))))) -> 3.4816207e+08 | S21: =IF(Tables!S$5='User Inputs'!$F$9,Tables!S$22*Tables!$L$3,IF(Tables!S5='User Inputs'!$F$9+1,Tables!S22*Tables!$M$3,IF(Tables!S5='User Inputs'!$F$9+2,Tables!S22*Tables!$N$3,IF(Tables!S5='User Inputs'!$F$9+3,Tables!S22*Tables!$O$3,IF(Tables!S5='User Inputs'!$F$9+4,Tables!S22*Tables!$P$3,S22))))) -> 5.344894e+08 | ... AE21: =IF(Tables!AE$5='User Inputs'!$F$9,Tables!AE$22*Tables!$L$3,IF(Tables!AE5='User Inputs'!$F$9+1,Tables!AE22*Tables!$M$3,IF(Tables!AE5='User Inputs'!$F$9+2,Tables!AE22*Tables!$N$3,IF(Tables!AE5='User Inputs'!$F$9+3,Tables!AE22*Tables!$O$3,IF(Tables!AE5='User Inputs'!$F$9+4,Tables!AE22*Tables!$P$3,AE22))))) -> 1.5582987e+10 | AG21: =AG20+1 -> 17
C22: Total benefits | E22: =SUM(E11:E19) -> 0 | F22: =SUM(F11:F19) -> 0 | G22: =SUM(G11:G19) -> 0 | H22: =SUM(H11:H19) -> 2.8151426e+08 | I22: =SUM(I11:I19) -> 3.3317623e+08 | J22: =SUM(J11:J19) -> 3.8737942e+08 | K22: =SUM(K11:K19) -> 4.4445733e+08 | L22: =SUM(L11:L19) -> 5.042937e+08 | ... AD22: =SUM(AD11:AD19) -> 9.181196e+08 | AE22: =SUM(E22:AD22) -> 1.5582987e+10 | AG22: =AG21+1 -> 18
C23: Net Benefits | E23: =E22-E10 -> 0 | F23: =F22-F10 -> 0 | G23: =G22-G10 -> 0 | H23: =H22-H10 -> 4.4426033e+08 | I23: =I22-I10 -> 4.6189476e+08 | J23: =J22-J10 -> 5.3099293e+08 | K23: =K22-K10 -> 6.4832794e+08 | L23: =L22-L10 -> 6.8002435e+08 | ... AD23: =AD22-AD10 -> 1.1413397e+09 | AE23: =SUM(E23:AD23) -> 1.9733771e+10 | AG23: =AG22+1 -> 19
AG24: =AG23+1 -> 20
B25: 2. Population to be reached | AG25: =AG24+1 -> 21
D26: ='Country Model'!C28 -> Population numbers to be reached with Water | H26: ='Country Model'!H28+'Country Model'!AH28 -> 862606.51 | I26: ='Country Model'!I28+'Country Model'!AI28 -> 862606.51 | J26: ='Country Model'!J28+'Country Model'!AJ28 -> 862606.51 | K26: ='Country Model'!K28+'Country Model'!AK28 -> 862606.51 | L26: ='Country Model'!L28+'Country Model'!AL28 -> 862606.51 | M26: ='Country Model'!M28+'Country Model'!AM28 -> 862606.51 | N26: ='Country Model'!N28+'Country Model'!AN28 -> 862606.51 | O26: ='Country Model'!O28+'Country Model'!AO28 -> 256969.2 | ... AD26: ='Country Model'!AD28+'Country Model'!BD28 -> 393658.57 | AE26: =SUM(H26:AD26) -> 11165066 | AG26: =AG25+1 -> 22
D27: ='Country Model'!C29 -> Population numbers to be reached with Sanitation | H27: ='Country Model'!H29+'Country Model'!AH29 -> 1022458.6 | I27: ='Country Model'!I29+'Country Model'!AI29 -> 1022458.6 | J27: ='Country Model'!J29+'Country Model'!AJ29 -> 1022458.6 | K27: ='Country Model'!K29+'Country Model'!AK29 -> 1022458.6 | L27: ='Country Model'!L29+'Country Model'!AL29 -> 1022458.6 | M27: ='Country Model'!M29+'Country Model'!AM29 -> 1022458.6 | N27: ='Country Model'!N29+'Country Model'!AN29 -> 1022458.6 | O27: ='Country Model'!O29+'Country Model'!AO29 -> 256969.2 | ... AD27: ='Country Model'!AD29+'Country Model'!BD29 -> 393658.57 | AE27: =SUM(H27:AD27) -> 12284031 | AG27: =AG26+1 -> 23
D28: ='Country Model'!C30 -> Population numbers to be reached with Hygiene | H28: ='Country Model'!H30+'Country Model'!AH30 -> 1196308.2 | I28: ='Country Model'!I30+'Country Model'!AI30 -> 1196308.2 | J28: ='Country Model'!J30+'Country Model'!AJ30 -> 1196308.2 | K28: ='Country Model'!K30+'Country Model'!AK30 -> 1196308.2 | L28: ='Country Model'!L30+'Country Model'!AL30 -> 1196308.2 | M28: ='Country Model'!M30+'Country Model'!AM30 -> 1196308.2 | N28: ='Country Model'!N30+'Country Model'!AN30 -> 1196308.2 | O28: ='Country Model'!O30+'Country Model'!AO30 -> 256969.2 | ... AD28: ='Country Model'!AD30+'Country Model'!BD30 -> 393658.57 | AE28: =SUM(H28:AD28) -> 13500978 | AG28: =AG27+1 -> 24
D29: ='Country Model'!C31 -> Population numbers to be reached with OCV (with WASH) | H29: ='Country Model'!H31+'Country Model'!AH31 -> 7014147.3 | I29: ='Country Model'!I31+'Country Model'!AI31 -> 0 | J29: ='Country Model'!J31+'Country Model'!AJ31 -> 0 | K29: ='Country Model'!K31+'Country Model'!AK31 -> 7584536.4 | L29: ='Country Model'!L31+'Country Model'!AL31 -> 0 | M29: ='Country Model'!M31+'Country Model'!AM31 -> 0 | N29: ='Country Model'!N31+'Country Model'!AN31 -> 0 | O29: ='Country Model'!O31+'Country Model'!AO31 -> 0 | ... AD29: ='Country Model'!AD31+'Country Model'!BD31 -> 0 | AE29: =SUM(H29:AD29) -> 14598684 | AG29: =AG28+1 -> 25
D30: ='Country Model'!C32 -> Population numbers to be reached with OCV (alone) | H30: ='Country Model'!H32+'Country Model'!AH32 -> 7014147.3 | I30: ='Country Model'!I32+'Country Model'!AI32 -> 0 | J30: ='Country Model'!J32+'Country Model'!AJ32 -> 0 | K30: ='Country Model'!K32+'Country Model'!AK32 -> 7584536.4 | L30: ='Country Model'!L32+'Country Model'!AL32 -> 0 | M30: ='Country Model'!M32+'Country Model'!AM32 -> 0 | N30: ='Country Model'!N32+'Country Model'!AN32 -> 8204428 | O30: ='Country Model'!O32+'Country Model'!AO32 -> 0 | ... AD30: ='Country Model'!AD32+'Country Model'!BD32 -> 0 | AE30: =SUM(H30:AD30) -> 75211091 | AG30: =AG29+1 -> 26
D31: TOTAL | L31: =L30+L28 -> 1196308.2 | M31: =M30+M28 -> 1196308.2 | N31: =N30+N28 -> 9400736.3 | O31: =O30+O28 -> 256969.2 | P31: =P30+P28 -> 264261.75 | Q31: =Q30+Q28 -> 9150263.9 | R31: =R30+R28 -> 279525.89 | S31: =S30+S28 -> 287512.68 | ... AE31: =AE30+AE28 -> 88712069 | AG31: =AG30+1 -> 27
B32: 3a. WASH Total costs by year for increasing coverage - Urban | AF32: ="NPV @ "& ROUND(('User Inputs'!$F$11*100),0) & "%" -> NPV @ 5% | AG32: =AG31+1 -> 28
D33: Water | E33: ='Country Model'!E34+'Country Model'!E38 -> 0 | F33: ='Country Model'!F34+'Country Model'!F38 -> 0 | G33: ='Country Model'!G34+'Country Model'!G38 -> 0 | H33: ='Country Model'!H34+'Country Model'!H38 -> 14669258 | I33: ='Country Model'!I34+'Country Model'!I38 -> 7877719 | J33: ='Country Model'!J34+'Country Model'!J38 -> 8041152 | K33: ='Country Model'!K34+'Country Model'!K38 -> 8215066.5 | L33: ='Country Model'!L34+'Country Model'!L38 -> 8400056.4 | ... AD33: ='Country Model'!AD34+'Country Model'!AD38 -> 13351055 | AE33: =SUM(H33:AD33) -> 2.2413316e+08 | AF33: =NPV(NPV_Country,E33:AD33) -> 1.1027951e+08 | AG33: =AG32+1 -> 29
D34: Sanitation | E34: ='Country Model'!E35+'Country Model'!E39 -> 0 | F34: ='Country Model'!F35+'Country Model'!F39 -> 0 | G34: ='Country Model'!G35+'Country Model'!G39 -> 0 | H34: ='Country Model'!H35+'Country Model'!H39 -> 7180877.8 | I34: ='Country Model'!I35+'Country Model'!I39 -> 7755837.7 | J34: ='Country Model'!J35+'Country Model'!J39 -> 8378388.9 | K34: ='Country Model'!K35+'Country Model'!K39 -> 9051524.6 | L34: ='Country Model'!L35+'Country Model'!L39 -> 9778405.9 | ... AD34: ='Country Model'!AD35+'Country Model'!AD39 -> 14106718 | AE34: =SUM(H34:AD34) -> 2.3267089e+08 | AF34: =NPV(NPV_Country,E34:AD34) -> 1.1226413e+08 | AG34: =AG33+1 -> 30
D35: Hygiene | E35: ='Country Model'!E36+'Country Model'!E40 -> 0 | F35: ='Country Model'!F36+'Country Model'!F40 -> 0 | G35: ='Country Model'!G36+'Country Model'!G40 -> 0 | H35: ='Country Model'!H36+'Country Model'!H40 -> 4684069.7 | I35: ='Country Model'!I36+'Country Model'!I40 -> 6170490.7 | J35: ='Country Model'!J36+'Country Model'!J40 -> 7779947.8 | K35: ='Country Model'!K36+'Country Model'!K40 -> 9520178.9 | L35: ='Country Model'!L36+'Country Model'!L40 -> 11399356 | ... AD35: ='Country Model'!AD36+'Country Model'!AD40 -> 25965111 | AE35: =SUM(H35:AD35) -> 3.7883828e+08 | AF35: =NPV(NPV_Country,E35:AD35) -> 1.7083757e+08 | AG35: =AG34+1 -> 31
AG36: =AG35+1 -> 32
B37: 3b. WASH Total costs by year for increasing coverage - Rural | AG37: =AG36+1 -> 33
D38: Water | E38: ='Country Model'!AE34+'Country Model'!AE38 -> 0 | F38: ='Country Model'!AF34+'Country Model'!AF38 -> 0 | G38: ='Country Model'!AG34+'Country Model'!AG38 -> 0 | H38: ='Country Model'!AH34+'Country Model'!AH38 -> 50269874 | I38: ='Country Model'!AI34+'Country Model'!AI38 -> 54539989 | J38: ='Country Model'!AJ34+'Country Model'!AJ38 -> 59005278 | K38: ='Country Model'!AK34+'Country Model'!AK38 -> 63672579 | L38: ='Country Model'!AL34+'Country Model'!AL38 -> 68548945 | ... AD38: ='Country Model'!BD34+'Country Model'!BD38 -> 72348614 | AE38: =SUM(H38:AD38) -> 1.4259058e+09 | AF38: =NPV(NPV_Country,E38:AD38) -> 7.1243103e+08 | AG38: =AG37+1 -> 34
D39: Sanitation | E39: ='Country Model'!AE35+'Country Model'!AE39 -> 0 | F39: ='Country Model'!AF35+'Country Model'!AF39 -> 0 | G39: ='Country Model'!AG35+'Country Model'!AG39 -> 0 | H39: ='Country Model'!AH35+'Country Model'!AH39 -> 37481752 | I39: ='Country Model'!AI35+'Country Model'!AI39 -> 40868628 | J39: ='Country Model'!AJ35+'Country Model'!AJ39 -> 44413712 | K39: ='Country Model'!AK35+'Country Model'!AK39 -> 48122588 | L39: ='Country Model'!AL35+'Country Model'!AL39 -> 52001016 | ... AD39: ='Country Model'!BD35+'Country Model'!BD39 -> 48693186 | AE39: =SUM(H39:AD39) -> 9.9697004e+08 | AF39: =NPV(NPV_Country,E39:AD39) -> 5.055487e+08 | AG39: =AG38+1 -> 35
D40: Hygiene | E40: ='Country Model'!AE36+'Country Model'!AE40 -> 0 | F40: ='Country Model'!AF36+'Country Model'!AF40 -> 0 | G40: ='Country Model'!AG36+'Country Model'!AG40 -> 0 | H40: ='Country Model'!AH36+'Country Model'!AH40 -> 7217048.5 | I40: ='Country Model'!AI36+'Country Model'!AI40 -> 11505869 | J40: ='Country Model'!AJ36+'Country Model'!AJ40 -> 15995028 | K40: ='Country Model'!AK36+'Country Model'!AK40 -> 20691598 | L40: ='Country Model'!AL36+'Country Model'!AL40 -> 25602874 | ... AD40: ='Country Model'!BD36+'Country Model'!BD40 -> 48755391 | AE40: =SUM(H40:AD40) -> 8.0642584e+08 | AF40: =NPV(NPV_Country,E40:AD40) -> 3.682445e+08 | AG40: =AG39+1 -> 36
AG41: =AG40+1 -> 37
B42: 3d. Distribution of total costs | AG42: =AG41+1 -> 38
E43: Urban | F43: Rural | G43: TOTAL | AG43: =AG42+1 -> 39
D44: WASH capital costs | E44: =SUM('Country Model'!E34:AD36) -> 2.9083602e+08 | F44: =SUM('Country Model'!AE34:BD36) -> 8.7238897e+08 | G44: =SUM(E44:F44) -> 1.163225e+09 | AG44: =AG43+1 -> 40
D45: WASH O&M costs | E45: =SUM('Country Model'!E38:AD40) -> 5.4480631e+08 | F45: =SUM('Country Model'!AE38:BD40) -> 2.3569127e+09 | G45: =SUM(E45:F45) -> 2.901719e+09 | AG45: =AG44+1 -> 41
D46: OCV | E46: =SUM('Country Model'!E42:AC42) -> 12956161 | F46: =SUM('Country Model'!AE42:BD42) -> 72884099 | G46: =SUM(E46:F46) -> 85840260 | AG46: =AG45+1 -> 42
D47: Surveillance | G47: =SUM(E47:F47) -> 0 | AG47: =AG46+1 -> 43
AG48: =AG47+1 -> 44
B49: 4a. Cholera cases averted by implementing roadmap | AG49: =AG48+1 -> 45
D50: No roadmap | E50: ='Country Model'!E46+'Country Model'!AE46 -> 29427 | F50: ='Country Model'!F46+'Country Model'!AF46 -> 30384.659 | G50: ='Country Model'!G46+'Country Model'!AG46 -> 31376.02 | H50: ='Country Model'!H46+'Country Model'!AH46 -> 54494 | I50: ='Country Model'!I46+'Country Model'!AI46 -> 56006.352 | J50: ='Country Model'!J46+'Country Model'!AJ46 -> 57563.93 | K50: ='Country Model'!K46+'Country Model'!AK46 -> 59168.202 | L50: ='Country Model'!L46+'Country Model'!AL46 -> 60820.689 | ... AD50: ='Country Model'!AD46+'Country Model'!BD46 -> 100910.36 | AE50: =SUM(E50:AD50) -> 1822232.2 | AG50: =AG49+1 -> 46
D51: Roadmap | E51: =IF('Country Model'!$EQI$8="Crisis","NA",'Country Model'!E58+'Country Model'!AE58) -> 29427 | F51: =IF('Country Model'!$EQI$8="Crisis","NA",'Country Model'!F58+'Country Model'!AF58) -> 30384.659 | G51: =IF('Country Model'!$EQI$8="Crisis","NA",'Country Model'!G58+'Country Model'!AG58) -> 31376.02 | H51: =IF('Country Model'!$EQI$8="Crisis","NA",'Country Model'!H58+'Country Model'!AH58) -> 13188.464 | I51: =IF('Country Model'!$EQI$8="Crisis","NA",'Country Model'!I58+'Country Model'!AI58) -> 11295.399 | J51: =IF('Country Model'!$EQI$8="Crisis","NA",'Country Model'!J58+'Country Model'!AJ58) -> 9287.6256 | K51: =IF('Country Model'!$EQI$8="Crisis","NA",'Country Model'!K58+'Country Model'!AK58) -> 7159.8496 | L51: =IF('Country Model'!$EQI$8="Crisis","NA",'Country Model'!L58+'Country Model'!AL58) -> 4906.543 | ... AD51: =IF('Country Model'!$EQI$8="Crisis","NA",'Country Model'!AD58+'Country Model'!BD58) -> 0 | AE51: =SUM(E51:AD51) -> 139547.49 | AG51: =AG50+1 -> 47
D52: WASH alone | E52: =IF('Country Model'!$EQI$8="Crisis","NA",'Country Model'!E49+'Country Model'!AE49) -> 29427 | F52: =IF('Country Model'!$EQI$8="Crisis","NA",'Country Model'!F49+'Country Model'!AF49) -> 30384.659 | G52: =IF('Country Model'!$EQI$8="Crisis","NA",'Country Model'!G49+'Country Model'!AG49) -> 31376.02 | H52: =IF('Country Model'!$EQI$8="Crisis","NA",'Country Model'!H49+'Country Model'!AH49) -> 46709.143 | I52: =IF('Country Model'!$EQI$8="Crisis","NA",'Country Model'!I49+'Country Model'!AI49) -> 40004.537 | J52: =IF('Country Model'!$EQI$8="Crisis","NA",'Country Model'!J49+'Country Model'!AJ49) -> 32893.674 | K52: =IF('Country Model'!$EQI$8="Crisis","NA",'Country Model'!K49+'Country Model'!AK49) -> 25357.801 | L52: =IF('Country Model'!$EQI$8="Crisis","NA",'Country Model'!L49+'Country Model'!AL49) -> 17377.34 | ... AD52: =IF('Country Model'!$EQI$8="Crisis","NA",'Country Model'!AD49+'Country Model'!BD49) -> 0 | AE52: =SUM(E52:AD52) -> 262462.03 | AG52: =AG51+1 -> 48
D53: OCV alone | E53: ='Country Model'!E52+'Country Model'!AE52 -> 29427 | F53: ='Country Model'!F52+'Country Model'!AF52 -> 30384.659 | G53: ='Country Model'!G52+'Country Model'!AG52 -> 31376.02 | H53: ='Country Model'!H52+'Country Model'!AH52 -> 15386.541 | I53: ='Country Model'!I52+'Country Model'!AI52 -> 15813.558 | J53: ='Country Model'!J52+'Country Model'!AJ52 -> 16253.345 | K53: ='Country Model'!K52+'Country Model'!AK52 -> 16706.316 | L53: ='Country Model'!L52+'Country Model'!AL52 -> 17172.9 | ... AD53: ='Country Model'!AD52+'Country Model'!BD52 -> 28492.337 | AE53: =SUM(E53:AD53) -> 579953.2 | AG53: =AG52+1 -> 49
D54: WASH and OCV | E54: =IF('Country Model'!$EQI$8="Crisis","NA",'Country Model'!E55+'Country Model'!AE55) -> 29427 | F54: =IF('Country Model'!$EQI$8="Crisis","NA",'Country Model'!F55+'Country Model'!AF55) -> 30384.659 | G54: =IF('Country Model'!$EQI$8="Crisis","NA",'Country Model'!G55+'Country Model'!AG55) -> 31376.02 | H54: =IF('Country Model'!$EQI$8="Crisis","NA",'Country Model'!H55+'Country Model'!AH55) -> 13188.464 | I54: =IF('Country Model'!$EQI$8="Crisis","NA",'Country Model'!I55+'Country Model'!AI55) -> 11295.399 | J54: =IF('Country Model'!$EQI$8="Crisis","NA",'Country Model'!J55+'Country Model'!AJ55) -> 9287.6256 | K54: =IF('Country Model'!$EQI$8="Crisis","NA",'Country Model'!K55+'Country Model'!AK55) -> 7159.8496 | L54: =IF('Country Model'!$EQI$8="Crisis","NA",'Country Model'!L55+'Country Model'!AL55) -> 4906.543 | ... AD54: =IF('Country Model'!$EQI$8="Crisis","NA",'Country Model'!AD55+'Country Model'!BD55) -> 0 | AE54: =SUM(E54:AD54) -> 139547.49 | AG54: =AG53+1 -> 50
AG55: =AG54+1 -> 51
B56: 4b. Cholera deaths averted by implementing roadmap | AG56: =AG55+1 -> 52
D57: No roadmap | E57: ='Country Model'!E47+'Country Model'!AE47 -> 1118 | F57: ='Country Model'!F47+'Country Model'!AF47 -> 1154.3837 | G57: ='Country Model'!G47+'Country Model'!AG47 -> 1192.0478 | H57: ='Country Model'!H47+'Country Model'!AH47 -> 1594 | I57: ='Country Model'!I47+'Country Model'!AI47 -> 1637.583 | J57: ='Country Model'!J47+'Country Model'!AJ47 -> 1682.4457 | K57: ='Country Model'!K47+'Country Model'!AK47 -> 1728.629 | L57: ='Country Model'!L47+'Country Model'!AL47 -> 1776.1751 | ... AD57: ='Country Model'!AD47+'Country Model'!BD47 -> 2923.125 | AE57: =SUM(E57:AD57) -> 53833.863 | AG57: =AG56+1 -> 53
D58: Roadmap | E58: =IF('Country Model'!$EQI$8="Crisis","NA",'Country Model'!E59+'Country Model'!AE59) -> 1118 | F58: =IF('Country Model'!$EQI$8="Crisis","NA",'Country Model'!F59+'Country Model'!AF59) -> 1154.3837 | G58: =IF('Country Model'!$EQI$8="Crisis","NA",'Country Model'!G59+'Country Model'!AG59) -> 1192.0478 | H58: =IF('Country Model'!$EQI$8="Crisis","NA",'Country Model'!H59+'Country Model'!AH59) -> 385.77479 | I58: =IF('Country Model'!$EQI$8="Crisis","NA",'Country Model'!I59+'Country Model'!AI59) -> 330.26883 | J58: =IF('Country Model'!$EQI$8="Crisis","NA",'Country Model'!J59+'Country Model'!AJ59) -> 271.45342 | K58: =IF('Country Model'!$EQI$8="Crisis","NA",'Country Model'!K59+'Country Model'!AK59) -> 209.17863 | L58: =IF('Country Model'!$EQI$8="Crisis","NA",'Country Model'!L59+'Country Model'!AL59) -> 143.28807 | ... AD58: =IF('Country Model'!$EQI$8="Crisis","NA",'Country Model'!AD59+'Country Model'!BD59) -> 0 | AE58: =SUM(E58:AD58) -> 4878.0138 | AG58: =AG57+1 -> 54
D59: WASH alone | E59: =IF('Country Model'!$EQI$8="Crisis","NA",'Country Model'!E50+'Country Model'!AE50) -> 1118 | F59: =IF('Country Model'!$EQI$8="Crisis","NA",'Country Model'!F50+'Country Model'!AF50) -> 1154.3837 | G59: =IF('Country Model'!$EQI$8="Crisis","NA",'Country Model'!G50+'Country Model'!AG50) -> 1192.0478 | H59: =IF('Country Model'!$EQI$8="Crisis","NA",'Country Model'!H50+'Country Model'!AH50) -> 1366.2857 | I59: =IF('Country Model'!$EQI$8="Crisis","NA",'Country Model'!I50+'Country Model'!AI50) -> 1169.7021 | J59: =IF('Country Model'!$EQI$8="Crisis","NA",'Country Model'!J50+'Country Model'!AJ50) -> 961.39753 | K59: =IF('Country Model'!$EQI$8="Crisis","NA",'Country Model'!K50+'Country Model'!AK50) -> 740.84099 | L59: =IF('Country Model'!$EQI$8="Crisis","NA",'Country Model'!L50+'Country Model'!AL50) -> 507.47859 | ... AD59: =IF('Country Model'!$EQI$8="Crisis","NA",'Country Model'!AD50+'Country Model'!BD50) -> 0 | AE59: =SUM(E59:AD59) -> 8470.8689 | AG59: =AG58+1 -> 55
D60: OCV alone | E60: ='Country Model'!E53+'Country Model'!AE53 -> 1118 | F60: ='Country Model'!F53+'Country Model'!AF53 -> 1154.3837 | G60: ='Country Model'!G53+'Country Model'!AG53 -> 1192.0478 | H60: ='Country Model'!H53+'Country Model'!AH53 -> 450.07059 | I60: ='Country Model'!I53+'Country Model'!AI53 -> 462.37636 | J60: ='Country Model'!J53+'Country Model'!AJ53 -> 475.04349 | K60: ='Country Model'!K53+'Country Model'!AK53 -> 488.08348 | L60: ='Country Model'!L53+'Country Model'!AL53 -> 501.50825 | ... AD60: ='Country Model'!AD53+'Country Model'!BD53 -> 825.35294 | AE60: =SUM(E60:AD60) -> 17686.388 | AG60: =AG59+1 -> 56
D61: WASH and OCV | E61: ='Country Model'!E56+'Country Model'!AE56 -> 1118 | F61: ='Country Model'!F56+'Country Model'!AF56 -> 1154.3837 | G61: ='Country Model'!G56+'Country Model'!AG56 -> 1192.0478 | H61: ='Country Model'!H56+'Country Model'!AH56 -> 385.77479 | I61: ='Country Model'!I56+'Country Model'!AI56 -> 330.26883 | J61: ='Country Model'!J56+'Country Model'!AJ56 -> 271.45342 | K61: ='Country Model'!K56+'Country Model'!AK56 -> 209.17863 | L61: ='Country Model'!L56+'Country Model'!AL56 -> 143.28807 | ... AD61: ='Country Model'!AD56+'Country Model'!BD56 -> 0 | AE61: =SUM(E61:AD61) -> 4878.0138 | AG61: =AG60+1 -> 57
AG62: =AG61+1 -> 58
B63: 4f. Diarrhea cases | AG63: =AG62+1 -> 59
D64: No roadmap | E64: ='Country Model'!E111+'Country Model'!AE111 -> 4365899 | F64: ='Country Model'!F111+'Country Model'!AF111 -> 4475703 | G64: ='Country Model'!G111+'Country Model'!AG111 -> 4588382.4 | H64: ='Country Model'!H111+'Country Model'!AH111 -> 1.1945287e+08 | I64: ='Country Model'!I111+'Country Model'!AI111 -> 1.2231125e+08 | J64: ='Country Model'!J111+'Country Model'!AJ111 -> 1.252387e+08 | K64: ='Country Model'!K111+'Country Model'!AK111 -> 1.2823691e+08 | L64: ='Country Model'!L111+'Country Model'!AL111 -> 1.3130762e+08 | ... AD64: ='Country Model'!AD111+'Country Model'!BD111 -> 2.0125037e+08 | AE64: =SUM(E64:AD64) -> 3.6229227e+09 | AG64: =AG63+1 -> 60
D65: Roadmap | E65: ='Country Model'!E112+'Country Model'!AE112 -> 4365899 | F65: ='Country Model'!F112+'Country Model'!AF112 -> 4475703 | G65: ='Country Model'!G112+'Country Model'!AG112 -> 4588382.4 | H65: ='Country Model'!H112+'Country Model'!AH112 -> 1.1092052e+08 | I65: ='Country Model'!I112+'Country Model'!AI112 -> 1.0483821e+08 | J65: ='Country Model'!J112+'Country Model'!AJ112 -> 98401833 | K65: ='Country Model'!K112+'Country Model'!AK112 -> 91597791 | L65: ='Country Model'!L112+'Country Model'!AL112 -> 84412043 | ... AD65: ='Country Model'!AD112+'Country Model'!BD112 -> 1.3338042e+08 | AE65: =SUM(E65:AD65) -> 2.2429862e+09 | AG65: =AG64+1 -> 61
AG66: =AG65+1 -> 62
B67: 4g. Diarrhea deaths | AG67: =AG66+1 -> 63
D68: No roadmap | E68: ='Country Model'!E117+'Country Model'!AE117 -> 133.85373 | F68: ='Country Model'!F117+'Country Model'!AF117 -> 139.24405 | G68: ='Country Model'!G117+'Country Model'!AG117 -> 144.86204 | H68: ='Country Model'!H117+'Country Model'!AH117 -> 2920.9273 | I68: ='Country Model'!I117+'Country Model'!AI117 -> 3024.6792 | J68: ='Country Model'!J117+'Country Model'!AJ117 -> 3132.1994 | K68: ='Country Model'!K117+'Country Model'!AK117 -> 3243.6289 | L68: ='Country Model'!L117+'Country Model'!AL117 -> 3359.1143 | ... AD68: ='Country Model'!AD117+'Country Model'!BD117 -> 6337.9061 | AE68: =SUM(E68:AD68) -> 101980.6 | AG68: =AG67+1 -> 64
D69: Roadmap | E69: ='Country Model'!E118+'Country Model'!AE118 -> 133.85373 | F69: ='Country Model'!F118+'Country Model'!AF118 -> 139.24405 | G69: ='Country Model'!G118+'Country Model'!AG118 -> 144.86204 | H69: ='Country Model'!H118+'Country Model'!AH118 -> 2712.2897 | I69: ='Country Model'!I118+'Country Model'!AI118 -> 2592.5822 | J69: ='Country Model'!J118+'Country Model'!AJ118 -> 2461.0138 | K69: ='Country Model'!K118+'Country Model'!AK118 -> 2316.8778 | L69: ='Country Model'!L118+'Country Model'!AL118 -> 2159.4306 | ... AD69: ='Country Model'!AD118+'Country Model'!BD118 -> 3490.513 | AE69: =SUM(E69:AD69) -> 58156.471 | AG69: =AG68+1 -> 65

Sheet Country Model
A1: ='User Inputs'!F5 -> Malawi
A2: =IF($EQI$8="Crisis","Crisis Country","")
A3: A | B3: B | C3: C | D3: D | E3: E | F3: F | G3: G | H3: H | I3: I | J3: J | K3: K | L3: L | M3: M | N3: N | O3: O | P3: P | Q3: Q | R3: R | S3: S | T3: T | U3: U | V3: V | W3: W | X3: X | Y3: Y | Z3: Z | AA3: AA | AB3: AB | AC3: AC | AD3: AD | AE3: AE | AF3: AF | AG3: AG | AH3: AH | AI3: AI | AJ3: AJ | AK3: AK | AL3: AL | AM3: AM | AN3: AN | AO3: AO | AP3: AP | AQ3: AQ | AR3: AR | AS3: AS | AT3: AT | AU3: AU | AV3: AV | AW3: AW | AX3: AX | AY3: AY | AZ3: AZ | BA3: BA | BB3: BB | BC3: BC | BD3: BD | BE3: BE | BF3: BF | BG3: BG | BH3: BH | BI3: BI | BJ3: BJ | BK3: BK | BL3: BL | BM3: BM | BN3: BN | BO3: BO | BP3: BP | BQ3: BQ | BR3: BR | BS3: BS | BT3: BT | BU3: BU | BV3: BV | BW3: BW | BX3: BX | BY3: BY | BZ3: BZ | CA3: CA | CB3: CB | CC3: CC | CD3: CD | CE3: CE | CF3: CF | CG3: CG | CH3: CH | CI3: CI | CJ3: CJ | CK3: CK | CL3: CL | CM3: CM | CN3: CN | CO3: CO | CP3: CP | CQ3: CQ | CR3: CR | CS3: CS | CT3: CT | CU3: CU | CV3: CV | CW3: CW | CX3: CX | CY3: CY | CZ3: CZ | DA3: DA | DB3: DB | DC3: DC | DD3: DD | DE3: DE | DF3: DF | DG3: DG | DH3: DH | DI3: DI | DJ3: DJ | DK3: DK | DL3: DL | DM3: DM | DN3: DN | DO3: DO | DP3: DP | DQ3: DQ | DR3: DR | DS3: DS | DT3: DT | DU3: DU | DV3: DV | DW3: DW | DX3: DX | DY3: DY | DZ3: DZ | EA3: EA | EB3: EB | EC3: EC | ED3: ED | EE3: EE | EF3: EF | EG3: EG | EH3: EH | EI3: EI | EJ3: EJ | EK3: EK | EL3: EL | EM3: EM | EN3: EN | EO3: EO | EP3: EP | EQ3: EQ | ER3: ER | ES3: ES | ET3: ET | EU3: EU | EV3: EV | EW3: EW | EX3: EX | EY3: EY | EZ3: EZ | FA3: FA | FB3: FB | FC3: FC | FD3: FD | FE3: FE | FF3: FF | FG3: FG | FH3: FH | FI3: FI | FJ3: FJ | FK3: FK | FL3: FL | FM3: FM | FN3: FN | FO3: FO | FP3: FP | FQ3: FQ | FR3: FR | FS3: FS | FT3: FT | FU3: FU | FV3: FV | FW3: FW | FX3: FX | FY3: FY | FZ3: FZ | GA3: GA | GB3: GB | GC3: GC | GD3: GD | GE3: GE | GF3: GF | GG3: GG | GH3: GH | GI3: GI | GJ3: GJ | GK3: GK | GL3: GL | GM3: GM | GN3: GN | GO3: GO | GP3: GP | GQ3: GQ | GR3: GR | GS3: GS | GT3: GT | GU3: GU | GV3: GV | GW3: GW | GX3: GX | GY3: GY | GZ3: GZ | HA3: HA | HB3: HB | HC3: HC | HD3: HD | HE3: HE | HF3: HF | HG3: HG | HH3: HH | HI3: HI | HJ3: HJ | HK3: HK | HL3: HL | HM3: HM | HN3: HN | HO3: HO | HP3: HP | HQ3: HQ | HR3: HR | HS3: HS | HT3: HT | HU3: HU | HV3: HV | HW3: HW | HX3: HX | HY3: HY | HZ3: HZ | IA3: IA | IB3: IB | IC3: IC | ID3: ID | IE3: IE | IF3: IF | IG3: IG | IH3: IH | II3: II | IJ3: IJ | IK3: IK | IL3: IL | IM3: IM | IN3: IN | IO3: IO | IP3: IP | IQ3: IQ | IR3: IR | IS3: IS | IT3: IT | IU3: IU | IV3: IV | IW3: IW | IX3: IX | IY3: IY | IZ3: IZ | JA3: JA | JB3: JB | JC3: JC | JD3: JD | JE3: JE | JF3: JF | JG3: JG | JH3: JH | JI3: JI | JJ3: JJ | JK3: JK | JL3: JL | JM3: JM | JN3: JN | JO3: JO | JP3: JP | JQ3: JQ | JR3: JR | JS3: JS | JT3: JT | JU3: JU | JV3: JV | JW3: JW | JX3: JX | JY3: JY | JZ3: JZ | KA3: KA | KB3: KB | KC3: KC | KD3: KD | KE3: KE | KF3: KF | KG3: KG | KH3: KH | KI3: KI | KJ3: KJ | KK3: KK | KL3: KL | KM3: KM | KN3: KN | KO3: KO | KP3: KP | KQ3: KQ | KR3: KR | KS3: KS | KT3: KT | KU3: KU | KV3: KV | KW3: KW | KX3: KX | KY3: KY | KZ3: KZ | LA3: LA | LB3: LB | LC3: LC | LD3: LD | LE3: LE | LF3: LF | LG3: LG | LH3: LH | LI3: LI | LJ3: LJ | LK3: LK | LL3: LL | LM3: LM | LN3: LN | LO3: LO | LP3: LP | LQ3: LQ | LR3: LR | LS3: LS | LT3: LT | LU3: LU | LV3: LV | LW3: LW | LX3: LX | LY3: LY | LZ3: LZ | MA3: MA | MB3: MB | MC3: MC | MD3: MD | ME3: ME | MF3: MF | MG3: MG | MH3: MH | MI3: MI | MJ3: MJ | MK3: MK | ML3: ML | MM3: MM | MN3: MN | MO3: MO | MP3: MP | MQ3: MQ | MR3: MR | MS3: MS | MT3: MT | MU3: MU | MV3: MV | MW3: MW | MX3: MX | MY3: MY | MZ3: MZ | NA3: NA | NB3: NB | NC3: NC | ND3: ND | NE3: NE | NF3: NF | NG3: NG | NH3: NH | NI3: NI | NJ3: NJ | NK3: NK | NL3: NL | NM3: NM | NN3: NN | NO3: NO | NP3: NP | NQ3: NQ | NR3: NR | NS3: NS | NT3: NT | NU3: NU | NV3: NV | NW3: NW | NX3: NX | NY3: NY | NZ3: NZ | OA3: OA | OB3: OB | OC3: OC | OD3: OD | OE3: OE | OF3: OF | OG3: OG | OH3: OH | OI3: OI | OJ3: OJ | OK3: OK | OL3: OL | OM3: OM | ON3: ON | OO3: OO | OP3: OP | OQ3: OQ | OR3: OR | OS3: OS | OT3: OT | OU3: OU | OV3: OV | OW3: OW | OX3: OX | OY3: OY | OZ3: OZ | PA3: PA | PB3: PB | PC3: PC | PD3: PD | PE3: PE | PF3: PF | PG3: PG | PH3: PH | PI3: PI | PJ3: PJ | PK3: PK | PL3: PL | PM3: PM | PN3: PN | PO3: PO | PP3: PP | PQ3: PQ | PR3: PR | PS3: PS | PT3: PT | PU3: PU | PV3: PV | PW3: PW | PX3: PX | PY3: PY | PZ3: PZ | QA3: QA | QB3: QB | QC3: QC | QD3: QD | QE3: QE | QF3: QF | QG3: QG | QH3: QH | QI3: QI | QJ3: QJ | QK3: QK | QL3: QL | QM3: QM | QN3: QN | QO3: QO | QP3: QP | QQ3: QQ | QR3: QR | QS3: QS | QT3: QT | QU3: QU | QV3: QV | QW3: QW | QX3: QX | QY3: QY | QZ3: QZ | RA3: RA | RB3: RB | RC3: RC | RD3: RD | RE3: RE | RF3: RF | RG3: RG | RH3: RH | RI3: RI | RJ3: RJ | RK3: RK | RL3: RL | RM3: RM | RN3: RN | RO3: RO | RP3: RP | RQ3: RQ | RR3: RR | RS3: RS | RT3: RT | RU3: RU | RV3: RV | RW3: RW | RX3: RX | RY3: RY | RZ3: RZ | SA3: SA | SB3: SB | SC3: SC | SD3: SD | SE3: SE | SF3: SF | SG3: SG | SH3: SH | SI3: SI | SJ3: SJ | SK3: SK | SL3: SL | SM3: SM | SN3: SN | SO3: SO | SP3: SP | SQ3: SQ | SR3: SR | SS3: SS | ST3: ST | SU3: SU | SV3: SV | SW3: SW | SX3: SX | SY3: SY | SZ3: SZ | TA3: TA | TB3: TB | TC3: TC | TD3: TD | TE3: TE | TF3: TF | TG3: TG | TH3: TH | TI3: TI | TJ3: TJ | TK3: TK | TL3: TL | TM3: TM | TN3: TN | TO3: TO | TP3: TP | TQ3: TQ | TR3: TR | TS3: TS | TT3: TT | TU3: TU | TV3: TV | TW3: TW | TX3: TX | TY3: TY | TZ3: TZ | UA3: UA | UB3: UB | UC3: UC | UD3: UD | UE3: UE | UF3: UF | UG3: UG | UH3: UH | UI3: UI | UJ3: UJ | UK3: UK | UL3: UL | UM3: UM | UN3: UN | UO3: UO | UP3: UP | UQ3: UQ | UR3: UR | US3: US | UT3: UT | UU3: UU | UV3: UV | UW3: UW | UX3: UX | UY3: UY | UZ3: UZ | VA3: VA | VB3: VB | VC3: VC | VD3: VD | VE3: VE | VF3: VF | VG3: VG | VH3: VH | VI3: VI | VJ3: VJ | VK3: VK | VL3: VL | VM3: VM | VN3: VN | VO3: VO | VP3: VP | VQ3: VQ | VR3: VR | VS3: VS | VT3: VT | VU3: VU | VV3: VV | VW3: VW | VX3: VX | VY3: VY | VZ3: VZ | WA3: WA | WB3: WB | WC3: WC | WD3: WD | WE3: WE | WF3: WF | WG3: WG | WH3: WH | WI3: WI | WJ3: WJ | WK3: WK | WL3: WL | WM3: WM | WN3: WN | WO3: WO | WP3: WP | WQ3: WQ | WR3: WR | WS3: WS | WT3: WT | WU3: WU | WV3: WV | WW3: WW | WX3: WX | WY3: WY | WZ3: WZ | XA3: XA | XB3: XB | XC3: XC | XD3: XD | XE3: XE | XF3: XF | XG3: XG | XH3: XH | XI3: XI | XJ3: XJ | XK3: XK | XL3: XL | XM3: XM | XN3: XN | XO3: XO | XP3: XP | XQ3: XQ | XR3: XR | XS3: XS | XT3: XT | XU3: XU | XV3: XV | XW3: XW | XX3: XX | XY3: XY | XZ3: XZ | YA3: YA | YB3: YB | YC3: YC | YD3: YD | YE3: YE | YF3: YF | YG3: YG | YH3: YH | YI3: YI | YJ3: YJ | YK3: YK | YL3: YL | YM3: YM | YN3: YN | YO3: YO | YP3: YP | YQ3: YQ | YR3: YR | YS3: YS | YT3: YT | YU3: YU | YV3: YV | YW3: YW | YX3: YX | YY3: YY | YZ3: YZ | ZA3: ZA | ZB3: ZB | ZC3: ZC | ZD3: ZD | ZE3: ZE | ZF3: ZF | ZG3: ZG | ZH3: ZH | ZI3: ZI | ZJ3: ZJ | ZK3: ZK | ZL3: ZL | ZM3: ZM | ZN3: ZN | ZO3: ZO | ZP3: ZP | ZQ3: ZQ | ZR3: ZR | ZS3: ZS | ZT3: ZT | ZU3: ZU | ZV3: ZV | ZW3: ZW | ZX3: ZX | ZY3: ZY | ZZ3: ZZ | AAA3: AAA | AAB3: AAB | AAC3: AAC | AAD3: AAD | AAE3: AAE | AAF3: AAF | AAG3: AAG | AAH3: AAH | AAI3: AAI | AAJ3: AAJ | AAK3: AAK | AAL3: AAL | AAM3: AAM | AAN3: AAN | AAO3: AAO | AAP3: AAP | AAQ3: AAQ | AAR3: AAR | AAS3: AAS | AAT3: AAT | AAU3: AAU | AAV3: AAV | AAW3: AAW | AAX3: AAX | AAY3: AAY | AAZ3: AAZ | ABA3: ABA | ABB3: ABB | ABC3: ABC | ABD3: ABD | ABE3: ABE | ABF3: ABF | ABG3: ABG | ABH3: ABH | ABI3: ABI | ABJ3: ABJ | ABK3: ABK | ABL3: ABL | ABM3: ABM | ABN3: ABN | ABO3: ABO | ABP3: ABP | ABQ3: ABQ | ABR3: ABR | ABS3: ABS | ABT3: ABT | ABU3: ABU | ABV3: ABV | ABW3: ABW | ABX3: ABX | ABY3: ABY | ABZ3: ABZ | ACA3: ACA | ACB3: ACB | ACC3: ACC | ACD3: ACD | ACE3: ACE | ACF3: ACF | ACG3: ACG | ACH3: ACH | ACI3: ACI | ACJ3: ACJ | ACK3: ACK | ACL3: ACL | ACM3: ACM | ACN3: ACN | ACO3: ACO | ACP3: ACP | ACQ3: ACQ | ACR3: ACR | ACS3: ACS | ACT3: ACT | ACU3: ACU | ACV3: ACV | ACW3: ACW | ACX3: ACX | ACY3: ACY | ACZ3: ACZ | ADA3: ADA | ADB3: ADB | ADC3: ADC | ADD3: ADD | ADE3: ADE | ADF3: ADF | ADG3: ADG | ADH3: ADH | ADI3: ADI | ADJ3: ADJ | ADK3: ADK | ADL3: ADL | ADM3: ADM | ADN3: ADN | ADO3: ADO | ADP3: ADP | ADQ3: ADQ | ADR3: ADR | ADS3: ADS | ADT3: ADT | ADU3: ADU | ADV3: ADV | ADW3: ADW | ADX3: ADX | ADY3: ADY | ADZ3: ADZ | AEA3: AEA | AEB3: AEB | AEC3: AEC | AED3: AED | AEE3: AEE | AEF3: AEF | AEG3: AEG | AEH3: AEH | AEI3: AEI | AEJ3: AEJ | AEK3: AEK | AEL3: AEL | AEM3: AEM | AEN3: AEN | AEO3: AEO | AEP3: AEP | AEQ3: AEQ | AER3: AER | AES3: AES | AET3: AET | AEU3: AEU | AEV3: AEV | AEW3: AEW | AEX3: AEX | AEY3: AEY | AEZ3: AEZ | AFA3: AFA | AFB3: AFB | AFC3: AFC | AFD3: AFD | AFE3: AFE | AFF3: AFF | AFG3: AFG | AFH3: AFH | AFI3: AFI | AFJ3: AFJ | AFK3: AFK | AFL3: AFL | AFM3: AFM | AFN3: AFN | AFO3: AFO | AFP3: AFP | AFQ3: AFQ | AFR3: AFR | AFS3: AFS | AFT3: AFT | AFU3: AFU | AFV3: AFV | AFW3: AFW | AFX3: AFX | AFY3: AFY | AFZ3: AFZ | AGA3: AGA | AGB3: AGB | AGC3: AGC | AGD3: AGD | AGE3: AGE | AGF3: AGF | AGG3: AGG | AGH3: AGH | AGI3: AGI | AGJ3: AGJ | AGK3: AGK | AGL3: AGL | AGM3: AGM | AGN3: AGN | AGO3: AGO | AGP3: AGP | AGQ3: AGQ | AGR3: AGR | AGS3: AGS | AGT3: AGT | AGU3: AGU | AGV3: AGV | AGW3: AGW | AGX3: AGX | AGY3: AGY | AGZ3: AGZ | AHA3: AHA | AHB3: AHB | AHC3: AHC | AHD3: AHD | AHE3: AHE | AHF3: AHF | AHG3: AHG | AHH3: AHH | AHI3: AHI | AHJ3: AHJ | AHK3: AHK | AHL3: AHL | AHM3: AHM | AHN3: AHN | AHO3: AHO | AHP3: AHP | AHQ3: AHQ | AHR3: AHR | AHS3: AHS | AHT3: AHT | AHU3: AHU | AHV3: AHV | AHW3: AHW | AHX3: AHX | AHY3: AHY | AHZ3: AHZ | AIA3: AIA | AIB3: AIB | AIC3: AIC | AID3: AID | AIE3: AIE | AIF3: AIF | AIG3: AIG | AIH3: AIH | AII3: AII | AIJ3: AIJ | AIK3: AIK | AIL3: AIL | AIM3: AIM | AIN3: AIN | AIO3: AIO | AIP3: AIP | AIQ3: AIQ | AIR3: AIR | AIS3: AIS | AIT3: AIT | AIU3: AIU | AIV3: AIV | AIW3: AIW | AIX3: AIX | AIY3: AIY | AIZ3: AIZ | AJA3: AJA | AJB3: AJB | AJC3: AJC | AJD3: AJD | AJE3: AJE | AJF3: AJF | AJG3: AJG | AJH3: AJH | AJI3: AJI | AJJ3: AJJ | AJK3: AJK | AJL3: AJL | AJM3: AJM | AJN3: AJN | AJO3: AJO | AJP3: AJP | AJQ3: AJQ | AJR3: AJR | AJS3: AJS | AJT3: AJT | AJU3: AJU | AJV3: AJV | AJW3: AJW | AJX3: AJX | AJY3: AJY | AJZ3: AJZ | AKA3: AKA | AKB3: AKB | AKC3: AKC | AKD3: AKD | AKE3: AKE | AKF3: AKF | AKG3: AKG | AKH3: AKH | AKI3: AKI | AKJ3: AKJ | AKK3: AKK | AKL3: AKL | AKM3: AKM | AKN3: AKN | AKO3: AKO | AKP3: AKP | AKQ3: AKQ | AKR3: AKR | AKS3: AKS | AKT3: AKT | AKU3: AKU | AKV3: AKV | AKW3: AKW | AKX3: AKX | AKY3: AKY | AKZ3: AKZ | ALA3: ALA | ALB3: ALB | ALC3: ALC | ALD3: ALD | ALE3: ALE | ALF3: ALF | ALG3: ALG | ALH3: ALH | ALI3: ALI | ALJ3: ALJ | ALK3: ALK | ALL3: ALL | ALM3: ALM | ALN3: ALN | ALO3: ALO | ALP3: ALP | ALQ3: ALQ | ALR3: ALR | ALS3: ALS | ALT3: ALT | ALU3: ALU | ALV3: ALV | ALW3: ALW | ALX3: ALX | ALY3: ALY | ALZ3: ALZ | AMA3: AMA | AMB3: AMB | AMC3: AMC | AMD3: AMD | AME3: AME | AMF3: AMF | AMG3: AMG | AMH3: AMH | AMI3: AMI | AMJ3: AMJ | AMK3: AMK | AML3: AML | AMM3: AMM | AMN3: AMN | AMO3: AMO | AMP3: AMP | AMQ3: AMQ | AMR3: AMR | AMS3: AMS | AMT3: AMT | AMU3: AMU | AMV3: AMV | AMW3: AMW | AMX3: AMX | AMY3: AMY | AMZ3: AMZ | ANA3: ANA | ANB3: ANB | ANC3: ANC | AND3: AND | ANE3: ANE | ANF3: ANF | ANG3: ANG | ANH3: ANH | ANI3: ANI | ANJ3: ANJ | ANK3: ANK | ANL3: ANL | ANM3: ANM | ANN3: ANN | ANO3: ANO | ANP3: ANP | ANQ3: ANQ | ANR3: ANR | ANS3: ANS | ANT3: ANT | ANU3: ANU | ANV3: ANV | ANW3: ANW | ANX3: ANX | ANY3: ANY | ANZ3: ANZ | AOA3: AOA | AOB3: AOB | AOC3: AOC | AOD3: AOD | AOE3: AOE | AOF3: AOF | AOG3: AOG | AOH3: AOH | AOI3: AOI | AOJ3: AOJ | AOK3: AOK | AOL3: AOL | AOM3: AOM | AON3: AON | AOO3: AOO | AOP3: AOP | AOQ3: AOQ | AOR3: AOR | AOS3: AOS | AOT3: AOT | AOU3: AOU | AOV3: AOV | AOW3: AOW | AOX3: AOX | AOY3: AOY | AOZ3: AOZ | APA3: APA | APB3: APB | APC3: APC | APD3: APD | APE3: APE | APF3: APF | APG3: APG | APH3: APH | API3: API | APJ3: APJ | APK3: APK | APL3: APL | APM3: APM | APN3: APN | APO3: APO | APP3: APP | APQ3: APQ | APR3: APR | APS3: APS | APT3: APT | APU3: APU | APV3: APV | APW3: APW | APX3: APX | APY3: APY | APZ3: APZ | AQA3: AQA | AQB3: AQB | AQC3: AQC | AQD3: AQD | AQE3: AQE | AQF3: AQF | AQG3: AQG | AQH3: AQH | AQI3: AQI | AQJ3: AQJ | AQK3: AQK | AQL3: AQL | AQM3: AQM | AQN3: AQN | AQO3: AQO | AQP3: AQP | AQQ3: AQQ | AQR3: AQR | AQS3: AQS | AQT3: AQT | AQU3: AQU | AQV3: AQV | AQW3: AQW | AQX3: AQX | AQY3: AQY | AQZ3: AQZ | ARA3: ARA | ARB3: ARB | ARC3: ARC | ARD3: ARD | ARE3: ARE | ARF3: ARF | ARG3: ARG | ARH3: ARH | ARI3: ARI | ARJ3: ARJ | ARK3: ARK | ARL3: ARL | ARM3: ARM | ARN3: ARN | ARO3: ARO | ARP3: ARP | ARQ3: ARQ | ARR3: ARR | ARS3: ARS | ART3: ART | ARU3: ARU | ARV3: ARV | ARW3: ARW | ARX3: ARX | ARY3: ARY | ARZ3: ARZ | ASA3: ASA | ASB3: ASB | ASC3: ASC | ASD3: ASD | ASE3: ASE | ASF3: ASF | ASG3: ASG | ASH3: ASH | ASI3: ASI | ASJ3: ASJ | ASK3: ASK | ASL3: ASL | ASM3: ASM | ASN3: ASN | ASO3: ASO | ASP3: ASP | ASQ3: ASQ | ASR3: ASR | ASS3: ASS | AST3: AST | ASU3: ASU | ASV3: ASV | ASW3: ASW | ASX3: ASX | ASY3: ASY | ASZ3: ASZ | ATA3: ATA | ATB3: ATB | ATC3: ATC | ATD3: ATD | ATE3: ATE | ATF3: ATF | ATG3: ATG | ATH3: ATH | ATI3: ATI | ATJ3: ATJ | ATK3: ATK | ATL3: ATL | ATM3: ATM | ATN3: ATN | ATO3: ATO | ATP3: ATP | ATQ3: ATQ | ATR3: ATR | ATS3: ATS | ATT3: ATT | ATU3: ATU | ATV3: ATV | ATW3: ATW | ATX3: ATX | ATY3: ATY | ATZ3: ATZ | AUA3: AUA | AUB3: AUB | AUC3: AUC | AUD3: AUD | AUE3: AUE | AUF3: AUF | AUG3: AUG | AUH3: AUH | AUI3: AUI | AUJ3: AUJ | AUK3: AUK | AUL3: AUL | AUM3: AUM | AUN3: AUN | AUO3: AUO | AUP3: AUP | AUQ3: AUQ | AUR3: AUR | AUS3: AUS | AUT3: AUT | AUU3: AUU | AUV3: AUV | AUW3: AUW | AUX3: AUX | AUY3: AUY | AUZ3: AUZ | AVA3: AVA | AVB3: AVB | AVC3: AVC | AVD3: AVD | AVE3: AVE | AVF3: AVF | AVG3: AVG | AVH3: AVH | AVI3: AVI | AVJ3: AVJ | AVK3: AVK | AVL3: AVL | AVM3: AVM | AVN3: AVN | AVO3: AVO | AVP3: AVP | AVQ3: AVQ | AVR3: AVR | AVS3: AVS | AVT3: AVT | AVU3: AVU | AVV3: AVV | AVW3: AVW | AVX3: AVX | AVY3: AVY | AVZ3: AVZ | AWA3: AWA | AWB3: AWB | AWC3: AWC | AWD3: AWD | AWE3: AWE | AWF3: AWF | AWG3: AWG | AWH3: AWH | AWI3: AWI | AWJ3: AWJ | AWK3: AWK | AWL3: AWL | AWM3: AWM | AWN3: AWN | AWO3: AWO | AWP3: AWP | AWQ3: AWQ | AWR3: AWR | AWS3: AWS | AWT3: AWT | AWU3: AWU | AWV3: AWV | AWW3: AWW | AWX3: AWX | AWY3: AWY | AWZ3: AWZ | AXA3: AXA | AXB3: AXB | AXC3: AXC | AXD3: AXD | AXE3: AXE | AXF3: AXF | AXG3: AXG | AXH3: AXH | AXI3: AXI | AXJ3: AXJ | AXK3: AXK | AXL3: AXL | AXM3: AXM | AXN3: AXN | AXO3: AXO | AXP3: AXP | AXQ3: AXQ | AXR3: AXR | AXS3: AXS | AXT3: AXT | AXU3: AXU | AXV3: AXV | AXW3: AXW | AXX3: AXX | AXY3: AXY | AXZ3: AXZ | AYA3: AYA | AYB3: AYB | AYC3: AYC | AYD3: AYD | AYE3: AYE | AYF3: AYF | AYG3: AYG | AYH3: AYH | AYI3: AYI | AYJ3: AYJ | AYK3: AYK | AYL3: AYL | AYM3: AYM | AYN3: AYN | AYO3: AYO | AYP3: AYP | AYQ3: AYQ | AYR3: AYR | AYS3: AYS | AYT3: AYT | AYU3: AYU | AYV3: AYV | AYW3: AYW | AYX3: AYX | AYY3: AYY | AYZ3: AYZ | AZA3: AZA | AZB3: AZB | AZC3: AZC | AZD3: AZD | AZE3: AZE | AZF3: AZF | AZG3: AZG | AZH3: AZH | AZI3: AZI | AZJ3: AZJ | AZK3: AZK | AZL3: AZL | AZM3: AZM | AZN3: AZN | AZO3: AZO | AZP3: AZP | AZQ3: AZQ | AZR3: AZR | AZS3: AZS | AZT3: AZT | AZU3: AZU | AZV3: AZV | AZW3: AZW | AZX3: AZX | AZY3: AZY | AZZ3: AZZ | BAA3: BAA | BAB3: BAB | BAC3: BAC | BAD3: BAD | BAE3: BAE | BAF3: BAF | BAG3: BAG | BAH3: BAH | BAI3: BAI | BAJ3: BAJ | BAK3: BAK | BAL3: BAL | BAM3: BAM | BAN3: BAN | BAO3: BAO | BAP3: BAP | BAQ3: BAQ | BAR3: BAR | BAS3: BAS | BAT3: BAT | BAU3: BAU | BAV3: BAV | BAW3: BAW | BAX3: BAX | BAY3: BAY | BAZ3: BAZ | BBA3: BBA | BBB3: BBB | BBC3: BBC | BBD3: BBD | BBE3: BBE | BBF3: BBF | BBG3: BBG | BBH3: BBH | BBI3: BBI | BBJ3: BBJ | BBK3: BBK | BBL3: BBL | BBM3: BBM | BBN3: BBN | BBO3: BBO | BBP3: BBP | BBQ3: BBQ | BBR3: BBR | BBS3: BBS | BBT3: BBT | BBU3: BBU | BBV3: BBV | BBW3: BBW | BBX3: BBX | BBY3: BBY | BBZ3: BBZ | BCA3: BCA | BCB3: BCB | BCC3: BCC | BCD3: BCD | BCE3: BCE | BCF3: BCF | BCG3: BCG | BCH3: BCH | BCI3: BCI | BCJ3: BCJ | BCK3: BCK | BCL3: BCL | BCM3: BCM | BCN3: BCN | BCO3: BCO | BCP3: BCP | BCQ3: BCQ | BCR3: BCR | BCS3: BCS | BCT3: BCT | BCU3: BCU | BCV3: BCV | BCW3: BCW | BCX3: BCX | BCY3: BCY | BCZ3: BCZ | BDA3: BDA | BDB3: BDB | BDC3: BDC | BDD3: BDD | BDE3: BDE | BDF3: BDF | BDG3: BDG | BDH3: BDH | BDI3: BDI | BDJ3: BDJ | BDK3: BDK | BDL3: BDL | BDM3: BDM | BDN3: BDN | BDO3: BDO | BDP3: BDP | BDQ3: BDQ | BDR3: BDR | BDS3: BDS | BDT3: BDT | BDU3: BDU | BDV3: BDV | BDW3: BDW | BDX3: BDX | BDY3: BDY | BDZ3: BDZ | BEA3: BEA | BEB3: BEB | BEC3: BEC | BED3: BED | BEE3: BEE | BEF3: BEF | BEG3: BEG | BEH3: BEH | BEI3: BEI | BEJ3: BEJ | BEK3: BEK | BEL3: BEL | BEM3: BEM | BEN3: BEN | BEO3: BEO | BEP3: BEP | BEQ3: BEQ | BER3: BER | BES3: BES | BET3: BET | BEU3: BEU | BEV3: BEV | BEW3: BEW | BEX3: BEX | BEY3: BEY | BEZ3: BEZ | BFA3: BFA | BFB3: BFB | BFC3: BFC | BFD3: BFD | BFE3: BFE | BFF3: BFF | BFG3: BFG | BFH3: BFH | BFI3: BFI | BFJ3: BFJ | BFK3: BFK | BFL3: BFL | BFM3: BFM | BFN3: BFN | BFO3: BFO | BFP3: BFP | BFQ3: BFQ | BFR3: BFR | BFS3: BFS | BFT3: BFT | BFU3: BFU | BFV3: BFV | BFW3: BFW | BFX3: BFX | BFY3: BFY | BFZ3: BFZ | BGA3: BGA | BGB3: BGB | BGC3: BGC | BGD3: BGD | BGE3: BGE | BGF3: BGF | BGG3: BGG | BGH3: BGH | BGI3: BGI | BGJ3: BGJ | BGK3: BGK | BGL3: BGL | BGM3: BGM | BGN3: BGN | BGO3: BGO | BGP3: BGP | BGQ3: BGQ | BGR3: BGR | BGS3: BGS | BGT3: BGT | BGU3: BGU | BGV3: BGV | BGW3: BGW | BGX3: BGX | BGY3: BGY | BGZ3: BGZ | BHA3: BHA | BHB3: BHB | BHC3: BHC | BHD3: BHD | BHE3: BHE | BHF3: BHF | BHG3: BHG | BHH3: BHH | BHI3: BHI | BHJ3: BHJ | BHK3: BHK | BHL3: BHL | BHM3: BHM | BHN3: BHN | BHO3: BHO | BHP3: BHP | BHQ3: BHQ | BHR3: BHR | BHS3: BHS | BHT3: BHT | BHU3: BHU | BHV3: BHV | BHW3: BHW | BHX3: BHX | BHY3: BHY | BHZ3: BHZ | BIA3: BIA | BIB3: BIB | BIC3: BIC | BID3: BID | BIE3: BIE | BIF3: BIF | BIG3: BIG | BIH3: BIH | BII3: BII | BIJ3: BIJ | BIK3: BIK | BIL3: BIL | BIM3: BIM | BIN3: BIN | BIO3: BIO | BIP3: BIP | BIQ3: BIQ | BIR3: BIR | BIS3: BIS | BIT3: BIT | BIU3: BIU | BIV3: BIV | BIW3: BIW | BIX3: BIX | BIY3: BIY | BIZ3: BIZ | BJA3: BJA | BJB3: BJB | BJC3: BJC | BJD3: BJD | BJE3: BJE | BJF3: BJF | BJG3: BJG | BJH3: BJH | BJI3: BJI | BJJ3: BJJ | BJK3: BJK | BJL3: BJL | BJM3: BJM | BJN3: BJN | BJO3: BJO | BJP3: BJP | BJQ3: BJQ | BJR3: BJR | BJS3: BJS | BJT3: BJT | BJU3: BJU | BJV3: BJV | BJW3: BJW | BJX3: BJX | BJY3: BJY | BJZ3: BJZ | BKA3: BKA | BKB3: BKB | BKC3: BKC | BKD3: BKD | BKE3: BKE | BKF3: BKF | BKG3: BKG | BKH3: BKH | BKI3: BKI | BKJ3: BKJ | BKK3: BKK | BKL3: BKL | BKM3: BKM | BKN3: BKN | BKO3: BKO | BKP3: BKP | BKQ3: BKQ | BKR3: BKR | BKS3: BKS | BKT3: BKT | BKU3: BKU | BKV3: BKV | BKW3: BKW | BKX3: BKX | BKY3: BKY | BKZ3: BKZ | BLA3: BLA | BLB3: BLB | BLC3: BLC | BLD3: BLD | BLE3: BLE | BLF3: BLF | BLG3: BLG | BLH3: BLH | BLI3: BLI | BLJ3: BLJ | BLK3: BLK | BLL3: BLL | BLM3: BLM | BLN3: BLN | BLO3: BLO | BLP3: BLP | BLQ3: BLQ | BLR3: BLR | BLS3: BLS | BLT3: BLT | BLU3: BLU | BLV3: BLV | BLW3: BLW | BLX3: BLX | BLY3: BLY | BLZ3: BLZ | BMA3: BMA | BMB3: BMB | BMC3: BMC | BMD3: BMD | BME3: BME | BMF3: BMF | BMG3: BMG | BMH3: BMH | BMI3: BMI | BMJ3: BMJ | BMK3: BMK | BML3: BML | BMM3: BMM | BMN3: BMN | BMO3: BMO | BMP3: BMP | BMQ3: BMQ | BMR3: BMR | BMS3: BMS | BMT3: BMT | BMU3: BMU | BMV3: BMV | BMW3: BMW | BMX3: BMX | BMY3: BMY | BMZ3: BMZ | BNA3: BNA | BNB3: BNB | BNC3: BNC | BND3: BND | BNE3: BNE | BNF3: BNF | BNG3: BNG | BNH3: BNH | BNI3: BNI | BNJ3: BNJ | BNK3: BNK | BNL3: BNL | BNM3: BNM | BNN3: BNN | BNO3: BNO | BNP3: BNP | BNQ3: BNQ | BNR3: BNR | BNS3: BNS | BNT3: BNT | BNU3: BNU | BNV3: BNV | BNW3: BNW | BNX3: BNX | BNY3: BNY | BNZ3: BNZ | BOA3: BOA | BOB3: BOB | BOC3: BOC | BOD3: BOD | BOE3: BOE | BOF3: BOF | BOG3: BOG | BOH3: BOH | BOI3: BOI | BOJ3: BOJ | BOK3: BOK | BOL3: BOL | BOM3: BOM | BON3: BON | BOO3: BOO | BOP3: BOP | BOQ3: BOQ | BOR3: BOR | BOS3: BOS | BOT3: BOT | BOU3: BOU | BOV3: BOV | BOW3: BOW | BOX3: BOX | BOY3: BOY | BOZ3: BOZ | BPA3: BPA | BPB3: BPB | BPC3: BPC | BPD3: BPD | BPE3: BPE | BPF3: BPF | BPG3: BPG | BPH3: BPH | BPI3: BPI | BPJ3: BPJ | BPK3: BPK | BPL3: BPL | BPM3: BPM | BPN3: BPN | BPO3: BPO | BPP3: BPP | BPQ3: BPQ | BPR3: BPR | BPS3: BPS | BPT3: BPT | BPU3: BPU | BPV3: BPV | BPW3: BPW | BPX3: BPX | BPY3: BPY | BPZ3: BPZ | BQA3: BQA | BQB3: BQB | BQC3: BQC | BQD3: BQD | BQE3: BQE | BQF3: BQF | BQG3: BQG | BQH3: BQH | BQI3: BQI | BQJ3: BQJ | BQK3: BQK | BQL3: BQL | BQM3: BQM | BQN3: BQN | BQO3: BQO | BQP3: BQP | BQQ3: BQQ | BQR3: BQR | BQS3: BQS | BQT3: BQT | BQU3: BQU | BQV3: BQV | BQW3: BQW | BQX3: BQX | BQY3: BQY | BQZ3: BQZ | BRA3: BRA | BRB3: BRB | BRC3: BRC | BRD3: BRD | BRE3: BRE | BRF3: BRF | BRG3: BRG | BRH3: BRH | BRI3: BRI | BRJ3: BRJ | BRK3: BRK | BRL3: BRL | BRM3: BRM | BRN3: BRN | BRO3: BRO | BRP3: BRP | BRQ3: BRQ | BRR3: BRR | BRS3: BRS | BRT3: BRT | BRU3: BRU | BRV3: BRV | BRW3: BRW | BRX3: BRX | BRY3: BRY | BRZ3: BRZ | BSA3: BSA | BSB3: BSB | BSC3: BSC | BSD3: BSD | BSE3: BSE | BSF3: BSF | BSG3: BSG | BSH3: BSH | BSI3: BSI | BSJ3: BSJ | BSK3: BSK | BSL3: BSL | BSM3: BSM | BSN3: BSN | BSO3: BSO | BSP3: BSP | BSQ3: BSQ | BSR3: BSR | BSS3: BSS | BST3: BST | BSU3: BSU | BSV3: BSV | BSW3: BSW | BSX3: BSX | BSY3: BSY | BSZ3: BSZ | BTA3: BTA | BTB3: BTB | BTC3: BTC | BTD3: BTD | BTE3: BTE | BTF3: BTF | BTG3: BTG | BTH3: BTH | BTI3: BTI | BTJ3: BTJ | BTK3: BTK | BTL3: BTL | BTM3: BTM | BTN3: BTN | BTO3: BTO | BTP3: BTP | BTQ3: BTQ | BTR3: BTR | BTS3: BTS | BTT3: BTT | BTU3: BTU | BTV3: BTV | BTW3: BTW | BTX3: BTX | BTY3: BTY | BTZ3: BTZ | BUA3: BUA | BUB3: BUB | BUC3: BUC | BUD3: BUD | BUE3: BUE | BUF3: BUF | BUG3: BUG | BUH3: BUH | BUI3: BUI | BUJ3: BUJ | BUK3: BUK | BUL3: BUL | BUM3: BUM | BUN3: BUN | BUO3: BUO | BUP3: BUP | BUQ3: BUQ | BUR3: BUR | BUS3: BUS | BUT3: BUT | BUU3: BUU | BUV3: BUV | BUW3: BUW | BUX3: BUX | BUY3: BUY | BUZ3: BUZ | BVA3: BVA | BVB3: BVB | BVC3: BVC | BVD3: BVD | BVE3: BVE | BVF3: BVF | BVG3: BVG | BVH3: BVH | BVI3: BVI | BVJ3: BVJ | BVK3: BVK | BVL3: BVL | BVM3: BVM | BVN3: BVN | BVO3: BVO | BVP3: BVP | BVQ3: BVQ | BVR3: BVR | BVS3: BVS | BVT3: BVT | BVU3: BVU | BVV3: BVV | BVW3: BVW | BVX3: BVX | BVY3: BVY | BVZ3: BVZ | BWA3: BWA | BWB3: BWB | BWC3: BWC | BWD3: BWD | BWE3: BWE | BWF3: BWF | BWG3: BWG | BWH3: BWH | BWI3: BWI | BWJ3: BWJ | BWK3: BWK | BWL3: BWL | BWM3: BWM | BWN3: BWN | BWO3: BWO | BWP3: BWP | BWQ3: BWQ | BWR3: BWR | BWS3: BWS | BWT3: BWT | BWU3: BWU | BWV3: BWV | BWW3: BWW | BWX3: BWX | BWY3: BWY | BWZ3: BWZ | BXA3: BXA | BXB3: BXB | BXC3: BXC | BXD3: BXD | BXE3: BXE | BXF3: BXF | BXG3: BXG | BXH3: BXH | BXI3: BXI | BXJ3: BXJ | BXK3: BXK | BXL3: BXL | BXM3: BXM | BXN3: BXN | BXO3: BXO | BXP3: BXP | BXQ3: BXQ | BXR3: BXR | BXS3: BXS | BXT3: BXT | BXU3: BXU | BXV3: BXV | BXW3: BXW | BXX3: BXX | BXY3: BXY | BXZ3: BXZ | BYA3: BYA | BYB3: BYB | BYC3: BYC | BYD3: BYD | BYE3: BYE | BYF3: BYF | BYG3: BYG | BYH3: BYH | BYI3: BYI | BYJ3: BYJ | BYK3: BYK | BYL3: BYL | BYM3: BYM | BYN3: BYN | BYO3: BYO | BYP3: BYP | BYQ3: BYQ | BYR3: BYR | BYS3: BYS | BYT3: BYT | BYU3: BYU | BYV3: BYV | BYW3: BYW | BYX3: BYX | BYY3: BYY | BYZ3: BYZ | BZA3: BZA | BZB3: BZB | BZC3: BZC | BZD3: BZD | BZE3: BZE | BZF3: BZF | BZG3: BZG | BZH3: BZH | BZI3: BZI | BZJ3: BZJ | BZK3: BZK | BZL3: BZL | BZM3: BZM | BZN3: BZN | BZO3: BZO | BZP3: BZP | BZQ3: BZQ | BZR3: BZR | BZS3: BZS | BZT3: BZT | BZU3: BZU | BZV3: BZV | BZW3: BZW | BZX3: BZX | BZY3: BZY | BZZ3: BZZ | CAA3: CAA | CAB3: CAB | CAC3: CAC | CAD3: CAD | CAE3: CAE | CAF3: CAF | CAG3: CAG | CAH3: CAH | CAI3: CAI | CAJ3: CAJ | CAK3: CAK | CAL3: CAL | CAM3: CAM | CAN3: CAN | CAO3: CAO | CAP3: CAP | CAQ3: CAQ | CAR3: CAR | CAS3: CAS | CAT3: CAT | CAU3: CAU | CAV3: CAV | CAW3: CAW | CAX3: CAX | CAY3: CAY | CAZ3: CAZ | CBA3: CBA | CBB3: CBB | CBC3: CBC | CBD3: CBD | CBE3: CBE | CBF3: CBF | CBG3: CBG | CBH3: CBH | CBI3: CBI | CBJ3: CBJ | CBK3: CBK | CBL3: CBL | CBM3: CBM | CBN3: CBN | CBO3: CBO | CBP3: CBP | CBQ3: CBQ | CBR3: CBR | CBS3: CBS | CBT3: CBT | CBU3: CBU | CBV3: CBV | CBW3: CBW | CBX3: CBX | CBY3: CBY | CBZ3: CBZ | CCA3: CCA | CCB3: CCB | CCC3: CCC | CCD3: CCD | CCE3: CCE | CCF3: CCF | CCG3: CCG | CCH3: CCH | CCI3: CCI | CCJ3: CCJ | CCK3: CCK | CCL3: CCL | CCM3: CCM | CCN3: CCN | CCO3: CCO | CCP3: CCP | CCQ3: CCQ | CCR3: CCR | CCS3: CCS | CCT3: CCT | CCU3: CCU | CCV3: CCV | CCW3: CCW | CCX3: CCX | CCY3: CCY | CCZ3: CCZ | CDA3: CDA | CDB3: CDB | CDC3: CDC | CDD3: CDD | CDE3: CDE | CDF3: CDF | CDG3: CDG | CDH3: CDH | CDI3: CDI | CDJ3: CDJ | CDK3: CDK | CDL3: CDL | CDM3: CDM | CDN3: CDN | CDO3: CDO | CDP3: CDP | CDQ3: CDQ | CDR3: CDR | CDS3: CDS | CDT3: CDT | CDU3: CDU | CDV3: CDV | CDW3: CDW | CDX3: CDX | CDY3: CDY | CDZ3: CDZ | CEA3: CEA | CEB3: CEB | CEC3: CEC | CED3: CED | CEE3: CEE | CEF3: CEF | CEG3: CEG | CEH3: CEH | CEI3: CEI | CEJ3: CEJ | CEK3: CEK | CEL3: CEL | CEM3: CEM | CEN3: CEN | CEO3: CEO | CEP3: CEP | CEQ3: CEQ | CER3: CER | CES3: CES | CET3: CET | CEU3: CEU | CEV3: CEV | CEW3: CEW | CEX3: CEX | CEY3: CEY | CEZ3: CEZ | CFA3: CFA | CFB3: CFB | CFC3: CFC | CFD3: CFD | CFE3: CFE | CFF3: CFF | CFG3: CFG | CFH3: CFH | CFI3: CFI | CFJ3: CFJ | CFK3: CFK | CFL3: CFL | CFM3: CFM | CFN3: CFN | CFO3: CFO | CFP3: CFP | CFQ3: CFQ | CFR3: CFR | CFS3: CFS | CFT3: CFT | CFU3: CFU | CFV3: CFV | CFW3: CFW | CFX3: CFX | CFY3: CFY | CFZ3: CFZ | CGA3: CGA | CGB3: CGB | CGC3: CGC | CGD3: CGD | CGE3: CGE | CGF3: CGF | CGG3: CGG | CGH3: CGH | CGI3: CGI | CGJ3: CGJ | CGK3: CGK | CGL3: CGL | CGM3: CGM | CGN3: CGN | CGO3: CGO | CGP3: CGP | CGQ3: CGQ | CGR3: CGR | CGS3: CGS | CGT3: CGT | CGU3: CGU | CGV3: CGV | CGW3: CGW | CGX3: CGX | CGY3: CGY | CGZ3: CGZ | CHA3: CHA | CHB3: CHB | CHC3: CHC | CHD3: CHD | CHE3: CHE | CHF3: CHF | CHG3: CHG | CHH3: CHH | CHI3: CHI | CHJ3: CHJ | CHK3: CHK | CHL3: CHL | CHM3: CHM | CHN3: CHN | CHO3: CHO | CHP3: CHP | CHQ3: CHQ | CHR3: CHR | CHS3: CHS | CHT3: CHT | CHU3: CHU | CHV3: CHV | CHW3: CHW | CHX3: CHX | CHY3: CHY | CHZ3: CHZ | CIA3: CIA | CIB3: CIB | CIC3: CIC | CID3: CID | CIE3: CIE | CIF3: CIF | CIG3: CIG | CIH3: CIH | CII3: CII | CIJ3: CIJ | CIK3: CIK | CIL3: CIL | CIM3: CIM | CIN3: CIN | CIO3: CIO | CIP3: CIP | CIQ3: CIQ | CIR3: CIR | CIS3: CIS | CIT3: CIT | CIU3: CIU | CIV3: CIV | CIW3: CIW | CIX3: CIX | CIY3: CIY | CIZ3: CIZ | CJA3: CJA | CJB3: CJB | CJC3: CJC | CJD3: CJD | CJE3: CJE | CJF3: CJF | CJG3: CJG | CJH3: CJH | CJI3: CJI | CJJ3: CJJ | CJK3: CJK | CJL3: CJL | CJM3: CJM | CJN3: CJN | CJO3: CJO | CJP3: CJP | CJQ3: CJQ | CJR3: CJR | CJS3: CJS | CJT3: CJT | CJU3: CJU | CJV3: CJV | CJW3: CJW | CJX3: CJX | CJY3: CJY | CJZ3: CJZ | CKA3: CKA | CKB3: CKB | CKC3: CKC | CKD3: CKD | CKE3: CKE | CKF3: CKF | CKG3: CKG | CKH3: CKH | CKI3: CKI | CKJ3: CKJ | CKK3: CKK | CKL3: CKL | CKM3: CKM | CKN3: CKN | CKO3: CKO | CKP3: CKP | CKQ3: CKQ | CKR3: CKR | CKS3: CKS | CKT3: CKT | CKU3: CKU | CKV3: CKV | CKW3: CKW | CKX3: CKX | CKY3: CKY | CKZ3: CKZ | CLA3: CLA | CLB3: CLB | CLC3: CLC | CLD3: CLD | CLE3: CLE | CLF3: CLF | CLG3: CLG | CLH3: CLH | CLI3: CLI | CLJ3: CLJ | CLK3: CLK | CLL3: CLL | CLM3: CLM | CLN3: CLN | CLO3: CLO | CLP3: CLP | CLQ3: CLQ | CLR3: CLR | CLS3: CLS | CLT3: CLT | CLU3: CLU | CLV3: CLV | CLW3: CLW | CLX3: CLX | CLY3: CLY | CLZ3: CLZ | CMA3: CMA | CMB3: CMB | CMC3: CMC | CMD3: CMD | CME3: CME | CMF3: CMF | CMG3: CMG | CMH3: CMH | CMI3: CMI | CMJ3: CMJ | CMK3: CMK | CML3: CML | CMM3: CMM | CMN3: CMN | CMO3: CMO | CMP3: CMP | CMQ3: CMQ | CMR3: CMR | CMS3: CMS | CMT3: CMT | CMU3: CMU | CMV3: CMV | CMW3: CMW | CMX3: CMX | CMY3: CMY | CMZ3: CMZ | CNA3: CNA | CNB3: CNB | CNC3: CNC | CND3: CND | CNE3: CNE | CNF3: CNF | CNG3: CNG | CNH3: CNH | CNI3: CNI | CNJ3: CNJ | CNK3: CNK | CNL3: CNL | CNM3: CNM | CNN3: CNN | CNO3: CNO | CNP3: CNP | CNQ3: CNQ | CNR3: CNR | CNS3: CNS | CNT3: CNT | CNU3: CNU | CNV3: CNV | CNW3: CNW | CNX3: CNX | CNY3: CNY | CNZ3: CNZ | COA3: COA | COB3: COB | COC3: COC | COD3: COD | COE3: COE | COF3: COF | COG3: COG | COH3: COH | COI3: COI | COJ3: COJ | COK3: COK | COL3: COL | COM3: COM | CON3: CON | COO3: COO | COP3: COP | COQ3: COQ | COR3: COR | COS3: COS | COT3: COT | COU3: COU | COV3: COV | COW3: COW | COX3: COX | COY3: COY | COZ3: COZ | CPA3: CPA | CPB3: CPB | CPC3: CPC | CPD3: CPD | CPE3: CPE | CPF3: CPF | CPG3: CPG | CPH3: CPH | CPI3: CPI | CPJ3: CPJ | CPK3: CPK | CPL3: CPL | CPM3: CPM | CPN3: CPN | CPO3: CPO | CPP3: CPP | CPQ3: CPQ | CPR3: CPR | CPS3: CPS | CPT3: CPT | CPU3: CPU | CPV3: CPV | CPW3: CPW | CPX3: CPX | CPY3: CPY | CPZ3: CPZ | CQA3: CQA | CQB3: CQB | CQC3: CQC | CQD3: CQD | CQE3: CQE | CQF3: CQF | CQG3: CQG | CQH3: CQH | CQI3: CQI | CQJ3: CQJ | CQK3: CQK | CQL3: CQL | CQM3: CQM | CQN3: CQN | CQO3: CQO | CQP3: CQP | CQQ3: CQQ | CQR3: CQR | CQS3: CQS | CQT3: CQT | CQU3: CQU | CQV3: CQV | CQW3: CQW | CQX3: CQX | CQY3: CQY | CQZ3: CQZ | CRA3: CRA | CRB3: CRB | CRC3: CRC | CRD3: CRD | CRE3: CRE | CRF3: CRF | CRG3: CRG | CRH3: CRH | CRI3: CRI | CRJ3: CRJ | CRK3: CRK | CRL3: CRL | CRM3: CRM | CRN3: CRN | CRO3: CRO | CRP3: CRP | CRQ3: CRQ | CRR3: CRR | CRS3: CRS | CRT3: CRT | CRU3: CRU | CRV3: CRV | CRW3: CRW | CRX3: CRX | CRY3: CRY | CRZ3: CRZ | CSA3: CSA | CSB3: CSB | CSC3: CSC | CSD3: CSD | CSE3: CSE | CSF3: CSF | CSG3: CSG | CSH3: CSH | CSI3: CSI | CSJ3: CSJ | CSK3: CSK | CSL3: CSL | CSM3: CSM | CSN3: CSN | CSO3: CSO | CSP3: CSP | CSQ3: CSQ | CSR3: CSR | CSS3: CSS | CST3: CST | CSU3: CSU | CSV3: CSV | CSW3: CSW | CSX3: CSX | CSY3: CSY | CSZ3: CSZ | CTA3: CTA | CTB3: CTB | CTC3: CTC | CTD3: CTD | CTE3: CTE | CTF3: CTF | CTG3: CTG | CTH3: CTH | CTI3: CTI | CTJ3: CTJ | CTK3: CTK | CTL3: CTL | CTM3: CTM | CTN3: CTN | CTO3: CTO | CTP3: CTP | CTQ3: CTQ | CTR3: CTR | CTS3: CTS | CTT3: CTT | CTU3: CTU | CTV3: CTV | CTW3: CTW | CTX3: CTX | CTY3: CTY | CTZ3: CTZ | CUA3: CUA | CUB3: CUB | CUC3: CUC | CUD3: CUD | CUE3: CUE | CUF3: CUF | CUG3: CUG | CUH3: CUH | CUI3: CUI | CUJ3: CUJ | CUK3: CUK | CUL3: CUL | CUM3: CUM | CUN3: CUN | CUO3: CUO | CUP3: CUP | CUQ3: CUQ | CUR3: CUR | CUS3: CUS | CUT3: CUT | CUU3: CUU | CUV3: CUV | CUW3: CUW | CUX3: CUX | CUY3: CUY | CUZ3: CUZ | CVA3: CVA | CVB3: CVB | CVC3: CVC | CVD3: CVD | CVE3: CVE | CVF3: CVF | CVG3: CVG | CVH3: CVH | CVI3: CVI | CVJ3: CVJ | CVK3: CVK | CVL3: CVL | CVM3: CVM | CVN3: CVN | CVO3: CVO | CVP3: CVP | CVQ3: CVQ | CVR3: CVR | CVS3: CVS | CVT3: CVT | CVU3: CVU | CVV3: CVV | CVW3: CVW | CVX3: CVX | CVY3: CVY | CVZ3: CVZ | CWA3: CWA | CWB3: CWB | CWC3: CWC | CWD3: CWD | CWE3: CWE | CWF3: CWF | CWG3: CWG | CWH3: CWH | CWI3: CWI | CWJ3: CWJ | CWK3: CWK | CWL3: CWL | CWM3: CWM | CWN3: CWN | CWO3: CWO | CWP3: CWP | CWQ3: CWQ | CWR3: CWR | CWS3: CWS | CWT3: CWT | CWU3: CWU | CWV3: CWV | CWW3: CWW | CWX3: CWX | CWY3: CWY | CWZ3: CWZ | CXA3: CXA | CXB3: CXB | CXC3: CXC | CXD3: CXD | CXE3: CXE | CXF3: CXF | CXG3: CXG | CXH3: CXH | CXI3: CXI | CXJ3: CXJ | CXK3: CXK | CXL3: CXL | CXM3: CXM | CXN3: CXN | CXO3: CXO | CXP3: CXP | CXQ3: CXQ | CXR3: CXR | CXS3: CXS | CXT3: CXT | CXU3: CXU | CXV3: CXV | CXW3: CXW | CXX3: CXX | CXY3: CXY | CXZ3: CXZ | CYA3: CYA | CYB3: CYB | CYC3: CYC | CYD3: CYD | CYE3: CYE | CYF3: CYF | CYG3: CYG | CYH3: CYH | CYI3: CYI | CYJ3: CYJ | CYK3: CYK | CYL3: CYL | CYM3: CYM | CYN3: CYN | CYO3: CYO | CYP3: CYP | CYQ3: CYQ | CYR3: CYR | CYS3: CYS | CYT3: CYT | CYU3: CYU | CYV3: CYV | CYW3: CYW | CYX3: CYX | CYY3: CYY | CYZ3: CYZ | CZA3: CZA | CZB3: CZB | CZC3: CZC | CZD3: CZD | CZE3: CZE | CZF3: CZF | CZG3: CZG | CZH3: CZH | CZI3: CZI | CZJ3: CZJ | CZK3: CZK | CZL3: CZL | CZM3: CZM | CZN3: CZN | CZO3: CZO | CZP3: CZP | CZQ3: CZQ | CZR3: CZR | CZS3: CZS | CZT3: CZT | CZU3: CZU | CZV3: CZV | CZW3: CZW | CZX3: CZX | CZY3: CZY | CZZ3: CZZ | DAA3: DAA | DAB3: DAB | DAC3: DAC | DAD3: DAD | DAE3: DAE | DAF3: DAF | DAG3: DAG | DAH3: DAH | DAI3: DAI | DAJ3: DAJ | DAK3: DAK | DAL3: DAL | DAM3: DAM | DAN3: DAN | DAO3: DAO | DAP3: DAP | DAQ3: DAQ | DAR3: DAR | DAS3: DAS | DAT3: DAT | DAU3: DAU | DAV3: DAV | DAW3: DAW | DAX3: DAX | DAY3: DAY | DAZ3: DAZ | DBA3: DBA | DBB3: DBB | DBC3: DBC | DBD3: DBD | DBE3: DBE | DBF3: DBF | DBG3: DBG | DBH3: DBH | DBI3: DBI | DBJ3: DBJ | DBK3: DBK | DBL3: DBL | DBM3: DBM | DBN3: DBN | DBO3: DBO | DBP3: DBP | DBQ3: DBQ | DBR3: DBR | DBS3: DBS | DBT3: DBT | DBU3: DBU | DBV3: DBV | DBW3: DBW | DBX3: DBX | DBY3: DBY | DBZ3: DBZ | DCA3: DCA | DCB3: DCB | DCC3: DCC | DCD3: DCD | DCE3: DCE | DCF3: DCF | DCG3: DCG | DCH3: DCH | DCI3: DCI | DCJ3: DCJ | DCK3: DCK | DCL3: DCL | DCM3: DCM | DCN3: DCN | DCO3: DCO | DCP3: DCP | DCQ3: DCQ | DCR3: DCR | DCS3: DCS | DCT3: DCT | DCU3: DCU | DCV3: DCV | DCW3: DCW | DCX3: DCX | DCY3: DCY | DCZ3: DCZ | DDA3: DDA | DDB3: DDB | DDC3: DDC | DDD3: DDD | DDE3: DDE | DDF3: DDF | DDG3: DDG | DDH3: DDH | DDI3: DDI | DDJ3: DDJ | DDK3: DDK | DDL3: DDL | DDM3: DDM | DDN3: DDN | DDO3: DDO | DDP3: DDP | DDQ3: DDQ | DDR3: DDR | DDS3: DDS | DDT3: DDT | DDU3: DDU | DDV3: DDV | DDW3: DDW | DDX3: DDX | DDY3: DDY | DDZ3: DDZ | DEA3: DEA | DEB3: DEB | DEC3: DEC | DED3: DED | DEE3: DEE | DEF3: DEF | DEG3: DEG | DEH3: DEH | DEI3: DEI | DEJ3: DEJ | DEK3: DEK | DEL3: DEL | DEM3: DEM | DEN3: DEN | DEO3: DEO | DEP3: DEP | DEQ3: DEQ | DER3: DER | DES3: DES | DET3: DET | DEU3: DEU | DEV3: DEV | DEW3: DEW | DEX3: DEX | DEY3: DEY | DEZ3: DEZ | DFA3: DFA | DFB3: DFB | DFC3: DFC | DFD3: DFD | DFE3: DFE | DFF3: DFF | DFG3: DFG | DFH3: DFH | DFI3: DFI | DFJ3: DFJ | DFK3: DFK | DFL3: DFL | DFM3: DFM | DFN3: DFN | DFO3: DFO | DFP3: DFP | DFQ3: DFQ | DFR3: DFR | DFS3: DFS | DFT3: DFT | DFU3: DFU | DFV3: DFV | DFW3: DFW | DFX3: DFX | DFY3: DFY | DFZ3: DFZ | DGA3: DGA | DGB3: DGB | DGC3: DGC | DGD3: DGD | DGE3: DGE | DGF3: DGF | DGG3: DGG | DGH3: DGH | DGI3: DGI | DGJ3: DGJ | DGK3: DGK | DGL3: DGL | DGM3: DGM | DGN3: DGN | DGO3: DGO | DGP3: DGP | DGQ3: DGQ | DGR3: DGR | DGS3: DGS | DGT3: DGT | DGU3: DGU | DGV3: DGV | DGW3: DGW | DGX3: DGX | DGY3: DGY | DGZ3: DGZ | DHA3: DHA | DHB3: DHB | DHC3: DHC | DHD3: DHD | DHE3: DHE | DHF3: DHF | DHG3: DHG | DHH3: DHH | DHI3: DHI | DHJ3: DHJ | DHK3: DHK | DHL3: DHL | DHM3: DHM | DHN3: DHN | DHO3: DHO | DHP3: DHP | DHQ3: DHQ | DHR3: DHR | DHS3: DHS | DHT3: DHT | DHU3: DHU | DHV3: DHV | DHW3: DHW | DHX3: DHX | DHY3: DHY | DHZ3: DHZ | DIA3: DIA | DIB3: DIB | DIC3: DIC | DID3: DID | DIE3: DIE | DIF3: DIF | DIG3: DIG | DIH3: DIH | DII3: DII | DIJ3: DIJ | DIK3: DIK | DIL3: DIL | DIM3: DIM | DIN3: DIN | DIO3: DIO | DIP3: DIP | DIQ3: DIQ | DIR3: DIR | DIS3: DIS | DIT3: DIT | DIU3: DIU | DIV3: DIV | DIW3: DIW | DIX3: DIX | DIY3: DIY | DIZ3: DIZ | DJA3: DJA | DJB3: DJB | DJC3: DJC | DJD3: DJD | DJE3: DJE | DJF3: DJF | DJG3: DJG | DJH3: DJH | DJI3: DJI | DJJ3: DJJ | DJK3: DJK | DJL3: DJL | DJM3: DJM | DJN3: DJN | DJO3: DJO | DJP3: DJP | DJQ3: DJQ | DJR3: DJR | DJS3: DJS | DJT3: DJT | DJU3: DJU | DJV3: DJV | DJW3: DJW | DJX3: DJX | DJY3: DJY | DJZ3: DJZ | DKA3: DKA | DKB3: DKB | DKC3: DKC | DKD3: DKD | DKE3: DKE | DKF3: DKF | DKG3: DKG | DKH3: DKH | DKI3: DKI | DKJ3: DKJ | DKK3: DKK | DKL3: DKL | DKM3: DKM | DKN3: DKN | DKO3: DKO | DKP3: DKP | DKQ3: DKQ | DKR3: DKR | DKS3: DKS | DKT3: DKT | DKU3: DKU | DKV3: DKV | DKW3: DKW | DKX3: DKX | DKY3: DKY | DKZ3: DKZ | DLA3: DLA | DLB3: DLB | DLC3: DLC | DLD3: DLD | DLE3: DLE | DLF3: DLF | DLG3: DLG | DLH3: DLH | DLI3: DLI | DLJ3: DLJ | DLK3: DLK | DLL3: DLL | DLM3: DLM | DLN3: DLN | DLO3: DLO | DLP3: DLP | DLQ3: DLQ | DLR3: DLR | DLS3: DLS | DLT3: DLT | DLU3: DLU | DLV3: DLV | DLW3: DLW | DLX3: DLX | DLY3: DLY | DLZ3: DLZ | DMA3: DMA | DMB3: DMB | DMC3: DMC | DMD3: DMD | DME3: DME | DMF3: DMF | DMG3: DMG | DMH3: DMH | DMI3: DMI | DMJ3: DMJ | DMK3: DMK | DML3: DML | DMM3: DMM | DMN3: DMN | DMO3: DMO | DMP3: DMP | DMQ3: DMQ | DMR3: DMR | DMS3: DMS | DMT3: DMT | DMU3: DMU | DMV3: DMV | DMW3: DMW | DMX3: DMX | DMY3: DMY | DMZ3: DMZ | DNA3: DNA | DNB3: DNB | DNC3: DNC | DND3: DND | DNE3: DNE | DNF3: DNF | DNG3: DNG | DNH3: DNH | DNI3: DNI | DNJ3: DNJ | DNK3: DNK | DNL3: DNL | DNM3: DNM | DNN3: DNN | DNO3: DNO | DNP3: DNP | DNQ3: DNQ | DNR3: DNR | DNS3: DNS | DNT3: DNT | DNU3: DNU | DNV3: DNV | DNW3: DNW | DNX3: DNX | DNY3: DNY | DNZ3: DNZ | DOA3: DOA | DOB3: DOB | DOC3: DOC | DOD3: DOD | DOE3: DOE | DOF3: DOF | DOG3: DOG | DOH3: DOH | DOI3: DOI | DOJ3: DOJ | DOK3: DOK | DOL3: DOL | DOM3: DOM | DON3: DON | DOO3: DOO | DOP3: DOP | DOQ3: DOQ | DOR3: DOR | DOS3: DOS | DOT3: DOT | DOU3: DOU | DOV3: DOV | DOW3: DOW | DOX3: DOX | DOY3: DOY | DOZ3: DOZ | DPA3: DPA | DPB3: DPB | DPC3: DPC | DPD3: DPD | DPE3: DPE | DPF3: DPF | DPG3: DPG | DPH3: DPH | DPI3: DPI | DPJ3: DPJ | DPK3: DPK | DPL3: DPL | DPM3: DPM | DPN3: DPN | DPO3: DPO | DPP3: DPP | DPQ3: DPQ | DPR3: DPR | DPS3: DPS | DPT3: DPT | DPU3: DPU | DPV3: DPV | DPW3: DPW | DPX3: DPX | DPY3: DPY | DPZ3: DPZ | DQA3: DQA | DQB3: DQB | DQC3: DQC | DQD3: DQD | DQE3: DQE | DQF3: DQF | DQG3: DQG | DQH3: DQH | DQI3: DQI | DQJ3: DQJ | DQK3: DQK | DQL3: DQL | DQM3: DQM | DQN3: DQN | DQO3: DQO | DQP3: DQP | DQQ3: DQQ | DQR3: DQR | DQS3: DQS | DQT3: DQT | DQU3: DQU | DQV3: DQV | DQW3: DQW | DQX3: DQX | DQY3: DQY | DQZ3: DQZ | DRA3: DRA | DRB3: DRB | DRC3: DRC | DRD3: DRD | DRE3: DRE | DRF3: DRF | DRG3: DRG | DRH3: DRH | DRI3: DRI | DRJ3: DRJ | DRK3: DRK | DRL3: DRL | DRM3: DRM | DRN3: DRN | DRO3: DRO | DRP3: DRP | DRQ3: DRQ | DRR3: DRR | DRS3: DRS | DRT3: DRT | DRU3: DRU | DRV3: DRV | DRW3: DRW | DRX3: DRX | DRY3: DRY | DRZ3: DRZ | DSA3: DSA | DSB3: DSB | DSC3: DSC | DSD3: DSD | DSE3: DSE | DSF3: DSF | DSG3: DSG | DSH3: DSH | DSI3: DSI | DSJ3: DSJ | DSK3: DSK | DSL3: DSL | DSM3: DSM | DSN3: DSN | DSO3: DSO | DSP3: DSP | DSQ3: DSQ | DSR3: DSR | DSS3: DSS | DST3: DST | DSU3: DSU | DSV3: DSV | DSW3: DSW | DSX3: DSX | DSY3: DSY | DSZ3: DSZ | DTA3: DTA | DTB3: DTB | DTC3: DTC | DTD3: DTD | DTE3: DTE | DTF3: DTF | DTG3: DTG | DTH3: DTH | DTI3: DTI | DTJ3: DTJ | DTK3: DTK | DTL3: DTL | DTM3: DTM | DTN3: DTN | DTO3: DTO | DTP3: DTP | DTQ3: DTQ | DTR3: DTR | DTS3: DTS | DTT3: DTT | DTU3: DTU | DTV3: DTV | DTW3: DTW | DTX3: DTX | DTY3: DTY | DTZ3: DTZ | DUA3: DUA | DUB3: DUB | DUC3: DUC | DUD3: DUD | DUE3: DUE | DUF3: DUF | DUG3: DUG | DUH3: DUH | DUI3: DUI | DUJ3: DUJ | DUK3: DUK | DUL3: DUL | DUM3: DUM | DUN3: DUN | DUO3: DUO | DUP3: DUP | DUQ3: DUQ | DUR3: DUR | DUS3: DUS | DUT3: DUT | DUU3: DUU | DUV3: DUV | DUW3: DUW | DUX3: DUX | DUY3: DUY | DUZ3: DUZ | DVA3: DVA | DVB3: DVB | DVC3: DVC | DVD3: DVD | DVE3: DVE | DVF3: DVF | DVG3: DVG | DVH3: DVH | DVI3: DVI | DVJ3: DVJ | DVK3: DVK | DVL3: DVL | DVM3: DVM | DVN3: DVN | DVO3: DVO | DVP3: DVP | DVQ3: DVQ | DVR3: DVR | DVS3: DVS | DVT3: DVT | DVU3: DVU | DVV3: DVV | DVW3: DVW | DVX3: DVX | DVY3: DVY | DVZ3: DVZ | DWA3: DWA | DWB3: DWB | DWC3: DWC | DWD3: DWD | DWE3: DWE | DWF3: DWF | DWG3: DWG | DWH3: DWH | DWI3: DWI | DWJ3: DWJ | DWK3: DWK | DWL3: DWL | DWM3: DWM | DWN3: DWN | DWO3: DWO | DWP3: DWP | DWQ3: DWQ | DWR3: DWR | DWS3: DWS | DWT3: DWT | DWU3: DWU | DWV3: DWV | DWW3: DWW | DWX3: DWX | DWY3: DWY | DWZ3: DWZ | DXA3: DXA | DXB3: DXB | DXC3: DXC | DXD3: DXD | DXE3: DXE | DXF3: DXF | DXG3: DXG | DXH3: DXH | DXI3: DXI | DXJ3: DXJ | DXK3: DXK | DXL3: DXL | DXM3: DXM | DXN3: DXN | DXO3: DXO | DXP3: DXP | DXQ3: DXQ | DXR3: DXR | DXS3: DXS | DXT3: DXT | DXU3: DXU | DXV3: DXV | DXW3: DXW | DXX3: DXX | DXY3: DXY | DXZ3: DXZ | DYA3: DYA | DYB3: DYB | DYC3: DYC | DYD3: DYD | DYE3: DYE | DYF3: DYF | DYG3: DYG | DYH3: DYH | DYI3: DYI | DYJ3: DYJ | DYK3: DYK | DYL3: DYL | DYM3: DYM | DYN3: DYN | DYO3: DYO | DYP3: DYP | DYQ3: DYQ | DYR3: DYR | DYS3: DYS | DYT3: DYT | DYU3: DYU | DYV3: DYV | DYW3: DYW | DYX3: DYX | DYY3: DYY | DYZ3: DYZ | DZA3: DZA | DZB3: DZB | DZC3: DZC | DZD3: DZD | DZE3: DZE | DZF3: DZF | DZG3: DZG | DZH3: DZH | DZI3: DZI | DZJ3: DZJ | DZK3: DZK | DZL3: DZL | DZM3: DZM | DZN3: DZN | DZO3: DZO | DZP3: DZP | DZQ3: DZQ | DZR3: DZR | DZS3: DZS | DZT3: DZT | DZU3: DZU | DZV3: DZV | DZW3: DZW | DZX3: DZX | DZY3: DZY | DZZ3: DZZ | EAA3: EAA | EAB3: EAB | EAC3: EAC | EAD3: EAD | EAE3: EAE | EAF3: EAF | EAG3: EAG | EAH3: EAH | EAI3: EAI | EAJ3: EAJ | EAK3: EAK | EAL3: EAL | EAM3: EAM | EAN3: EAN | EAO3: EAO | EAP3: EAP | EAQ3: EAQ | EAR3: EAR | EAS3: EAS | EAT3: EAT | EAU3: EAU | EAV3: EAV | EAW3: EAW | EAX3: EAX | EAY3: EAY | EAZ3: EAZ | EBA3: EBA | EBB3: EBB | EBC3: EBC | EBD3: EBD | EBE3: EBE | EBF3: EBF | EBG3: EBG | EBH3: EBH | EBI3: EBI | EBJ3: EBJ | EBK3: EBK | EBL3: EBL | EBM3: EBM | EBN3: EBN | EBO3: EBO | EBP3: EBP | EBQ3: EBQ | EBR3: EBR | EBS3: EBS | EBT3: EBT | EBU3: EBU | EBV3: EBV | EBW3: EBW | EBX3: EBX | EBY3: EBY | EBZ3: EBZ | ECA3: ECA | ECB3: ECB | ECC3: ECC | ECD3: ECD | ECE3: ECE | ECF3: ECF | ECG3: ECG | ECH3: ECH | ECI3: ECI | ECJ3: ECJ | ECK3: ECK | ECL3: ECL | ECM3: ECM | ECN3: ECN | ECO3: ECO | ECP3: ECP | ECQ3: ECQ | ECR3: ECR | ECS3: ECS | ECT3: ECT | ECU3: ECU | ECV3: ECV | ECW3: ECW | ECX3: ECX | ECY3: ECY | ECZ3: ECZ | EDA3: EDA | EDB3: EDB | EDC3: EDC | EDD3: EDD | EDE3: EDE | EDF3: EDF | EDG3: EDG | EDH3: EDH | EDI3: EDI | EDJ3: EDJ | EDK3: EDK | EDL3: EDL | EDM3: EDM | EDN3: EDN | EDO3: EDO | EDP3: EDP | EDQ3: EDQ | EDR3: EDR | EDS3: EDS | EDT3: EDT | EDU3: EDU | EDV3: EDV | EDW3: EDW | EDX3: EDX | EDY3: EDY | EDZ3: EDZ | EEA3: EEA | EEB3: EEB | EEC3: EEC | EED3: EED | EEE3: EEE | EEF3: EEF | EEG3: EEG | EEH3: EEH | EEI3: EEI | EEJ3: EEJ | EEK3: EEK | EEL3: EEL | EEM3: EEM | EEN3: EEN | EEO3: EEO | EEP3: EEP | EEQ3: EEQ | EER3: EER | EES3: EES | EET3: EET | EEU3: EEU | EEV3: EEV | EEW3: EEW | EEX3: EEX | EEY3: EEY | EEZ3: EEZ | EFA3: EFA | EFB3: EFB | EFC3: EFC | EFD3: EFD | EFE3: EFE | EFF3: EFF | EFG3: EFG | EFH3: EFH | EFI3: EFI | EFJ3: EFJ | EFK3: EFK | EFL3: EFL | EFM3: EFM | EFN3: EFN | EFO3: EFO | EFP3: EFP | EFQ3: EFQ | EFR3: EFR | EFS3: EFS | EFT3: EFT | EFU3: EFU | EFV3: EFV | EFW3: EFW | EFX3: EFX | EFY3: EFY | EFZ3: EFZ | EGA3: EGA | EGB3: EGB | EGC3: EGC | EGD3: EGD | EGE3: EGE | EGF3: EGF | EGG3: EGG | EGH3: EGH | EGI3: EGI | EGJ3: EGJ | EGK3: EGK | EGL3: EGL | EGM3: EGM | EGN3: EGN | EGO3: EGO | EGP3: EGP | EGQ3: EGQ | EGR3: EGR | EGS3: EGS | EGT3: EGT | EGU3: EGU | EGV3: EGV | EGW3: EGW | EGX3: EGX | EGY3: EGY | EGZ3: EGZ | EHA3: EHA | EHB3: EHB | EHC3: EHC | EHD3: EHD | EHE3: EHE | EHF3: EHF | EHG3: EHG | EHH3: EHH | EHI3: EHI | EHJ3: EHJ | EHK3: EHK | EHL3: EHL | EHM3: EHM | EHN3: EHN | EHO3: EHO | EHP3: EHP | EHQ3: EHQ | EHR3: EHR | EHS3: EHS | EHT3: EHT | EHU3: EHU | EHV3: EHV | EHW3: EHW | EHX3: EHX | EHY3: EHY | EHZ3: EHZ | EIA3: EIA | EIB3: EIB | EIC3: EIC | EID3: EID | EIE3: EIE | EIF3: EIF | EIG3: EIG | EIH3: EIH | EII3: EII | EIJ3: EIJ | EIK3: EIK | EIL3: EIL | EIM3: EIM | EIN3: EIN | EIO3: EIO | EIP3: EIP | EIQ3: EIQ | EIR3: EIR | EIS3: EIS | EIT3: EIT | EIU3: EIU | EIV3: EIV | EIW3: EIW | EIX3: EIX | EIY3: EIY | EIZ3: EIZ | EJA3: EJA | EJB3: EJB | EJC3: EJC | EJD3: EJD | EJE3: EJE | EJF3: EJF | EJG3: EJG | EJH3: EJH | EJI3: EJI | EJJ3: EJJ | EJK3: EJK | EJL3: EJL | EJM3: EJM | EJN3: EJN | EJO3: EJO | EJP3: EJP | EJQ3: EJQ | EJR3: EJR | EJS3: EJS | EJT3: EJT | EJU3: EJU | EJV3: EJV | EJW3: EJW | EJX3: EJX | EJY3: EJY | EJZ3: EJZ | EKA3: EKA | EKB3: EKB | EKC3: EKC | EKD3: EKD | EKE3: EKE | EKF3: EKF | EKG3: EKG | EKH3: EKH | EKI3: EKI | EKJ3: EKJ | EKK3: EKK | EKL3: EKL | EKM3: EKM | EKN3: EKN | EKO3: EKO | EKP3: EKP | EKQ3: EKQ | EKR3: EKR | EKS3: EKS | EKT3: EKT | EKU3: EKU | EKV3: EKV | EKW3: EKW | EKX3: EKX | EKY3: EKY | EKZ3: EKZ | ELA3: ELA | ELB3: ELB | ELC3: ELC | ELD3: ELD | ELE3: ELE | ELF3: ELF | ELG3: ELG | ELH3: ELH | ELI3: ELI | ELJ3: ELJ | ELK3: ELK | ELL3: ELL | ELM3: ELM | ELN3: ELN | ELO3: ELO | ELP3: ELP | ELQ3: ELQ | ELR3: ELR | ELS3: ELS | ELT3: ELT | ELU3: ELU | ELV3: ELV | ELW3: ELW | ELX3: ELX | ELY3: ELY | ELZ3: ELZ | EMA3: EMA | EMB3: EMB | EMC3: EMC | EMD3: EMD | EME3: EME | EMF3: EMF | EMG3: EMG | EMH3: EMH | EMI3: EMI | EMJ3: EMJ | EMK3: EMK | EML3: EML | EMM3: EMM | EMN3: EMN | EMO3: EMO | EMP3: EMP | EMQ3: EMQ | EMR3: EMR | EMS3: EMS | EMT3: EMT | EMU3: EMU | EMV3: EMV | EMW3: EMW | EMX3: EMX | EMY3: EMY | EMZ3: EMZ | ENA3: ENA | ENB3: ENB | ENC3: ENC | END3: END | ENE3: ENE | ENF3: ENF | ENG3: ENG | ENH3: ENH | ENI3: ENI | ENJ3: ENJ | ENK3: ENK | ENL3: ENL | ENM3: ENM | ENN3: ENN | ENO3: ENO | ENP3: ENP | ENQ3: ENQ | ENR3: ENR | ENS3: ENS | ENT3: ENT | ENU3: ENU | ENV3: ENV | ENW3: ENW | ENX3: ENX | ENY3: ENY | ENZ3: ENZ | EOA3: EOA | EOB3: EOB | EOC3: EOC | EOD3: EOD | EOE3: EOE | EOF3: EOF | EOG3: EOG | EOH3: EOH | EOI3: EOI | EOJ3: EOJ | EOK3: EOK | EOL3: EOL | EOM3: EOM | EON3: EON | EOO3: EOO | EOP3: EOP | EOQ3: EOQ | EOR3: EOR | EOS3: EOS | EOT3: EOT | EOU3: EOU | EOV3: EOV | EOW3: EOW | EOX3: EOX | EOY3: EOY | EOZ3: EOZ | EPA3: EPA | EPB3: EPB | EPC3: EPC | EPD3: EPD | EPE3: EPE | EPF3: EPF | EPG3: EPG | EPH3: EPH | EPI3: EPI | EPJ3: EPJ | EPK3: EPK | EPL3: EPL | EPM3: EPM | EPN3: EPN | EPO3: EPO | EPP3: EPP | EPQ3: EPQ | EPR3: EPR | EPS3: EPS | EPT3: EPT | EPU3: EPU | EPV3: EPV | EPW3: EPW | EPX3: EPX | EPY3: EPY | EPZ3: EPZ | EQA3: EQA | EQB3: EQB | EQC3: EQC | EQD3: EQD | EQE3: EQE | EQF3: EQF | EQG3: EQG | EQH3: EQH | EQI3: EQI
A4: Country | B4: ISO-3 | C4: Category | D4: Size | E4: UN Region | F4: WHO Region | G4: WB Income Group | H4: GAVI | I4: Population (total, '000) | K4: Elimination plans | N4: Demographic information | CE4: Coverage assumptions for WASH and OCV (%), according to Roadmap timings | NG4: Population to be reached with interventions | XG4: Unit costs per capita in 2018 prices (US$) for non-response preventive interventions | YL4: WASH capital costs by year for increasing coverage | AEL4: WASH O&M costs by year for serving population with service | AKL4: OCV Costs of preventive campaigns (when WASH implemented) | AML4: OCV Costs of preventive campaigns (when WASH not implemented) | AOL4: Cholera health impacts - business as usual | ASN4: Cholera health outcomes - WASH alone | AWP4: Cholera health outcomes - OCV alone | BAR4: Cholera health outcomes - WASH and OCV | BET4: Cholera health outcomes - WASH, OCV and CM | BIV4: Other costs for cholera response | BJZ4: Costs by year for responding to outbreaks - business as usual | BRZ4: Costs by year for responding to outbreaks - WASH only | BZZ4: Costs by year for responding to outbreaks - OCV alone | CHZ4: Costs by year for responding to outbreaks - WASH and OCV | CPZ4: Costs by year for responding to outbreaks - WASH, OCV and CM | CXZ4: Loss of value due to cholera deaths | DHZ4: Other health impacts | DIT4: Total costs of treatment seeking (other health) | DMT4: Loss of health-related productive time (other health) | DQT4: Loss of value of life (other health) | DUT4: Gain in water access-related productive time | DWT4: Gain in sanitation access time | DYT4: GDP | DYU4: Value of loss of life (VSL) | DYW4: Value of hour of time lost | DYY4: Increase in value of time | DZA4: Discount rate | DZB4: Coverage | DZG4: Coverage | DZL4: Gains in time (water = hours per HH per day; sanitation = hours per person) | EBO4: Total cases (other health) | EIY4: Total deaths (other health)
C5: 1=high capacity | D5: 2=large and/or low capacity country | H5: Country | I5: 2018 | K5: Roadmap start | L5: Elimination year (80% WASH coverage in hotspots) | M5: Years to reach elimination year | N5: Pop. Growth (annual) | P5: Population age breakdown | V5: Av. HH size | X5: Hotspot Population (thousands) | CE5: Water Coverage - Basic+ (target) | EM5: Sanitation Coverage - Basic (target) | GU5: Hygiene Coverage - Basic (target) | JC5: OCV Coverage (target) when WASH implemented | LG5: OCV Coverage (target) when WASH not implemented | NG5: Population numbers to be reached with Water | PG5: Population numbers to be reached with Sanitation | RG5: Population numbers to be reached with Hygiene | TG5: Population numbers to be reached with OCV (with WASH) | VG5: Population numbers to be reached with OCV (alone) | XG5: Water (long term) - basic plus treatment | XO5: Sanitation (long term) | XU5: Hygiene (long term) | YA5: Emergency WASH (for population still not covered with 1 or more WASH element) | YC5: Costs of enhanced surveillance (annual lump sum) | YE5: OCV Campaigns | YL5: Water | AAL5: Sanitation | ACL5: Hygiene | AEL5: Water | AGL5: Sanitation | AIL5: Hygiene | AKL5: OCV | AML5: OCV | AOL5: Predicted number of cholera cases - business as usual | AQM5: Predicted number of cholera deaths - business as usual | ASN5: Predicted number of cholera cases - WASH alone | AUO5: Predicted number of cholera deaths - WASH alone | AWP5: Predicted number of cholera cases - OCV alone | AYQ5: Predicted number of cholera deaths - OCV alone | BAR5: Predicted number of cholera cases - WASH and OCV | BCS5: Predicted number of cholera deaths - WASH and OCV | BET5: Predicted number of cholera cases - WASH, OCV and CM | BGU5: Predicted number of cholera deaths - WASH, OCV and CM | BIV5: % population in outbreak covered with emergency WASH | BIX5: % overall hotspot population receiving emergency OCV during outbreak | BIZ5: % cases in outbreak needing intensive medical care (i.e. more than ORS) | BJB5: % cases in outbreak covered with ORS case management (regular) | BJD5: % cases in outbreak covered with intensive case management (regular) | BJF5: Under CM strengthening, % population in outbreak receiving needed CM | BJH5: Unit costs | BJX5: Days of productive time loss/adult/cholera case | BJZ5: Emergency WASH | BLZ5: Emergency OCV | BNZ5: Case management of cholera cases | BPZ5: Loss of productive time of adults | BRZ5: Emergency WASH | BTZ5: Emergency OCV | BVZ5: Case management for cholera cases | BXZ5: Loss of productive time of adults | BZZ5: Emergency WASH | CBZ5: Emergency OCV | CDZ5: Case Management | CFZ5: Loss of productive time of adults | CHZ5: Emergency WASH | CJZ5: Emergency OCV | CLZ5: Case Management | CNZ5: Loss of productive time of adults | CPZ5: Emergency WASH | CRZ5: Emergency OCV | CTZ5: Case Management | CVZ5: Loss of productive time of adults | CXZ5: Business as usual | CZZ5: WASH alone | DBZ5: OCV alone | DDZ5: WASH and OCV | DFZ5: WASH, OCV and CM | DHZ5: Health assumptions | DIB5: Diarrhea prevalence rate | DIH5: Treatment seeking rate | DIJ5: Cost/case seeking treatment | DIL5: % cases treated ORS | DIN5: Days off work for diarrhea (adults) | DIP5: National diarrhea deaths | DIR5: Hotspot diarrhea deaths | DIT5: Business as usual | DKT5: WASH | DMT5: Business as usual | DOT5: WASH | DQT5: Business as usual | DST5: WASH | DUT5: Water | DWT5: Sanitation | DZA5: Global | DZB5: Urban | DZG5: Rural | DZL5: Urban | DZQ5: Rural | EBO5: Business as usual | EDO5: WASH | EFO5: Averted cases | EHO5: Aggregated cases BAU | EIA5: Aggregated cases WASH | EIM5: Aggregated cases averted | EIY5: Business as usual | EKY5: WASH | EMY5: Averted deaths | EOY5: Aggregated deaths BAU | EPK5: Aggregated deaths WASH | EPW5: Aggregated deaths averted
C6: 2=moderate capacity | D6: 1=small and/or high capacity country | N6: Urban | O6: Rural | P6: Urban | S6: Rural | V6: Urban | W6: Rural | X6: Total and distribution | AE6: Urban | BE6: Rural | CE6: Urban | DI6: Rural | EM6: Urban | FQ6: Rural | GU6: Urban | HY6: Rural | JC6: Urban | KG6: Rural | LG6: Urban | MG6: Rural | NG6: Urban | OG6: Rural | PG6: Urban | QG6: Rural | RG6: Urban | SG6: Rural | TG6: Urban | UG6: Rural | VG6: Urban | WG6: Rural | XG6: Urban (tubewell) | XK6: Rural (tubewell) | XO6: Urban (pit latrine) | XR6: Rural (pit latrine) | XU6: Urban | XX6: Rural | YA6: Urban | YB6: Rural | YC6: EPI surveillance | YD6: Lab capacity | YE6: Vaccine unit price / dose 2018 | YF6: Vaccine unit price / dose 2019-2020 | YG6: Vaccine unit price / dose, after 2020 | YH6: Doses | YI6: Vaccine Delivery Cost | YL6: Urban | ZL6: Rural | AAL6: Urban | ABL6: Rural | ACL6: Urban | ADL6: Rural | AEL6: Urban | AFL6: Rural | AGL6: Urban | AHL6: Rural | AIL6: Urban | AJL6: Rural | AKL6: Urban | ALL6: Rural | AML6: Urban | ANL6: Rural | AOL6: Total | AOM6: Urban | APM6: Rural | AQM6: Total | AQN6: Urban | ARN6: Rural | ASN6: Protective | ASO6: Urban | ATO6: Rural | AUO6: Protective | AUP6: Urban | AVP6: Rural | AWP6: Protective | AWQ6: Urban | AXQ6: Rural | AYQ6: Protective | AYR6: Urban | AZR6: Rural | BAR6: Protective | BAS6: Urban | BBS6: Rural | BCS6: Protective | BCT6: Urban | BDT6: Rural | BET6: Incremental | BEU6: Urban | BFU6: Rural | BGU6: Incremental | BGV6: Urban | BHV6: Rural | BJH6: Emergency WASH (cost per unserved person) | BJJ6: Proportion of hotspot (population) with outbreaks per year | BJL6: OCV vaccine | BJP6: OCV Delivery Costs per Unit (Person) | BJR6: ORS cost per case | BJT6: Intensive CM (routine) | BJV6: Intensive CM (strengthened) | BJZ6: Urban | BKZ6: Rural | BLZ6: Urban | BMZ6: Rural | BNZ6: Urban | BOZ6: Rural | BPZ6: Urban | BQZ6: Rural | BRZ6: Urban | BSZ6: Rural | BTZ6: Urban | BUZ6: Rural | BVZ6: Urban | BWZ6: Rural | BXZ6: Urban | BYZ6: Rural | BZZ6: Urban | CAZ6: Rural | CBZ6: Urban | CCZ6: Rural | CDZ6: Urban | CEZ6: Rural | CFZ6: Urban | CGZ6: Rural | CHZ6: Urban | CIZ6: Rural | CJZ6: Urban | CKZ6: Rural | CLZ6: Urban | CMZ6: Rural | CNZ6: Urban | COZ6: Rural | CPZ6: Urban | CQZ6: Rural | CRZ6: Urban | CSZ6: Rural | CTZ6: Urban | CUZ6: Rural | CVZ6: Urban | CWZ6: Rural | CXZ6: Urban | CYZ6: Rural | CZZ6: Urban | DAZ6: Rural | DBZ6: Urban | DCZ6: Rural | DDZ6: Urban | DEZ6: Rural | DFZ6: Urban | DGZ6: Rural | DHZ6: % attribution | DIA6: % reduction from | DIB6: Urban | DIE6: Rural | DIH6: Urban | DII6: Rural | DIJ6: Urban | DIK6: Rural | DIL6: Urban | DIM6: Rural | DIN6: Urban | DIO6: Rural | DIT6: Urban | DJT6: Rural | DKT6: Urban | DLT6: Rural | DMT6: Urban | DNT6: Rural | DOT6: Urban | DPT6: Rural | DQT6: Urban | DRT6: Rural | DST6: Urban | DTT6: Rural | DUT6: Urban | DVT6: Rural | DWT6: Urban | DXT6: Rural | DZA6: 0.05 | DZB6: Limited service | DZC6: Unimproved service | DZD6: Surface water | DZE6: Percent with OD | DZF6: Percent shared | DZG6: Limited service | DZH6: Unimproved service | DZI6: Surface water | DZJ6: Percent with OD | DZK6: Percent shared | DZL6: Water | DZO6: Sanitation | DZP6: From shared | DZQ6: Water | DZT6: Sanitation | EBO6: Urban | ECO6: Rural | EDO6: Urban | EEO6: Rural | EFO6: Urban | EGO6: Rural | EHO6: Urban | EHS6: Rural | EHW6: Total | EIA6: Urban | EIE6: Rural | EII6: Total | EIM6: Urban | EIQ6: Rural | EIU6: Total | EIY6: Urban | EJY6: Rural | EKY6: Urban | ELY6: Rural | EMY6: Urban | ENY6: Rural | EOY6: Urban | EPC6: Rural | EPG6: Total | EPK6: Urban | EPO6: Rural | EPS6: Total | EPW6: Urban | EQA6: Rural | EQE6: Total
C7: 3=crisis country (control only) | I7: Urban | J7: Rural | M7: 13 | P7: 0-4 years | Q7: 5-14 years | R7: 15+ years | S7: 0-4 years | T7: 5-14 years | U7: 15+ years | V7: Members | W7: Members | X7: FOR CALCULS: Total pop at risk | Y7: MEMORY: MEAN | Z7: MEMORY: LOW | AA7: MEMORY: HIGH | AB7: Urban | AC7: Rural | AD7: TOTAL 2018 Hotspot | AE7: 2015 | AF7: 2016 | AG7: 2017 | AH7: 2018 | AI7: 2019 | AJ7: 2020 | AK7: 2021 | AL7: 2022 | AM7: 2023 | AN7: 2024 | AO7: 2025 | AP7: 2026 | AQ7: 2027 | AR7: 2028 | AS7: 2029 | AT7: 2030 | AU7: 2031 | AV7: 2032 | AW7: 2033 | AX7: 2034 | AY7: 2035 | AZ7: 2036 | BA7: 2037 | BB7: 2038 | BC7: 2039 | BD7: 2040 | BE7: 2015 | BF7: 2016 | BG7: 2017 | BH7: 2018 | BI7: 2019 | BJ7: 2020 | BK7: 2021 | BL7: 2022 | BM7: 2023 | BN7: 2024 | BO7: 2025 | BP7: 2026 | BQ7: 2027 | BR7: 2028 | BS7: 2029 | BT7: 2030 | BU7: 2031 | BV7: 2032 | BW7: 2033 | BX7: 2034 | BY7: 2035 | BZ7: 2036 | CA7: 2037 | CB7: 2038 | CC7: 2039 | CD7: 2040 | CE7: Coverage adjustment factor | CF7: Target in elimination year | CG7: Basic JMP 2015 | CH7: Free contam. | CI7: 2015 | CJ7: 2016 | CK7: 2017 | CL7: 2018 | CM7: 2019 | CN7: 2020 | CO7: 2021 | CP7: 2022 | CQ7: 2023 | CR7: 2024 | CS7: 2025 | CT7: 2026 | CU7: 2027 | CV7: 2028 | CW7: 2029 | CX7: 2030 | CY7: 2031 | CZ7: 2032 | DA7: 2033 | DB7: 2034 | DC7: 2035 | DD7: 2036 | DE7: 2037 | DF7: 2038 | DG7: 2039 | DH7: 2040 | DI7: Coverage adjustment factor | DJ7: Target in elimination year | DK7: Basic JMP 2015 | DL7: Free contam. | DM7: 2015 | DN7: 2016 | DO7: 2017 | DP7: 2018 | DQ7: 2019 | DR7: 2020 | DS7: 2021 | DT7: 2022 | DU7: 2023 | DV7: 2024 | DW7: 2025 | DX7: 2026 | DY7: 2027 | DZ7: 2028 | EA7: 2029 | EB7: 2030 | EC7: 2031 | ED7: 2032 | EE7: 2033 | EF7: 2034 | EG7: 2035 | EH7: 2036 | EI7: 2037 | EJ7: 2038 | EK7: 2039 | EL7: 2040 | EM7: Coverage adjustment factor | EN7: Target in elimination year | EO7: Basic JMP 2015 | EP7: Dummy | EQ7: 2015 | ER7: 2016 | ES7: 2017 | ET7: 2018 | EU7: 2019 | EV7: 2020 | EW7: 2021 | EX7: 2022 | EY7: 2023 | EZ7: 2024 | FA7: 2025 | FB7: 2026 | FC7: 2027 | FD7: 2028 | FE7: 2029 | FF7: 2030 | FG7: 2031 | FH7: 2032 | FI7: 2033 | FJ7: 2034 | FK7: 2035 | FL7: 2036 | FM7: 2037 | FN7: 2038 | FO7: 2039 | FP7: 2040 | FQ7: Coverage adjustment factor | FR7: Target in elimination year | FS7: Basic JMP 2015 | FT7: Dummy | FU7: 2015 | FV7: 2016 | FW7: 2017 | FX7: 2018 | FY7: 2019 | FZ7: 2020 | GA7: 2021 | GB7: 2022 | GC7: 2023 | GD7: 2024 | GE7: 2025 | GF7: 2026 | GG7: 2027 | GH7: 2028 | GI7: 2029 | GJ7: 2030 | GK7: 2031 | GL7: 2032 | GM7: 2033 | GN7: 2034 | GO7: 2035 | GP7: 2036 | GQ7: 2037 | GR7: 2038 | GS7: 2039 | GT7: 2040 | GU7: Coverage adjustment factor | GV7: Target in elimination year | GW7: Basic JMP 2015 | GX7: Dummy | GY7: 2015 | GZ7: 2016 | HA7: 2017 | HB7: 2018 | HC7: 2019 | HD7: 2020 | HE7: 2021 | HF7: 2022 | HG7: 2023 | HH7: 2024 | HI7: 2025 | HJ7: 2026 | HK7: 2027 | HL7: 2028 | HM7: 2029 | HN7: 2030 | HO7: 2031 | HP7: 2032 | HQ7: 2033 | HR7: 2034 | HS7: 2035 | HT7: 2036 | HU7: 2037 | HV7: 2038 | HW7: 2039 | HX7: 2040 | HY7: Coverage adjustment factor | HZ7: Target in elimination year | IA7: Basic JMP 2015 | IB7: Dummy | IC7: 2015 | ID7: 2016 | IE7: 2017 | IF7: 2018 | IG7: 2019 | IH7: 2020 | II7: 2021 | IJ7: 2022 | IK7: 2023 | IL7: 2024 | IM7: 2025 | IN7: 2026 | IO7: 2027 | IP7: 2028 | IQ7: 2029 | IR7: 2030 | IS7: 2031 | IT7: 2032 | IU7: 2033 | IV7: 2034 | IW7: 2035 | IX7: 2036 | IY7: 2037 | IZ7: 2038 | JA7: 2039 | JB7: 2040 | JC7: OCV frequency (years) | JD7: Total number of times hotspots are fully vaccinated with 2 doses | JE7: Target coverage (2 doses) | JF7: Years to implement campaign | JG7: 2015 | JH7: 2016 | JI7: 2017 | JJ7: 2018 | JK7: 2019 | JL7: 2020 | JM7: 2021 | JN7: 2022 | JO7: 2023 | JP7: 2024 | JQ7: 2025 | JR7: 2026 | JS7: 2027 | JT7: 2028 | JU7: 2029 | JV7: 2030 | JW7: 2031 | JX7: 2032 | JY7: 2033 | JZ7: 2034 | KA7: 2035 | KB7: 2036 | KC7: 2037 | KD7: 2038 | KE7: 2039 | KF7: 2040 | KG7: 2015 | KH7: 2016 | KI7: 2017 | KJ7: 2018 | KK7: 2019 | KL7: 2020 | KM7: 2021 | KN7: 2022 | KO7: 2023 | KP7: 2024 | KQ7: 2025 | KR7: 2026 | KS7: 2027 | KT7: 2028 | KU7: 2029 | KV7: 2030 | KW7: 2031 | KX7: 2032 | KY7: 2033 | KZ7: 2034 | LA7: 2035 | LB7: 2036 | LC7: 2037 | LD7: 2038 | LE7: 2039 | LF7: 2040 | LG7: 2015 | LH7: 2016 | LI7: 2017 | LJ7: 2018 | LK7: 2019 | LL7: 2020 | LM7: 2021 | LN7: 2022 | LO7: 2023 | LP7: 2024 | LQ7: 2025 | LR7: 2026 | LS7: 2027 | LT7: 2028 | LU7: 2029 | LV7: 2030 | LW7: 2031 | LX7: 2032 | LY7: 2033 | LZ7: 2034 | MA7: 2035 | MB7: 2036 | MC7: 2037 | MD7: 2038 | ME7: 2039 | MF7: 2040 | MG7: 2015 | MH7: 2016 | MI7: 2017 | MJ7: 2018 | MK7: 2019 | ML7: 2020 | MM7: 2021 | MN7: 2022 | MO7: 2023 | MP7: 2024 | MQ7: 2025 | MR7: 2026 | MS7: 2027 | MT7: 2028 | MU7: 2029 | MV7: 2030 | MW7: 2031 | MX7: 2032 | MY7: 2033 | MZ7: 2034 | NA7: 2035 | NB7: 2036 | NC7: 2037 | ND7: 2038 | NE7: 2039 | NF7: 2040 | NG7: 2015 | NH7: 2016 | NI7: 2017 | NJ7: 2018 | NK7: 2019 | NL7: 2020 | NM7: 2021 | NN7: 2022 | NO7: 2023 | NP7: 2024 | NQ7: 2025 | NR7: 2026 | NS7: 2027 | NT7: 2028 | NU7: 2029 | NV7: 2030 | NW7: 2031 | NX7: 2032 | NY7: 2033 | NZ7: 2034 | OA7: 2035 | OB7: 2036 | OC7: 2037 | OD7: 2038 | OE7: 2039 | OF7: 2040 | OG7: 2015 | OH7: 2016 | OI7: 2017 | OJ7: 2018 | OK7: 2019 | OL7: 2020 | OM7: 2021 | ON7: 2022 | OO7: 2023 | OP7: 2024 | OQ7: 2025 | OR7: 2026 | OS7: 2027 | OT7: 2028 | OU7: 2029 | OV7: 2030 | OW7: 2031 | OX7: 2032 | OY7: 2033 | OZ7: 2034 | PA7: 2035 | PB7: 2036 | PC7: 2037 | PD7: 2038 | PE7: 2039 | PF7: 2040 | PG7: 2015 | PH7: 2016 | PI7: 2017 | PJ7: 2018 | PK7: 2019 | PL7: 2020 | PM7: 2021 | PN7: 2022 | PO7: 2023 | PP7: 2024 | PQ7: 2025 | PR7: 2026 | PS7: 2027 | PT7: 2028 | PU7: 2029 | PV7: 2030 | PW7: 2031 | PX7: 2032 | PY7: 2033 | PZ7: 2034 | QA7: 2035 | QB7: 2036 | QC7: 2037 | QD7: 2038 | QE7: 2039 | QF7: 2040 | QG7: 2015 | QH7: 2016 | QI7: 2017 | QJ7: 2018 | QK7: 2019 | QL7: 2020 | QM7: 2021 | QN7: 2022 | QO7: 2023 | QP7: 2024 | QQ7: 2025 | QR7: 2026 | QS7: 2027 | QT7: 2028 | QU7: 2029 | QV7: 2030 | QW7: 2031 | QX7: 2032 | QY7: 2033 | QZ7: 2034 | RA7: 2035 | RB7: 2036 | RC7: 2037 | RD7: 2038 | RE7: 2039 | RF7: 2040 | RG7: 2015 | RH7: 2016 | RI7: 2017 | RJ7: 2018 | RK7: 2019 | RL7: 2020 | RM7: 2021 | RN7: 2022 | RO7: 2023 | RP7: 2024 | RQ7: 2025 | RR7: 2026 | RS7: 2027 | RT7: 2028 | RU7: 2029 | RV7: 2030 | RW7: 2031 | RX7: 2032 | RY7: 2033 | RZ7: 2034 | SA7: 2035 | SB7: 2036 | SC7: 2037 | SD7: 2038 | SE7: 2039 | SF7: 2040 | SG7: 2015 | SH7: 2016 | SI7: 2017 | SJ7: 2018 | SK7: 2019 | SL7: 2020 | SM7: 2021 | SN7: 2022 | SO7: 2023 | SP7: 2024 | SQ7: 2025 | SR7: 2026 | SS7: 2027 | ST7: 2028 | SU7: 2029 | SV7: 2030 | SW7: 2031 | SX7: 2032 | SY7: 2033 | SZ7: 2034 | TA7: 2035 | TB7: 2036 | TC7: 2037 | TD7: 2038 | TE7: 2039 | TF7: 2040 | TG7: 2015 | TH7: 2016 | TI7: 2017 | TJ7: 2018 | TK7: 2019 | TL7: 2020 | TM7: 2021 | TN7: 2022 | TO7: 2023 | TP7: 2024 | TQ7: 2025 | TR7: 2026 | TS7: 2027 | TT7: 2028 | TU7: 2029 | TV7: 2030 | TW7: 2031 | TX7: 2032 | TY7: 2033 | TZ7: 2034 | UA7: 2035 | UB7: 2036 | UC7: 2037 | UD7: 2038 | UE7: 2039 | UF7: 2040 | UG7: 2015 | UH7: 2016 | UI7: 2017 | UJ7: 2018 | UK7: 2019 | UL7: 2020 | UM7: 2021 | UN7: 2022 | UO7: 2023 | UP7: 2024 | UQ7: 2025 | UR7: 2026 | US7: 2027 | UT7: 2028 | UU7: 2029 | UV7: 2030 | UW7: 2031 | UX7: 2032 | UY7: 2033 | UZ7: 2034 | VA7: 2035 | VB7: 2036 | VC7: 2037 | VD7: 2038 | VE7: 2039 | VF7: 2040 | VG7: 2015 | VH7: 2016 | VI7: 2017 | VJ7: 2018 | VK7: 2019 | VL7: 2020 | VM7: 2021 | VN7: 2022 | VO7: 2023 | VP7: 2024 | VQ7: 2025 | VR7: 2026 | VS7: 2027 | VT7: 2028 | VU7: 2029 | VV7: 2030 | VW7: 2031 | VX7: 2032 | VY7: 2033 | VZ7: 2034 | WA7: 2035 | WB7: 2036 | WC7: 2037 | WD7: 2038 | WE7: 2039 | WF7: 2040 | WG7: 2015 | WH7: 2016 | WI7: 2017 | WJ7: 2018 | WK7: 2019 | WL7: 2020 | WM7: 2021 | WN7: 2022 | WO7: 2023 | WP7: 2024 | WQ7: 2025 | WR7: 2026 | WS7: 2027 | WT7: 2028 | WU7: 2029 | WV7: 2030 | WW7: 2031 | WX7: 2032 | WY7: 2033 | WZ7: 2034 | XA7: 2035 | XB7: 2036 | XC7: 2037 | XD7: 2038 | XE7: 2039 | XF7: 2040 | XG7: New facility cost | XH7: New facility life | XI7: Treatment | XJ7: O&M cost | XK7: New facility cost | XL7: New facility life | XM7: Treatment | XN7: Operations cost | XO7: New facility cost | XP7: New facility life | XQ7: Operations cost | XR7: New facility cost | XS7: New facility life | XT7: Operations cost | XU7: New facility cost | XV7: New facility life | XW7: Operations cost | XX7: New facility cost | XY7: New facility life | XZ7: Operations cost | YI7: Urban | YJ7: Rural | YK7: Source | YL7: 2015 | YM7: 2016 | YN7: 2017 | YO7: 2018 | YP7: 2019 | YQ7: 2020 | YR7: 2021 | YS7: 2022 | YT7: 2023 | YU7: 2024 | YV7: 2025 | YW7: 2026 | YX7: 2027 | YY7: 2028 | YZ7: 2029 | ZA7: 2030 | ZB7: 2031 | ZC7: 2032 | ZD7: 2033 | ZE7: 2034 | ZF7: 2035 | ZG7: 2036 | ZH7: 2037 | ZI7: 2038 | ZJ7: 2039 | ZK7: 2040 | ZL7: 2015 | ZM7: 2016 | ZN7: 2017 | ZO7: 2018 | ZP7: 2019 | ZQ7: 2020 | ZR7: 2021 | ZS7: 2022 | ZT7: 2023 | ZU7: 2024 | ZV7: 2025 | ZW7: 2026 | ZX7: 2027 | ZY7: 2028 | ZZ7: 2029 | AAA7: 2030 | AAB7: 2031 | AAC7: 2032 | AAD7: 2033 | AAE7: 2034 | AAF7: 2035 | AAG7: 2036 | AAH7: 2037 | AAI7: 2038 | AAJ7: 2039 | AAK7: 2040 | AAL7: 2015 | AAM7: 2016 | AAN7: 2017 | AAO7: 2018 | AAP7: 2019 | AAQ7: 2020 | AAR7: 2021 | AAS7: 2022 | AAT7: 2023 | AAU7: 2024 | AAV7: 2025 | AAW7: 2026 | AAX7: 2027 | AAY7: 2028 | AAZ7: 2029 | ABA7: 2030 | ABB7: 2031 | ABC7: 2032 | ABD7: 2033 | ABE7: 2034 | ABF7: 2035 | ABG7: 2036 | ABH7: 2037 | ABI7: 2038 | ABJ7: 2039 | ABK7: 2040 | ABL7: 2015 | ABM7: 2016 | ABN7: 2017 | ABO7: 2018 | ABP7: 2019 | ABQ7: 2020 | ABR7: 2021 | ABS7: 2022 | ABT7: 2023 | ABU7: 2024 | ABV7: 2025 | ABW7: 2026 | ABX7: 2027 | ABY7: 2028 | ABZ7: 2029 | ACA7: 2030 | ACB7: 2031 | ACC7: 2032 | ACD7: 2033 | ACE7: 2034 | ACF7: 2035 | ACG7: 2036 | ACH7: 2037 | ACI7: 2038 | ACJ7: 2039 | ACK7: 2040 | ACL7: 2015 | ACM7: 2016 | ACN7: 2017 | ACO7: 2018 | ACP7: 2019 | ACQ7: 2020 | ACR7: 2021 | ACS7: 2022 | ACT7: 2023 | ACU7: 2024 | ACV7: 2025 | ACW7: 2026 | ACX7: 2027 | ACY7: 2028 | ACZ7: 2029 | ADA7: 2030 | ADB7: 2031 | ADC7: 2032 | ADD7: 2033 | ADE7: 2034 | ADF7: 2035 | ADG7: 2036 | ADH7: 2037 | ADI7: 2038 | ADJ7: 2039 | ADK7: 2040 | ADL7: 2015 | ADM7: 2016 | ADN7: 2017 | ADO7: 2018 | ADP7: 2019 | ADQ7: 2020 | ADR7: 2021 | ADS7: 2022 | ADT7: 2023 | ADU7: 2024 | ADV7: 2025 | ADW7: 2026 | ADX7: 2027 | ADY7: 2028 | ADZ7: 2029 | AEA7: 2030 | AEB7: 2031 | AEC7: 2032 | AED7: 2033 | AEE7: 2034 | AEF7: 2035 | AEG7: 2036 | AEH7: 2037 | AEI7: 2038 | AEJ7: 2039 | AEK7: 2040 | AEL7: 2015 | AEM7: 2016 | AEN7: 2017 | AEO7: 2018 | AEP7: 2019 | AEQ7: 2020 | AER7: 2021 | AES7: 2022 | AET7: 2023 | AEU7: 2024 | AEV7: 2025 | AEW7: 2026 | AEX7: 2027 | AEY7: 2028 | AEZ7: 2029 | AFA7: 2030 | AFB7: 2031 | AFC7: 2032 | AFD7: 2033 | AFE7: 2034 | AFF7: 2035 | AFG7: 2036 | AFH7: 2037 | AFI7: 2038 | AFJ7: 2039 | AFK7: 2040 | AFL7: 2015 | AFM7: 2016 | AFN7: 2017 | AFO7: 2018 | AFP7: 2019 | AFQ7: 2020 | AFR7: 2021 | AFS7: 2022 | AFT7: 2023 | AFU7: 2024 | AFV7: 2025 | AFW7: 2026 | AFX7: 2027 | AFY7: 2028 | AFZ7: 2029 | AGA7: 2030 | AGB7: 2031 | AGC7: 2032 | AGD7: 2033 | AGE7: 2034 | AGF7: 2035 | AGG7: 2036 | AGH7: 2037 | AGI7: 2038 | AGJ7: 2039 | AGK7: 2040 | AGL7: 2015 | AGM7: 2016 | AGN7: 2017 | AGO7: 2018 | AGP7: 2019 | AGQ7: 2020 | AGR7: 2021 | AGS7: 2022 | AGT7: 2023 | AGU7: 2024 | AGV7: 2025 | AGW7: 2026 | AGX7: 2027 | AGY7: 2028 | AGZ7: 2029 | AHA7: 2030 | AHB7: 2031 | AHC7: 2032 | AHD7: 2033 | AHE7: 2034 | AHF7: 2035 | AHG7: 2036 | AHH7: 2037 | AHI7: 2038 | AHJ7: 2039 | AHK7: 2040 | AHL7: 2015 | AHM7: 2016 | AHN7: 2017 | AHO7: 2018 | AHP7: 2019 | AHQ7: 2020 | AHR7: 2021 | AHS7: 2022 | AHT7: 2023 | AHU7: 2024 | AHV7: 2025 | AHW7: 2026 | AHX7: 2027 | AHY7: 2028 | AHZ7: 2029 | AIA7: 2030 | AIB7: 2031 | AIC7: 2032 | AID7: 2033 | AIE7: 2034 | AIF7: 2035 | AIG7: 2036 | AIH7: 2037 | AII7: 2038 | AIJ7: 2039 | AIK7: 2040 | AIL7: 2015 | AIM7: 2016 | AIN7: 2017 | AIO7: 2018 | AIP7: 2019 | AIQ7: 2020 | AIR7: 2021 | AIS7: 2022 | AIT7: 2023 | AIU7: 2024 | AIV7: 2025 | AIW7: 2026 | AIX7: 2027 | AIY7: 2028 | AIZ7: 2029 | AJA7: 2030 | AJB7: 2031 | AJC7: 2032 | AJD7: 2033 | AJE7: 2034 | AJF7: 2035 | AJG7: 2036 | AJH7: 2037 | AJI7: 2038 | AJJ7: 2039 | AJK7: 2040 | AJL7: 2015 | AJM7: 2016 | AJN7: 2017 | AJO7: 2018 | AJP7: 2019 | AJQ7: 2020 | AJR7: 2021 | AJS7: 2022 | AJT7: 2023 | AJU7: 2024 | AJV7: 2025 | AJW7: 2026 | AJX7: 2027 | AJY7: 2028 | AJZ7: 2029 | AKA7: 2030 | AKB7: 2031 | AKC7: 2032 | AKD7: 2033 | AKE7: 2034 | AKF7: 2035 | AKG7: 2036 | AKH7: 2037 | AKI7: 2038 | AKJ7: 2039 | AKK7: 2040 | AKL7: 2015 | AKM7: 2016 | AKN7: 2017 | AKO7: 2018 | AKP7: 2019 | AKQ7: 2020 | AKR7: 2021 | AKS7: 2022 | AKT7: 2023 | AKU7: 2024 | AKV7: 2025 | AKW7: 2026 | AKX7: 2027 | AKY7: 2028 | AKZ7: 2029 | ALA7: 2030 | ALB7: 2031 | ALC7: 2032 | ALD7: 2033 | ALE7: 2034 | ALF7: 2035 | ALG7: 2036 | ALH7: 2037 | ALI7: 2038 | ALJ7: 2039 | ALK7: 2040 | ALL7: 2015 | ALM7: 2016 | ALN7: 2017 | ALO7: 2018 | ALP7: 2019 | ALQ7: 2020 | ALR7: 2021 | ALS7: 2022 | ALT7: 2023 | ALU7: 2024 | ALV7: 2025 | ALW7: 2026 | ALX7: 2027 | ALY7: 2028 | ALZ7: 2029 | AMA7: 2030 | AMB7: 2031 | AMC7: 2032 | AMD7: 2033 | AME7: 2034 | AMF7: 2035 | AMG7: 2036 | AMH7: 2037 | AMI7: 2038 | AMJ7: 2039 | AMK7: 2040 | AML7: 2015 | AMM7: 2016 | AMN7: 2017 | AMO7: 2018 | AMP7: 2019 | AMQ7: 2020 | AMR7: 2021 | AMS7: 2022 | AMT7: 2023 | AMU7: 2024 | AMV7: 2025 | AMW7: 2026 | AMX7: 2027 | AMY7: 2028 | AMZ7: 2029 | ANA7: 2030 | ANB7: 2031 | ANC7: 2032 | AND7: 2033 | ANE7: 2034 | ANF7: 2035 | ANG7: 2036 | ANH7: 2037 | ANI7: 2038 | ANJ7: 2039 | ANK7: 2040 | ANL7: 2015 | ANM7: 2016 | ANN7: 2017 | ANO7: 2018 | ANP7: 2019 | ANQ7: 2020 | ANR7: 2021 | ANS7: 2022 | ANT7: 2023 | ANU7: 2024 | ANV7: 2025 | ANW7: 2026 | ANX7: 2027 | ANY7: 2028 | ANZ7: 2029 | AOA7: 2030 | AOB7: 2031 | AOC7: 2032 | AOD7: 2033 | AOE7: 2034 | AOF7: 2035 | AOG7: 2036 | AOH7: 2037 | AOI7: 2038 | AOJ7: 2039 | AOK7: 2040 | AOL7: 2015 | AOM7: 2015 | AON7: 2016 | AOO7: 2017 | AOP7: 2018 | AOQ7: 2019 | AOR7: 2020 | AOS7: 2021 | AOT7: 2022 | AOU7: 2023 | AOV7: 2024 | AOW7: 2025 | AOX7: 2026 | AOY7: 2027 | AOZ7: 2028 | APA7: 2029 | APB7: 2030 | APC7: 2031 | APD7: 2032 | APE7: 2033 | APF7: 2034 | APG7: 2035 | APH7: 2036 | API7: 2037 | APJ7: 2038 | APK7: 2039 | APL7: 2040 | APM7: 2015 | APN7: 2016 | APO7: 2017 | APP7: 2018 | APQ7: 2019 | APR7: 2020 | APS7: 2021 | APT7: 2022 | APU7: 2023 | APV7: 2024 | APW7: 2025 | APX7: 2026 | APY7: 2027 | APZ7: 2028 | AQA7: 2029 | AQB7: 2030 | AQC7: 2031 | AQD7: 2032 | AQE7: 2033 | AQF7: 2034 | AQG7: 2035 | AQH7: 2036 | AQI7: 2037 | AQJ7: 2038 | AQK7: 2039 | AQL7: 2040 | AQM7: 2015 | AQN7: 2015 | AQO7: 2016 | AQP7: 2017 | AQQ7: 2018 | AQR7: 2019 | AQS7: 2020 | AQT7: 2021 | AQU7: 2022 | AQV7: 2023 | AQW7: 2024 | AQX7: 2025 | AQY7: 2026 | AQZ7: 2027 | ARA7: 2028 | ARB7: 2029 | ARC7: 2030 | ARD7: 2031 | ARE7: 2032 | ARF7: 2033 | ARG7: 2034 | ARH7: 2035 | ARI7: 2036 | ARJ7: 2037 | ARK7: 2038 | ARL7: 2039 | ARM7: 2040 | ARN7: 2015 | ARO7: 2016 | ARP7: 2017 | ARQ7: 2018 | ARR7: 2019 | ARS7: 2020 | ART7: 2021 | ARU7: 2022 | ARV7: 2023 | ARW7: 2024 | ARX7: 2025 | ARY7: 2026 | ARZ7: 2027 | ASA7: 2028 | ASB7: 2029 | ASC7: 2030 | ASD7: 2031 | ASE7: 2032 | ASF7: 2033 | ASG7: 2034 | ASH7: 2035 | ASI7: 2036 | ASJ7: 2037 | ASK7: 2038 | ASL7: 2039 | ASM7: 2040 | ASN7: effect | ASO7: 2015 | ASP7: 2016 | ASQ7: 2017 | ASR7: 2018 | ASS7: 2019 | AST7: 2020 | ASU7: 2021 | ASV7: 2022 | ASW7: 2023 | ASX7: 2024 | ASY7: 2025 | ASZ7: 2026 | ATA7: 2027 | ATB7: 2028 | ATC7: 2029 | ATD7: 2030 | ATE7: 2031 | ATF7: 2032 | ATG7: 2033 | ATH7: 2034 | ATI7: 2035 | ATJ7: 2036 | ATK7: 2037 | ATL7: 2038 | ATM7: 2039 | ATN7: 2040 | ATO7: 2015 | ATP7: 2016 | ATQ7: 2017 | ATR7: 2018 | ATS7: 2019 | ATT7: 2020 | ATU7: 2021 | ATV7: 2022 | ATW7: 2023 | ATX7: 2024 | ATY7: 2025 | ATZ7: 2026 | AUA7: 2027 | AUB7: 2028 | AUC7: 2029 | AUD7: 2030 | AUE7: 2031 | AUF7: 2032 | AUG7: 2033 | AUH7: 2034 | AUI7: 2035 | AUJ7: 2036 | AUK7: 2037 | AUL7: 2038 | AUM7: 2039 | AUN7: 2040 | AUO7: effect | AUP7: 2015 | AUQ7: 2016 | AUR7: 2017 | AUS7: 2018 | AUT7: 2019 | AUU7: 2020 | AUV7: 2021 | AUW7: 2022 | AUX7: 2023 | AUY7: 2024 | AUZ7: 2025 | AVA7: 2026 | AVB7: 2027 | AVC7: 2028 | AVD7: 2029 | AVE7: 2030 | AVF7: 2031 | AVG7: 2032 | AVH7: 2033 | AVI7: 2034 | AVJ7: 2035 | AVK7: 2036 | AVL7: 2037 | AVM7: 2038 | AVN7: 2039 | AVO7: 2040 | AVP7: 2015 | AVQ7: 2016 | AVR7: 2017 | AVS7: 2018 | AVT7: 2019 | AVU7: 2020 | AVV7: 2021 | AVW7: 2022 | AVX7: 2023 | AVY7: 2024 | AVZ7: 2025 | AWA7: 2026 | AWB7: 2027 | AWC7: 2028 | AWD7: 2029 | AWE7: 2030 | AWF7: 2031 | AWG7: 2032 | AWH7: 2033 | AWI7: 2034 | AWJ7: 2035 | AWK7: 2036 | AWL7: 2037 | AWM7: 2038 | AWN7: 2039 | AWO7: 2040 | AWP7: effect | AWQ7: 2015 | AWR7: 2016 | AWS7: 2017 | AWT7: 2018 | AWU7: 2019 | AWV7: 2020 | AWW7: 2021 | AWX7: 2022 | AWY7: 2023 | AWZ7: 2024 | AXA7: 2025 | AXB7: 2026 | AXC7: 2027 | AXD7: 2028 | AXE7: 2029 | AXF7: 2030 | AXG7: 2031 | AXH7: 2032 | AXI7: 2033 | AXJ7: 2034 | AXK7: 2035 | AXL7: 2036 | AXM7: 2037 | AXN7: 2038 | AXO7: 2039 | AXP7: 2040 | AXQ7: 2015 | AXR7: 2016 | AXS7: 2017 | AXT7: 2018 | AXU7: 2019 | AXV7: 2020 | AXW7: 2021 | AXX7: 2022 | AXY7: 2023 | AXZ7: 2024 | AYA7: 2025 | AYB7: 2026 | AYC7: 2027 | AYD7: 2028 | AYE7: 2029 | AYF7: 2030 | AYG7: 2031 | AYH7: 2032 | AYI7: 2033 | AYJ7: 2034 | AYK7: 2035 | AYL7: 2036 | AYM7: 2037 | AYN7: 2038 | AYO7: 2039 | AYP7: 2040 | AYQ7: effect | AYR7: 2015 | AYS7: 2016 | AYT7: 2017 | AYU7: 2018 | AYV7: 2019 | AYW7: 2020 | AYX7: 2021 | AYY7: 2022 | AYZ7: 2023 | AZA7: 2024 | AZB7: 2025 | AZC7: 2026 | AZD7: 2027 | AZE7: 2028 | AZF7: 2029 | AZG7: 2030 | AZH7: 2031 | AZI7: 2032 | AZJ7: 2033 | AZK7: 2034 | AZL7: 2035 | AZM7: 2036 | AZN7: 2037 | AZO7: 2038 | AZP7: 2039 | AZQ7: 2040 | AZR7: 2015 | AZS7: 2016 | AZT7: 2017 | AZU7: 2018 | AZV7: 2019 | AZW7: 2020 | AZX7: 2021 | AZY7: 2022 | AZZ7: 2023 | BAA7: 2024 | BAB7: 2025 | BAC7: 2026 | BAD7: 2027 | BAE7: 2028 | BAF7: 2029 | BAG7: 2030 | BAH7: 2031 | BAI7: 2032 | BAJ7: 2033 | BAK7: 2034 | BAL7: 2035 | BAM7: 2036 | BAN7: 2037 | BAO7: 2038 | BAP7: 2039 | BAQ7: 2040 | BAR7: effect | BAS7: 2015 | BAT7: 2016 | BAU7: 2017 | BAV7: 2018 | BAW7: 2019 | BAX7: 2020 | BAY7: 2021 | BAZ7: 2022 | BBA7: 2023 | BBB7: 2024 | BBC7: 2025 | BBD7: 2026 | BBE7: 2027 | BBF7: 2028 | BBG7: 2029 | BBH7: 2030 | BBI7: 2031 | BBJ7: 2032 | BBK7: 2033 | BBL7: 2034 | BBM7: 2035 | BBN7: 2036 | BBO7: 2037 | BBP7: 2038 | BBQ7: 2039 | BBR7: 2040 | BBS7: 2015 | BBT7: 2016 | BBU7: 2017 | BBV7: 2018 | BBW7: 2019 | BBX7: 2020 | BBY7: 2021 | BBZ7: 2022 | BCA7: 2023 | BCB7: 2024 | BCC7: 2025 | BCD7: 2026 | BCE7: 2027 | BCF7: 2028 | BCG7: 2029 | BCH7: 2030 | BCI7: 2031 | BCJ7: 2032 | BCK7: 2033 | BCL7: 2034 | BCM7: 2035 | BCN7: 2036 | BCO7: 2037 | BCP7: 2038 | BCQ7: 2039 | BCR7: 2040 | BCS7: effect | BCT7: 2015 | BCU7: 2016 | BCV7: 2017 | BCW7: 2018 | BCX7: 2019 | BCY7: 2020 | BCZ7: 2021 | BDA7: 2022 | BDB7: 2023 | BDC7: 2024 | BDD7: 2025 | BDE7: 2026 | BDF7: 2027 | BDG7: 2028 | BDH7: 2029 | BDI7: 2030 | BDJ7: 2031 | BDK7: 2032 | BDL7: 2033 | BDM7: 2034 | BDN7: 2035 | BDO7: 2036 | BDP7: 2037 | BDQ7: 2038 | BDR7: 2039 | BDS7: 2040 | BDT7: 2015 | BDU7: 2016 | BDV7: 2017 | BDW7: 2018 | BDX7: 2019 | BDY7: 2020 | BDZ7: 2021 | BEA7: 2022 | BEB7: 2023 | BEC7: 2024 | BED7: 2025 | BEE7: 2026 | BEF7: 2027 | BEG7: 2028 | BEH7: 2029 | BEI7: 2030 | BEJ7: 2031 | BEK7: 2032 | BEL7: 2033 | BEM7: 2034 | BEN7: 2035 | BEO7: 2036 | BEP7: 2037 | BEQ7: 2038 | BER7: 2039 | BES7: 2040 | BET7: protect CM | BEU7: 2015 | BEV7: 2016 | BEW7: 2017 | BEX7: 2018 | BEY7: 2019 | BEZ7: 2020 | BFA7: 2021 | BFB7: 2022 | BFC7: 2023 | BFD7: 2024 | BFE7: 2025 | BFF7: 2026 | BFG7: 2027 | BFH7: 2028 | BFI7: 2029 | BFJ7: 2030 | BFK7: 2031 | BFL7: 2032 | BFM7: 2033 | BFN7: 2034 | BFO7: 2035 | BFP7: 2036 | BFQ7: 2037 | BFR7: 2038 | BFS7: 2039 | BFT7: 2040 | BFU7: 2015 | BFV7: 2016 | BFW7: 2017 | BFX7: 2018 | BFY7: 2019 | BFZ7: 2020 | BGA7: 2021 | BGB7: 2022 | BGC7: 2023 | BGD7: 2024 | BGE7: 2025 | BGF7: 2026 | BGG7: 2027 | BGH7: 2028 | BGI7: 2029 | BGJ7: 2030 | BGK7: 2031 | BGL7: 2032 | BGM7: 2033 | BGN7: 2034 | BGO7: 2035 | BGP7: 2036 | BGQ7: 2037 | BGR7: 2038 | BGS7: 2039 | BGT7: 2040 | BGU7: protect CM | BGV7: 2015 | BGW7: 2016 | BGX7: 2017 | BGY7: 2018 | BGZ7: 2019 | BHA7: 2020 | BHB7: 2021 | BHC7: 2022 | BHD7: 2023 | BHE7: 2024 | BHF7: 2025 | BHG7: 2026 | BHH7: 2027 | BHI7: 2028 | BHJ7: 2029 | BHK7: 2030 | BHL7: 2031 | BHM7: 2032 | BHN7: 2033 | BHO7: 2034 | BHP7: 2035 | BHQ7: 2036 | BHR7: 2037 | BHS7: 2038 | BHT7: 2039 | BHU7: 2040 | BHV7: 2015 | BHW7: 2016 | BHX7: 2017 | BHY7: 2018 | BHZ7: 2019 | BIA7: 2020 | BIB7: 2021 | BIC7: 2022 | BID7: 2023 | BIE7: 2024 | BIF7: 2025 | BIG7: 2026 | BIH7: 2027 | BII7: 2028 | BIJ7: 2029 | BIK7: 2030 | BIL7: 2031 | BIM7: 2032 | BIN7: 2033 | BIO7: 2034 | BIP7: 2035 | BIQ7: 2036 | BIR7: 2037 | BIS7: 2038 | BIT7: 2039 | BIU7: 2040 | BIV7: Urban | BIW7: Rural | BIX7: Urban | BIY7: Rural | BIZ7: Urban | BJA7: Rural | BJB7: Urban | BJC7: Rural | BJD7: Urban | BJE7: Rural | BJF7: Urban | BJG7: Rural | BJH7: Urban | BJI7: Rural | BJJ7: Urban | BJK7: Rural | BJL7: Vaccine price (2018) | BJM7: Vaccine price (2019-20) | BJN7: Vaccine price (>2021) | BJO7: Av. doses given per person in outbreak | BJP7: Urban | BJQ7: Rural | BJR7: Urban | BJS7: Rural | BJT7: Urban | BJU7: Rural | BJV7: Urban | BJW7: Rural | BJX7: Urban | BJY7: Rural | BJZ7: 2015 | BKA7: 2016 | BKB7: 2017 | BKC7: 2018 | BKD7: 2019 | BKE7: 2020 | BKF7: 2021 | BKG7: 2022 | BKH7: 2023 | BKI7: 2024 | BKJ7: 2025 | BKK7: 2026 | BKL7: 2027 | BKM7: 2028 | BKN7: 2029 | BKO7: 2030 | BKP7: 2031 | BKQ7: 2032 | BKR7: 2033 | BKS7: 2034 | BKT7: 2035 | BKU7: 2036 | BKV7: 2037 | BKW7: 2038 | BKX7: 2039 | BKY7: 2040 | BKZ7: 2015 | BLA7: 2016 | BLB7: 2017 | BLC7: 2018 | BLD7: 2019 | BLE7: 2020 | BLF7: 2021 | BLG7: 2022 | BLH7: 2023 | BLI7: 2024 | BLJ7: 2025 | BLK7: 2026 | BLL7: 2027 | BLM7: 2028 | BLN7: 2029 | BLO7: 2030 | BLP7: 2031 | BLQ7: 2032 | BLR7: 2033 | BLS7: 2034 | BLT7: 2035 | BLU7: 2036 | BLV7: 2037 | BLW7: 2038 | BLX7: 2039 | BLY7: 2040 | BLZ7: 2015 | BMA7: 2016 | BMB7: 2017 | BMC7: 2018 | BMD7: 2019 | BME7: 2020 | BMF7: 2021 | BMG7: 2022 | BMH7: 2023 | BMI7: 2024 | BMJ7: 2025 | BMK7: 2026 | BML7: 2027 | BMM7: 2028 | BMN7: 2029 | BMO7: 2030 | BMP7: 2031 | BMQ7: 2032 | BMR7: 2033 | BMS7: 2034 | BMT7: 2035 | BMU7: 2036 | BMV7: 2037 | BMW7: 2038 | BMX7: 2039 | BMY7: 2040 | BMZ7: 2015 | BNA7: 2016 | BNB7: 2017 | BNC7: 2018 | BND7: 2019 | BNE7: 2020 | BNF7: 2021 | BNG7: 2022 | BNH7: 2023 | BNI7: 2024 | BNJ7: 2025 | BNK7: 2026 | BNL7: 2027 | BNM7: 2028 | BNN7: 2029 | BNO7: 2030 | BNP7: 2031 | BNQ7: 2032 | BNR7: 2033 | BNS7: 2034 | BNT7: 2035 | BNU7: 2036 | BNV7: 2037 | BNW7: 2038 | BNX7: 2039 | BNY7: 2040 | BNZ7: 2015 | BOA7: 2016 | BOB7: 2017 | BOC7: 2018 | BOD7: 2019 | BOE7: 2020 | BOF7: 2021 | BOG7: 2022 | BOH7: 2023 | BOI7: 2024 | BOJ7: 2025 | BOK7: 2026 | BOL7: 2027 | BOM7: 2028 | BON7: 2029 | BOO7: 2030 | BOP7: 2031 | BOQ7: 2032 | BOR7: 2033 | BOS7: 2034 | BOT7: 2035 | BOU7: 2036 | BOV7: 2037 | BOW7: 2038 | BOX7: 2039 | BOY7: 2040 | BOZ7: 2015 | BPA7: 2016 | BPB7: 2017 | BPC7: 2018 | BPD7: 2019 | BPE7: 2020 | BPF7: 2021 | BPG7: 2022 | BPH7: 2023 | BPI7: 2024 | BPJ7: 2025 | BPK7: 2026 | BPL7: 2027 | BPM7: 2028 | BPN7: 2029 | BPO7: 2030 | BPP7: 2031 | BPQ7: 2032 | BPR7: 2033 | BPS7: 2034 | BPT7: 2035 | BPU7: 2036 | BPV7: 2037 | BPW7: 2038 | BPX7: 2039 | BPY7: 2040 | BPZ7: 2015 | BQA7: 2016 | BQB7: 2017 | BQC7: 2018 | BQD7: 2019 | BQE7: 2020 | BQF7: 2021 | BQG7: 2022 | BQH7: 2023 | BQI7: 2024 | BQJ7: 2025 | BQK7: 2026 | BQL7: 2027 | BQM7: 2028 | BQN7: 2029 | BQO7: 2030 | BQP7: 2031 | BQQ7: 2032 | BQR7: 2033 | BQS7: 2034 | BQT7: 2035 | BQU7: 2036 | BQV7: 2037 | BQW7: 2038 | BQX7: 2039 | BQY7: 2040 | BQZ7: 2015 | BRA7: 2016 | BRB7: 2017 | BRC7: 2018 | BRD7: 2019 | BRE7: 2020 | BRF7: 2021 | BRG7: 2022 | BRH7: 2023 | BRI7: 2024 | BRJ7: 2025 | BRK7: 2026 | BRL7: 2027 | BRM7: 2028 | BRN7: 2029 | BRO7: 2030 | BRP7: 2031 | BRQ7: 2032 | BRR7: 2033 | BRS7: 2034 | BRT7: 2035 | BRU7: 2036 | BRV7: 2037 | BRW7: 2038 | BRX7: 2039 | BRY7: 2040 | BRZ7: 2015 | BSA7: 2016 | BSB7: 2017 | BSC7: 2018 | BSD7: 2019 | BSE7: 2020 | BSF7: 2021 | BSG7: 2022 | BSH7: 2023 | BSI7: 2024 | BSJ7: 2025 | BSK7: 2026 | BSL7: 2027 | BSM7: 2028 | BSN7: 2029 | BSO7: 2030 | BSP7: 2031 | BSQ7: 2032 | BSR7: 2033 | BSS7: 2034 | BST7: 2035 | BSU7: 2036 | BSV7: 2037 | BSW7: 2038 | BSX7: 2039 | BSY7: 2040 | BSZ7: 2015 | BTA7: 2016 | BTB7: 2017 | BTC7: 2018 | BTD7: 2019 | BTE7: 2020 | BTF7: 2021 | BTG7: 2022 | BTH7: 2023 | BTI7: 2024 | BTJ7: 2025 | BTK7: 2026 | BTL7: 2027 | BTM7: 2028 | BTN7: 2029 | BTO7: 2030 | BTP7: 2031 | BTQ7: 2032 | BTR7: 2033 | BTS7: 2034 | BTT7: 2035 | BTU7: 2036 | BTV7: 2037 | BTW7: 2038 | BTX7: 2039 | BTY7: 2040 | BTZ7: 2015 | BUA7: 2016 | BUB7: 2017 | BUC7: 2018 | BUD7: 2019 | BUE7: 2020 | BUF7: 2021 | BUG7: 2022 | BUH7: 2023 | BUI7: 2024 | BUJ7: 2025 | BUK7: 2026 | BUL7: 2027 | BUM7: 2028 | BUN7: 2029 | BUO7: 2030 | BUP7: 2031 | BUQ7: 2032 | BUR7: 2033 | BUS7: 2034 | BUT7: 2035 | BUU7: 2036 | BUV7: 2037 | BUW7: 2038 | BUX7: 2039 | BUY7: 2040 | BUZ7: 2015 | BVA7: 2016 | BVB7: 2017 | BVC7: 2018 | BVD7: 2019 | BVE7: 2020 | BVF7: 2021 | BVG7: 2022 | BVH7: 2023 | BVI7: 2024 | BVJ7: 2025 | BVK7: 2026 | BVL7: 2027 | BVM7: 2028 | BVN7: 2029 | BVO7: 2030 | BVP7: 2031 | BVQ7: 2032 | BVR7: 2033 | BVS7: 2034 | BVT7: 2035 | BVU7: 2036 | BVV7: 2037 | BVW7: 2038 | BVX7: 2039 | BVY7: 2040 | BVZ7: 2015 | BWA7: 2016 | BWB7: 2017 | BWC7: 2018 | BWD7: 2019 | BWE7: 2020 | BWF7: 2021 | BWG7: 2022 | BWH7: 2023 | BWI7: 2024 | BWJ7: 2025 | BWK7: 2026 | BWL7: 2027 | BWM7: 2028 | BWN7: 2029 | BWO7: 2030 | BWP7: 2031 | BWQ7: 2032 | BWR7: 2033 | BWS7: 2034 | BWT7: 2035 | BWU7: 2036 | BWV7: 2037 | BWW7: 2038 | BWX7: 2039 | BWY7: 2040 | BWZ7: 2015 | BXA7: 2016 | BXB7: 2017 | BXC7: 2018 | BXD7: 2019 | BXE7: 2020 | BXF7: 2021 | BXG7: 2022 | BXH7: 2023 | BXI7: 2024 | BXJ7: 2025 | BXK7: 2026 | BXL7: 2027 | BXM7: 2028 | BXN7: 2029 | BXO7: 2030 | BXP7: 2031 | BXQ7: 2032 | BXR7: 2033 | BXS7: 2034 | BXT7: 2035 | BXU7: 2036 | BXV7: 2037 | BXW7: 2038 | BXX7: 2039 | BXY7: 2040 | BXZ7: 2015 | BYA7: 2016 | BYB7: 2017 | BYC7: 2018 | BYD7: 2019 | BYE7: 2020 | BYF7: 2021 | BYG7: 2022 | BYH7: 2023 | BYI7: 2024 | BYJ7: 2025 | BYK7: 2026 | BYL7: 2027 | BYM7: 2028 | BYN7: 2029 | BYO7: 2030 | BYP7: 2031 | BYQ7: 2032 | BYR7: 2033 | BYS7: 2034 | BYT7: 2035 | BYU7: 2036 | BYV7: 2037 | BYW7: 2038 | BYX7: 2039 | BYY7: 2040 | BYZ7: 2015 | BZA7: 2016 | BZB7: 2017 | BZC7: 2018 | BZD7: 2019 | BZE7: 2020 | BZF7: 2021 | BZG7: 2022 | BZH7: 2023 | BZI7: 2024 | BZJ7: 2025 | BZK7: 2026 | BZL7: 2027 | BZM7: 2028 | BZN7: 2029 | BZO7: 2030 | BZP7: 2031 | BZQ7: 2032 | BZR7: 2033 | BZS7: 2034 | BZT7: 2035 | BZU7: 2036 | BZV7: 2037 | BZW7: 2038 | BZX7: 2039 | BZY7: 2040 | BZZ7: 2015 | CAA7: 2016 | CAB7: 2017 | CAC7: 2018 | CAD7: 2019 | CAE7: 2020 | CAF7: 2021 | CAG7: 2022 | CAH7: 2023 | CAI7: 2024 | CAJ7: 2025 | CAK7: 2026 | CAL7: 2027 | CAM7: 2028 | CAN7: 2029 | CAO7: 2030 | CAP7: 2031 | CAQ7: 2032 | CAR7: 2033 | CAS7: 2034 | CAT7: 2035 | CAU7: 2036 | CAV7: 2037 | CAW7: 2038 | CAX7: 2039 | CAY7: 2040 | CAZ7: 2015 | CBA7: 2016 | CBB7: 2017 | CBC7: 2018 | CBD7: 2019 | CBE7: 2020 | CBF7: 2021 | CBG7: 2022 | CBH7: 2023 | CBI7: 2024 | CBJ7: 2025 | CBK7: 2026 | CBL7: 2027 | CBM7: 2028 | CBN7: 2029 | CBO7: 2030 | CBP7: 2031 | CBQ7: 2032 | CBR7: 2033 | CBS7: 2034 | CBT7: 2035 | CBU7: 2036 | CBV7: 2037 | CBW7: 2038 | CBX7: 2039 | CBY7: 2040 | CBZ7: 2015 | CCA7: 2016 | CCB7: 2017 | CCC7: 2018 | CCD7: 2019 | CCE7: 2020 | CCF7: 2021 | CCG7: 2022 | CCH7: 2023 | CCI7: 2024 | CCJ7: 2025 | CCK7: 2026 | CCL7: 2027 | CCM7: 2028 | CCN7: 2029 | CCO7: 2030 | CCP7: 2031 | CCQ7: 2032 | CCR7: 2033 | CCS7: 2034 | CCT7: 2035 | CCU7: 2036 | CCV7: 2037 | CCW7: 2038 | CCX7: 2039 | CCY7: 2040 | CCZ7: 2015 | CDA7: 2016 | CDB7: 2017 | CDC7: 2018 | CDD7: 2019 | CDE7: 2020 | CDF7: 2021 | CDG7: 2022 | CDH7: 2023 | CDI7: 2024 | CDJ7: 2025 | CDK7: 2026 | CDL7: 2027 | CDM7: 2028 | CDN7: 2029 | CDO7: 2030 | CDP7: 2031 | CDQ7: 2032 | CDR7: 2033 | CDS7: 2034 | CDT7: 2035 | CDU7: 2036 | CDV7: 2037 | CDW7: 2038 | CDX7: 2039 | CDY7: 2040 | CDZ7: 2015 | CEA7: 2016 | CEB7: 2017 | CEC7: 2018 | CED7: 2019 | CEE7: 2020 | CEF7: 2021 | CEG7: 2022 | CEH7: 2023 | CEI7: 2024 | CEJ7: 2025 | CEK7: 2026 | CEL7: 2027 | CEM7: 2028 | CEN7: 2029 | CEO7: 2030 | CEP7: 2031 | CEQ7: 2032 | CER7: 2033 | CES7: 2034 | CET7: 2035 | CEU7: 2036 | CEV7: 2037 | CEW7: 2038 | CEX7: 2039 | CEY7: 2040 | CEZ7: 2015 | CFA7: 2016 | CFB7: 2017 | CFC7: 2018 | CFD7: 2019 | CFE7: 2020 | CFF7: 2021 | CFG7: 2022 | CFH7: 2023 | CFI7: 2024 | CFJ7: 2025 | CFK7: 2026 | CFL7: 2027 | CFM7: 2028 | CFN7: 2029 | CFO7: 2030 | CFP7: 2031 | CFQ7: 2032 | CFR7: 2033 | CFS7: 2034 | CFT7: 2035 | CFU7: 2036 | CFV7: 2037 | CFW7: 2038 | CFX7: 2039 | CFY7: 2040 | CFZ7: 2015 | CGA7: 2016 | CGB7: 2017 | CGC7: 2018 | CGD7: 2019 | CGE7: 2020 | CGF7: 2021 | CGG7: 2022 | CGH7: 2023 | CGI7: 2024 | CGJ7: 2025 | CGK7: 2026 | CGL7: 2027 | CGM7: 2028 | CGN7: 2029 | CGO7: 2030 | CGP7: 2031 | CGQ7: 2032 | CGR7: 2033 | CGS7: 2034 | CGT7: 2035 | CGU7: 2036 | CGV7: 2037 | CGW7: 2038 | CGX7: 2039 | CGY7: 2040 | CGZ7: 2015 | CHA7: 2016 | CHB7: 2017 | CHC7: 2018 | CHD7: 2019 | CHE7: 2020 | CHF7: 2021 | CHG7: 2022 | CHH7: 2023 | CHI7: 2024 | CHJ7: 2025 | CHK7: 2026 | CHL7: 2027 | CHM7: 2028 | CHN7: 2029 | CHO7: 2030 | CHP7: 2031 | CHQ7: 2032 | CHR7: 2033 | CHS7: 2034 | CHT7: 2035 | CHU7: 2036 | CHV7: 2037 | CHW7: 2038 | CHX7: 2039 | CHY7: 2040 | CHZ7: 2015 | CIA7: 2016 | CIB7: 2017 | CIC7: 2018 | CID7: 2019 | CIE7: 2020 | CIF7: 2021 | CIG7: 2022 | CIH7: 2023 | CII7: 2024 | CIJ7: 2025 | CIK7: 2026 | CIL7: 2027 | CIM7: 2028 | CIN7: 2029 | CIO7: 2030 | CIP7: 2031 | CIQ7: 2032 | CIR7: 2033 | CIS7: 2034 | CIT7: 2035 | CIU7: 2036 | CIV7: 2037 | CIW7: 2038 | CIX7: 2039 | CIY7: 2040 | CIZ7: 2015 | CJA7: 2016 | CJB7: 2017 | CJC7: 2018 | CJD7: 2019 | CJE7: 2020 | CJF7: 2021 | CJG7: 2022 | CJH7: 2023 | CJI7: 2024 | CJJ7: 2025 | CJK7: 2026 | CJL7: 2027 | CJM7: 2028 | CJN7: 2029 | CJO7: 2030 | CJP7: 2031 | CJQ7: 2032 | CJR7: 2033 | CJS7: 2034 | CJT7: 2035 | CJU7: 2036 | CJV7: 2037 | CJW7: 2038 | CJX7: 2039 | CJY7: 2040 | CJZ7: 2015 | CKA7: 2016 | CKB7: 2017 | CKC7: 2018 | CKD7: 2019 | CKE7: 2020 | CKF7: 2021 | CKG7: 2022 | CKH7: 2023 | CKI7: 2024 | CKJ7: 2025 | CKK7: 2026 | CKL7: 2027 | CKM7: 2028 | CKN7: 2029 | CKO7: 2030 | CKP7: 2031 | CKQ7: 2032 | CKR7: 2033 | CKS7: 2034 | CKT7: 2035 | CKU7: 2036 | CKV7: 2037 | CKW7: 2038 | CKX7: 2039 | CKY7: 2040 | CKZ7: 2015 | CLA7: 2016 | CLB7: 2017 | CLC7: 2018 | CLD7: 2019 | CLE7: 2020 | CLF7: 2021 | CLG7: 2022 | CLH7: 2023 | CLI7: 2024 | CLJ7: 2025 | CLK7: 2026 | CLL7: 2027 | CLM7: 2028 | CLN7: 2029 | CLO7: 2030 | CLP7: 2031 | CLQ7: 2032 | CLR7: 2033 | CLS7: 2034 | CLT7: 2035 | CLU7: 2036 | CLV7: 2037 | CLW7: 2038 | CLX7: 2039 | CLY7: 2040 | CLZ7: 2015 | CMA7: 2016 | CMB7: 2017 | CMC7: 2018 | CMD7: 2019 | CME7: 2020 | CMF7: 2021 | CMG7: 2022 | CMH7: 2023 | CMI7: 2024 | CMJ7: 2025 | CMK7: 2026 | CML7: 2027 | CMM7: 2028 | CMN7: 2029 | CMO7: 2030 | CMP7: 2031 | CMQ7: 2032 | CMR7: 2033 | CMS7: 2034 | CMT7: 2035 | CMU7: 2036 | CMV7: 2037 | CMW7: 2038 | CMX7: 2039 | CMY7: 2040 | CMZ7: 2015 | CNA7: 2016 | CNB7: 2017 | CNC7: 2018 | CND7: 2019 | CNE7: 2020 | CNF7: 2021 | CNG7: 2022 | CNH7: 2023 | CNI7: 2024 | CNJ7: 2025 | CNK7: 2026 | CNL7: 2027 | CNM7: 2028 | CNN7: 2029 | CNO7: 2030 | CNP7: 2031 | CNQ7: 2032 | CNR7: 2033 | CNS7: 2034 | CNT7: 2035 | CNU7: 2036 | CNV7: 2037 | CNW7: 2038 | CNX7: 2039 | CNY7: 2040 | CNZ7: 2015 | COA7: 2016 | COB7: 2017 | COC7: 2018 | COD7: 2019 | COE7: 2020 | COF7: 2021 | COG7: 2022 | COH7: 2023 | COI7: 2024 | COJ7: 2025 | COK7: 2026 | COL7: 2027 | COM7: 2028 | CON7: 2029 | COO7: 2030 | COP7: 2031 | COQ7: 2032 | COR7: 2033 | COS7: 2034 | COT7: 2035 | COU7: 2036 | COV7: 2037 | COW7: 2038 | COX7: 2039 | COY7: 2040 | COZ7: 2015 | CPA7: 2016 | CPB7: 2017 | CPC7: 2018 | CPD7: 2019 | CPE7: 2020 | CPF7: 2021 | CPG7: 2022 | CPH7: 2023 | CPI7: 2024 | CPJ7: 2025 | CPK7: 2026 | CPL7: 2027 | CPM7: 2028 | CPN7: 2029 | CPO7: 2030 | CPP7: 2031 | CPQ7: 2032 | CPR7: 2033 | CPS7: 2034 | CPT7: 2035 | CPU7: 2036 | CPV7: 2037 | CPW7: 2038 | CPX7: 2039 | CPY7: 2040 | CPZ7: 2015 | CQA7: 2016 | CQB7: 2017 | CQC7: 2018 | CQD7: 2019 | CQE7: 2020 | CQF7: 2021 | CQG7: 2022 | CQH7: 2023 | CQI7: 2024 | CQJ7: 2025 | CQK7: 2026 | CQL7: 2027 | CQM7: 2028 | CQN7: 2029 | CQO7: 2030 | CQP7: 2031 | CQQ7: 2032 | CQR7: 2033 | CQS7: 2034 | CQT7: 2035 | CQU7: 2036 | CQV7: 2037 | CQW7: 2038 | CQX7: 2039 | CQY7: 2040 | CQZ7: 2015 | CRA7: 2016 | CRB7: 2017 | CRC7: 2018 | CRD7: 2019 | CRE7: 2020 | CRF7: 2021 | CRG7: 2022 | CRH7: 2023 | CRI7: 2024 | CRJ7: 2025 | CRK7: 2026 | CRL7: 2027 | CRM7: 2028 | CRN7: 2029 | CRO7: 2030 | CRP7: 2031 | CRQ7: 2032 | CRR7: 2033 | CRS7: 2034 | CRT7: 2035 | CRU7: 2036 | CRV7: 2037 | CRW7: 2038 | CRX7: 2039 | CRY7: 2040 | CRZ7: 2015 | CSA7: 2016 | CSB7: 2017 | CSC7: 2018 | CSD7: 2019 | CSE7: 2020 | CSF7: 2021 | CSG7: 2022 | CSH7: 2023 | CSI7: 2024 | CSJ7: 2025 | CSK7: 2026 | CSL7: 2027 | CSM7: 2028 | CSN7: 2029 | CSO7: 2030 | CSP7: 2031 | CSQ7: 2032 | CSR7: 2033 | CSS7: 2034 | CST7: 2035 | CSU7: 2036 | CSV7: 2037 | CSW7: 2038 | CSX7: 2039 | CSY7: 2040 | CSZ7: 2015 | CTA7: 2016 | CTB7: 2017 | CTC7: 2018 | CTD7: 2019 | CTE7: 2020 | CTF7: 2021 | CTG7: 2022 | CTH7: 2023 | CTI7: 2024 | CTJ7: 2025 | CTK7: 2026 | CTL7: 2027 | CTM7: 2028 | CTN7: 2029 | CTO7: 2030 | CTP7: 2031 | CTQ7: 2032 | CTR7: 2033 | CTS7: 2034 | CTT7: 2035 | CTU7: 2036 | CTV7: 2037 | CTW7: 2038 | CTX7: 2039 | CTY7: 2040 | CTZ7: 2015 | CUA7: 2016 | CUB7: 2017 | CUC7: 2018 | CUD7: 2019 | CUE7: 2020 | CUF7: 2021 | CUG7: 2022 | CUH7: 2023 | CUI7: 2024 | CUJ7: 2025 | CUK7: 2026 | CUL7: 2027 | CUM7: 2028 | CUN7: 2029 | CUO7: 2030 | CUP7: 2031 | CUQ7: 2032 | CUR7: 2033 | CUS7: 2034 | CUT7: 2035 | CUU7: 2036 | CUV7: 2037 | CUW7: 2038 | CUX7: 2039 | CUY7: 2040 | CUZ7: 2015 | CVA7: 2016 | CVB7: 2017 | CVC7: 2018 | CVD7: 2019 | CVE7: 2020 | CVF7: 2021 | CVG7: 2022 | CVH7: 2023 | CVI7: 2024 | CVJ7: 2025 | CVK7: 2026 | CVL7: 2027 | CVM7: 2028 | CVN7: 2029 | CVO7: 2030 | CVP7: 2031 | CVQ7: 2032 | CVR7: 2033 | CVS7: 2034 | CVT7: 2035 | CVU7: 2036 | CVV7: 2037 | CVW7: 2038 | CVX7: 2039 | CVY7: 2040 | CVZ7: 2015 | CWA7: 2016 | CWB7: 2017 | CWC7: 2018 | CWD7: 2019 | CWE7: 2020 | CWF7: 2021 | CWG7: 2022 | CWH7: 2023 | CWI7: 2024 | CWJ7: 2025 | CWK7: 2026 | CWL7: 2027 | CWM7: 2028 | CWN7: 2029 | CWO7: 2030 | CWP7: 2031 | CWQ7: 2032 | CWR7: 2033 | CWS7: 2034 | CWT7: 2035 | CWU7: 2036 | CWV7: 2037 | CWW7: 2038 | CWX7: 2039 | CWY7: 2040 | CWZ7: 2015 | CXA7: 2016 | CXB7: 2017 | CXC7: 2018 | CXD7: 2019 | CXE7: 2020 | CXF7: 2021 | CXG7: 2022 | CXH7: 2023 | CXI7: 2024 | CXJ7: 2025 | CXK7: 2026 | CXL7: 2027 | CXM7: 2028 | CXN7: 2029 | CXO7: 2030 | CXP7: 2031 | CXQ7: 2032 | CXR7: 2033 | CXS7: 2034 | CXT7: 2035 | CXU7: 2036 | CXV7: 2037 | CXW7: 2038 | CXX7: 2039 | CXY7: 2040 | CXZ7: 2015 | CYA7: 2016 | CYB7: 2017 | CYC7: 2018 | CYD7: 2019 | CYE7: 2020 | CYF7: 2021 | CYG7: 2022 | CYH7: 2023 | CYI7: 2024 | CYJ7: 2025 | CYK7: 2026 | CYL7: 2027 | CYM7: 2028 | CYN7: 2029 | CYO7: 2030 | CYP7: 2031 | CYQ7: 2032 | CYR7: 2033 | CYS7: 2034 | CYT7: 2035 | CYU7: 2036 | CYV7: 2037 | CYW7: 2038 | CYX7: 2039 | CYY7: 2040 | CYZ7: 2015 | CZA7: 2016 | CZB7: 2017 | CZC7: 2018 | CZD7: 2019 | CZE7: 2020 | CZF7: 2021 | CZG7: 2022 | CZH7: 2023 | CZI7: 2024 | CZJ7: 2025 | CZK7: 2026 | CZL7: 2027 | CZM7: 2028 | CZN7: 2029 | CZO7: 2030 | CZP7: 2031 | CZQ7: 2032 | CZR7: 2033 | CZS7: 2034 | CZT7: 2035 | CZU7: 2036 | CZV7: 2037 | CZW7: 2038 | CZX7: 2039 | CZY7: 2040 | CZZ7: 2015 | DAA7: 2016 | DAB7: 2017 | DAC7: 2018 | DAD7: 2019 | DAE7: 2020 | DAF7: 2021 | DAG7: 2022 | DAH7: 2023 | DAI7: 2024 | DAJ7: 2025 | DAK7: 2026 | DAL7: 2027 | DAM7: 2028 | DAN7: 2029 | DAO7: 2030 | DAP7: 2031 | DAQ7: 2032 | DAR7: 2033 | DAS7: 2034 | DAT7: 2035 | DAU7: 2036 | DAV7: 2037 | DAW7: 2038 | DAX7: 2039 | DAY7: 2040 | DAZ7: 2015 | DBA7: 2016 | DBB7: 2017 | DBC7: 2018 | DBD7: 2019 | DBE7: 2020 | DBF7: 2021 | DBG7: 2022 | DBH7: 2023 | DBI7: 2024 | DBJ7: 2025 | DBK7: 2026 | DBL7: 2027 | DBM7: 2028 | DBN7: 2029 | DBO7: 2030 | DBP7: 2031 | DBQ7: 2032 | DBR7: 2033 | DBS7: 2034 | DBT7: 2035 | DBU7: 2036 | DBV7: 2037 | DBW7: 2038 | DBX7: 2039 | DBY7: 2040 | DBZ7: 2015 | DCA7: 2016 | DCB7: 2017 | DCC7: 2018 | DCD7: 2019 | DCE7: 2020 | DCF7: 2021 | DCG7: 2022 | DCH7: 2023 | DCI7: 2024 | DCJ7: 2025 | DCK7: 2026 | DCL7: 2027 | DCM7: 2028 | DCN7: 2029 | DCO7: 2030 | DCP7: 2031 | DCQ7: 2032 | DCR7: 2033 | DCS7: 2034 | DCT7: 2035 | DCU7: 2036 | DCV7: 2037 | DCW7: 2038 | DCX7: 2039 | DCY7: 2040 | DCZ7: 2015 | DDA7: 2016 | DDB7: 2017 | DDC7: 2018 | DDD7: 2019 | DDE7: 2020 | DDF7: 2021 | DDG7: 2022 | DDH7: 2023 | DDI7: 2024 | DDJ7: 2025 | DDK7: 2026 | DDL7: 2027 | DDM7: 2028 | DDN7: 2029 | DDO7: 2030 | DDP7: 2031 | DDQ7: 2032 | DDR7: 2033 | DDS7: 2034 | DDT7: 2035 | DDU7: 2036 | DDV7: 2037 | DDW7: 2038 | DDX7: 2039 | DDY7: 2040 | DDZ7: 2015 | DEA7: 2016 | DEB7: 2017 | DEC7: 2018 | DED7: 2019 | DEE7: 2020 | DEF7: 2021 | DEG7: 2022 | DEH7: 2023 | DEI7: 2024 | DEJ7: 2025 | DEK7: 2026 | DEL7: 2027 | DEM7: 2028 | DEN7: 2029 | DEO7: 2030 | DEP7: 2031 | DEQ7: 2032 | DER7: 2033 | DES7: 2034 | DET7: 2035 | DEU7: 2036 | DEV7: 2037 | DEW7: 2038 | DEX7: 2039 | DEY7: 2040 | DEZ7: 2015 | DFA7: 2016 | DFB7: 2017 | DFC7: 2018 | DFD7: 2019 | DFE7: 2020 | DFF7: 2021 | DFG7: 2022 | DFH7: 2023 | DFI7: 2024 | DFJ7: 2025 | DFK7: 2026 | DFL7: 2027 | DFM7: 2028 | DFN7: 2029 | DFO7: 2030 | DFP7: 2031 | DFQ7: 2032 | DFR7: 2033 | DFS7: 2034 | DFT7: 2035 | DFU7: 2036 | DFV7: 2037 | DFW7: 2038 | DFX7: 2039 | DFY7: 2040 | DFZ7: 2015 | DGA7: 2016 | DGB7: 2017 | DGC7: 2018 | DGD7: 2019 | DGE7: 2020 | DGF7: 2021 | DGG7: 2022 | DGH7: 2023 | DGI7: 2024 | DGJ7: 2025 | DGK7: 2026 | DGL7: 2027 | DGM7: 2028 | DGN7: 2029 | DGO7: 2030 | DGP7: 2031 | DGQ7: 2032 | DGR7: 2033 | DGS7: 2034 | DGT7: 2035 | DGU7: 2036 | DGV7: 2037 | DGW7: 2038 | DGX7: 2039 | DGY7: 2040 | DGZ7: 2015 | DHA7: 2016 | DHB7: 2017 | DHC7: 2018 | DHD7: 2019 | DHE7: 2020 | DHF7: 2021 | DHG7: 2022 | DHH7: 2023 | DHI7: 2024 | DHJ7: 2025 | DHK7: 2026 | DHL7: 2027 | DHM7: 2028 | DHN7: 2029 | DHO7: 2030 | DHP7: 2031 | DHQ7: 2032 | DHR7: 2033 | DHS7: 2034 | DHT7: 2035 | DHU7: 2036 | DHV7: 2037 | DHW7: 2038 | DHX7: 2039 | DHY7: 2040 | DHZ7: to poor WASH | DIA7: basic WASH | DIB7: 0-4 yr | DIC7: 5-14 yr | DID7: 15+ yr | DIE7: 0-4 yr | DIF7: 5-14 yr | DIG7: 15+ yr | DIH7: Total | DII7: Total | DIJ7: Total | DIK7: Total | DIL7: Total | DIM7: Total | DIN7: Total | DIO7: Total | DIP7: Urban | DIQ7: Rural | DIR7: Urban | DIS7: Rural | DIT7: 2015 | DIU7: 2016 | DIV7: 2017 | DIW7: 2018 | DIX7: 2019 | DIY7: 2020 | DIZ7: 2021 | DJA7: 2022 | DJB7: 2023 | DJC7: 2024 | DJD7: 2025 | DJE7: 2026 | DJF7: 2027 | DJG7: 2028 | DJH7: 2029 | DJI7: 2030 | DJJ7: 2031 | DJK7: 2032 | DJL7: 2033 | DJM7: 2034 | DJN7: 2035 | DJO7: 2036 | DJP7: 2037 | DJQ7: 2038 | DJR7: 2039 | DJS7: 2040 | DJT7: 2015 | DJU7: 2016 | DJV7: 2017 | DJW7: 2018 | DJX7: 2019 | DJY7: 2020 | DJZ7: 2021 | DKA7: 2022 | DKB7: 2023 | DKC7: 2024 | DKD7: 2025 | DKE7: 2026 | DKF7: 2027 | DKG7: 2028 | DKH7: 2029 | DKI7: 2030 | DKJ7: 2031 | DKK7: 2032 | DKL7: 2033 | DKM7: 2034 | DKN7: 2035 | DKO7: 2036 | DKP7: 2037 | DKQ7: 2038 | DKR7: 2039 | DKS7: 2040 | DKT7: 2015 | DKU7: 2016 | DKV7: 2017 | DKW7: 2018 | DKX7: 2019 | DKY7: 2020 | DKZ7: 2021 | DLA7: 2022 | DLB7: 2023 | DLC7: 2024 | DLD7: 2025 | DLE7: 2026 | DLF7: 2027 | DLG7: 2028 | DLH7: 2029 | DLI7: 2030 | DLJ7: 2031 | DLK7: 2032 | DLL7: 2033 | DLM7: 2034 | DLN7: 2035 | DLO7: 2036 | DLP7: 2037 | DLQ7: 2038 | DLR7: 2039 | DLS7: 2040 | DLT7: 2015 | DLU7: 2016 | DLV7: 2017 | DLW7: 2018 | DLX7: 2019 | DLY7: 2020 | DLZ7: 2021 | DMA7: 2022 | DMB7: 2023 | DMC7: 2024 | DMD7: 2025 | DME7: 2026 | DMF7: 2027 | DMG7: 2028 | DMH7: 2029 | DMI7: 2030 | DMJ7: 2031 | DMK7: 2032 | DML7: 2033 | DMM7: 2034 | DMN7: 2035 | DMO7: 2036 | DMP7: 2037 | DMQ7: 2038 | DMR7: 2039 | DMS7: 2040 | DMT7: 2015 | DMU7: 2016 | DMV7: 2017 | DMW7: 2018 | DMX7: 2019 | DMY7: 2020 | DMZ7: 2021 | DNA7: 2022 | DNB7: 2023 | DNC7: 2024 | DND7: 2025 | DNE7: 2026 | DNF7: 2027 | DNG7: 2028 | DNH7: 2029 | DNI7: 2030 | DNJ7: 2031 | DNK7: 2032 | DNL7: 2033 | DNM7: 2034 | DNN7: 2035 | DNO7: 2036 | DNP7: 2037 | DNQ7: 2038 | DNR7: 2039 | DNS7: 2040 | DNT7: 2015 | DNU7: 2016 | DNV7: 2017 | DNW7: 2018 | DNX7: 2019 | DNY7: 2020 | DNZ7: 2021 | DOA7: 2022 | DOB7: 2023 | DOC7: 2024 | DOD7: 2025 | DOE7: 2026 | DOF7: 2027 | DOG7: 2028 | DOH7: 2029 | DOI7: 2030 | DOJ7: 2031 | DOK7: 2032 | DOL7: 2033 | DOM7: 2034 | DON7: 2035 | DOO7: 2036 | DOP7: 2037 | DOQ7: 2038 | DOR7: 2039 | DOS7: 2040 | DOT7: 2015 | DOU7: 2016 | DOV7: 2017 | DOW7: 2018 | DOX7: 2019 | DOY7: 2020 | DOZ7: 2021 | DPA7: 2022 | DPB7: 2023 | DPC7: 2024 | DPD7: 2025 | DPE7: 2026 | DPF7: 2027 | DPG7: 2028 | DPH7: 2029 | DPI7: 2030 | DPJ7: 2031 | DPK7: 2032 | DPL7: 2033 | DPM7: 2034 | DPN7: 2035 | DPO7: 2036 | DPP7: 2037 | DPQ7: 2038 | DPR7: 2039 | DPS7: 2040 | DPT7: 2015 | DPU7: 2016 | DPV7: 2017 | DPW7: 2018 | DPX7: 2019 | DPY7: 2020 | DPZ7: 2021 | DQA7: 2022 | DQB7: 2023 | DQC7: 2024 | DQD7: 2025 | DQE7: 2026 | DQF7: 2027 | DQG7: 2028 | DQH7: 2029 | DQI7: 2030 | DQJ7: 2031 | DQK7: 2032 | DQL7: 2033 | DQM7: 2034 | DQN7: 2035 | DQO7: 2036 | DQP7: 2037 | DQQ7: 2038 | DQR7: 2039 | DQS7: 2040 | DQT7: 2015 | DQU7: 2016 | DQV7: 2017 | DQW7: 2018 | DQX7: 2019 | DQY7: 2020 | DQZ7: 2021 | DRA7: 2022 | DRB7: 2023 | DRC7: 2024 | DRD7: 2025 | DRE7: 2026 | DRF7: 2027 | DRG7: 2028 | DRH7: 2029 | DRI7: 2030 | DRJ7: 2031 | DRK7: 2032 | DRL7: 2033 | DRM7: 2034 | DRN7: 2035 | DRO7: 2036 | DRP7: 2037 | DRQ7: 2038 | DRR7: 2039 | DRS7: 2040 | DRT7: 2015 | DRU7: 2016 | DRV7: 2017 | DRW7: 2018 | DRX7: 2019 | DRY7: 2020 | DRZ7: 2021 | DSA7: 2022 | DSB7: 2023 | DSC7: 2024 | DSD7: 2025 | DSE7: 2026 | DSF7: 2027 | DSG7: 2028 | DSH7: 2029 | DSI7: 2030 | DSJ7: 2031 | DSK7: 2032 | DSL7: 2033 | DSM7: 2034 | DSN7: 2035 | DSO7: 2036 | DSP7: 2037 | DSQ7: 2038 | DSR7: 2039 | DSS7: 2040 | DST7: 2015 | DSU7: 2016 | DSV7: 2017 | DSW7: 2018 | DSX7: 2019 | DSY7: 2020 | DSZ7: 2021 | DTA7: 2022 | DTB7: 2023 | DTC7: 2024 | DTD7: 2025 | DTE7: 2026 | DTF7: 2027 | DTG7: 2028 | DTH7: 2029 | DTI7: 2030 | DTJ7: 2031 | DTK7: 2032 | DTL7: 2033 | DTM7: 2034 | DTN7: 2035 | DTO7: 2036 | DTP7: 2037 | DTQ7: 2038 | DTR7: 2039 | DTS7: 2040 | DTT7: 2015 | DTU7: 2016 | DTV7: 2017 | DTW7: 2018 | DTX7: 2019 | DTY7: 2020 | DTZ7: 2021 | DUA7: 2022 | DUB7: 2023 | DUC7: 2024 | DUD7: 2025 | DUE7: 2026 | DUF7: 2027 | DUG7: 2028 | DUH7: 2029 | DUI7: 2030 | DUJ7: 2031 | DUK7: 2032 | DUL7: 2033 | DUM7: 2034 | DUN7: 2035 | DUO7: 2036 | DUP7: 2037 | DUQ7: 2038 | DUR7: 2039 | DUS7: 2040 | DUT7: 2015 | DUU7: 2016 | DUV7: 2017 | DUW7: 2018 | DUX7: 2019 | DUY7: 2020 | DUZ7: 2021 | DVA7: 2022 | DVB7: 2023 | DVC7: 2024 | DVD7: 2025 | DVE7: 2026 | DVF7: 2027 | DVG7: 2028 | DVH7: 2029 | DVI7: 2030 | DVJ7: 2031 | DVK7: 2032 | DVL7: 2033 | DVM7: 2034 | DVN7: 2035 | DVO7: 2036 | DVP7: 2037 | DVQ7: 2038 | DVR7: 2039 | DVS7: 2040 | DVT7: 2015 | DVU7: 2016 | DVV7: 2017 | DVW7: 2018 | DVX7: 2019 | DVY7: 2020 | DVZ7: 2021 | DWA7: 2022 | DWB7: 2023 | DWC7: 2024 | DWD7: 2025 | DWE7: 2026 | DWF7: 2027 | DWG7: 2028 | DWH7: 2029 | DWI7: 2030 | DWJ7: 2031 | DWK7: 2032 | DWL7: 2033 | DWM7: 2034 | DWN7: 2035 | DWO7: 2036 | DWP7: 2037 | DWQ7: 2038 | DWR7: 2039 | DWS7: 2040 | DWT7: 2015 | DWU7: 2016 | DWV7: 2017 | DWW7: 2018 | DWX7: 2019 | DWY7: 2020 | DWZ7: 2021 | DXA7: 2022 | DXB7: 2023 | DXC7: 2024 | DXD7: 2025 | DXE7: 2026 | DXF7: 2027 | DXG7: 2028 | DXH7: 2029 | DXI7: 2030 | DXJ7: 2031 | DXK7: 2032 | DXL7: 2033 | DXM7: 2034 | DXN7: 2035 | DXO7: 2036 | DXP7: 2037 | DXQ7: 2038 | DXR7: 2039 | DXS7: 2040 | DXT7: 2015 | DXU7: 2016 | DXV7: 2017 | DXW7: 2018 | DXX7: 2019 | DXY7: 2020 | DXZ7: 2021 | DYA7: 2022 | DYB7: 2023 | DYC7: 2024 | DYD7: 2025 | DYE7: 2026 | DYF7: 2027 | DYG7: 2028 | DYH7: 2029 | DYI7: 2030 | DYJ7: 2031 | DYK7: 2032 | DYL7: 2033 | DYM7: 2034 | DYN7: 2035 | DYO7: 2036 | DYP7: 2037 | DYQ7: 2038 | DYR7: 2039 | DYS7: 2040 | DYT7: 2017 | DYU7: Urban | DYV7: Rural | DYW7: Urban | DYX7: Rural | DYY7: Urban | DYZ7: Rural | DZL7: From limited | DZM7: From unimproved | DZN7: From surface water | DZO7: From ODF | DZP7: From shared | DZQ7: From limited | DZR7: From unimproved | DZS7: From surface water | DZT7: From ODF | DZU7: From shared | DZW7: Annual increase | EBO7: 2015 | EBP7: 2016 | EBQ7: 2017 | EBR7: 2018 | EBS7: 2019 | EBT7: 2020 | EBU7: 2021 | EBV7: 2022 | EBW7: 2023 | EBX7: 2024 | EBY7: 2025 | EBZ7: 2026 | ECA7: 2027 | ECB7: 2028 | ECC7: 2029 | ECD7: 2030 | ECE7: 2031 | ECF7: 2032 | ECG7: 2033 | ECH7: 2034 | ECI7: 2035 | ECJ7: 2036 | ECK7: 2037 | ECL7: 2038 | ECM7: 2039 | ECN7: 2040 | ECO7: 2015 | ECP7: 2016 | ECQ7: 2017 | ECR7: 2018 | ECS7: 2019 | ECT7: 2020 | ECU7: 2021 | ECV7: 2022 | ECW7: 2023 | ECX7: 2024 | ECY7: 2025 | ECZ7: 2026 | EDA7: 2027 | EDB7: 2028 | EDC7: 2029 | EDD7: 2030 | EDE7: 2031 | EDF7: 2032 | EDG7: 2033 | EDH7: 2034 | EDI7: 2035 | EDJ7: 2036 | EDK7: 2037 | EDL7: 2038 | EDM7: 2039 | EDN7: 2040 | EDO7: 2015 | EDP7: 2016 | EDQ7: 2017 | EDR7: 2018 | EDS7: 2019 | EDT7: 2020 | EDU7: 2021 | EDV7: 2022 | EDW7: 2023 | EDX7: 2024 | EDY7: 2025 | EDZ7: 2026 | EEA7: 2027 | EEB7: 2028 | EEC7: 2029 | EED7: 2030 | EEE7: 2031 | EEF7: 2032 | EEG7: 2033 | EEH7: 2034 | EEI7: 2035 | EEJ7: 2036 | EEK7: 2037 | EEL7: 2038 | EEM7: 2039 | EEN7: 2040 | EEO7: 2015 | EEP7: 2016 | EEQ7: 2017 | EER7: 2018 | EES7: 2019 | EET7: 2020 | EEU7: 2021 | EEV7: 2022 | EEW7: 2023 | EEX7: 2024 | EEY7: 2025 | EEZ7: 2026 | EFA7: 2027 | EFB7: 2028 | EFC7: 2029 | EFD7: 2030 | EFE7: 2031 | EFF7: 2032 | EFG7: 2033 | EFH7: 2034 | EFI7: 2035 | EFJ7: 2036 | EFK7: 2037 | EFL7: 2038 | EFM7: 2039 | EFN7: 2040 | EFO7: 2015 | EFP7: 2016 | EFQ7: 2017 | EFR7: 2018 | EFS7: 2019 | EFT7: 2020 | EFU7: 2021 | EFV7: 2022 | EFW7: 2023 | EFX7: 2024 | EFY7: 2025 | EFZ7: 2026 | EGA7: 2027 | EGB7: 2028 | EGC7: 2029 | EGD7: 2030 | EGE7: 2031 | EGF7: 2032 | EGG7: 2033 | EGH7: 2034 | EGI7: 2035 | EGJ7: 2036 | EGK7: 2037 | EGL7: 2038 | EGM7: 2039 | EGN7: 2040 | EGO7: 2015 | EGP7: 2016 | EGQ7: 2017 | EGR7: 2018 | EGS7: 2019 | EGT7: 2020 | EGU7: 2021 | EGV7: 2022 | EGW7: 2023 | EGX7: 2024 | EGY7: 2025 | EGZ7: 2026 | EHA7: 2027 | EHB7: 2028 | EHC7: 2029 | EHD7: 2030 | EHE7: 2031 | EHF7: 2032 | EHG7: 2033 | EHH7: 2034 | EHI7: 2035 | EHJ7: 2036 | EHK7: 2037 | EHL7: 2038 | EHM7: 2039 | EHN7: 2040 | EHO7: Total BAU 2018-30 | EHP7: Total BAU 2018-40 | EHQ7: Annual BAU 2018-30 | EHR7: Annual BAU 2018-40 | EHS7: Total BAU 2018-30 | EHT7: Total BAU 2018-40 | EHU7: Annual BAU 2018-30 | EHV7: Annual BAU 2018-40 | EHW7: Total BAU 2018-30 | EHX7: Total BAU 2018-40 | EHY7: Annual BAU 2018-30 | EHZ7: Annual BAU 2018-40 | EIA7: Total WASH 2018-30 | EIB7: Total WASH 2018-40 | EIC7: Annual WASH 2018-30 | EID7: Annual WASH 2018-40 | EIE7: Total WASH 2018-30 | EIF7: Total WASH 2018-40 | EIG7: Annual WASH 2018-30 | EIH7: Annual WASH 2018-40 | EII7: Total WASH 2018-30 | EIJ7: Total WASH 2018-40 | EIK7: Annual WASH 2018-30 | EIL7: Annual WASH 2018-40 | EIM7: Total averted 2018-30 | EIN7: Total averted 2018-40 | EIO7: Annual averted 2018-30 | EIP7: Annual averted 2018-40 | EIQ7: Total averted 2018-30 | EIR7: Total averted 2018-40 | EIS7: Annual averted 2018-30 | EIT7: Annual averted 2018-40 | EIU7: Total averted 2018-30 | EIV7: Total averted 2018-40 | EIW7: Annual averted 2018-30 | EIX7: Annual averted 2018-40 | EIY7: 2015 | EIZ7: 2016 | EJA7: 2017 | EJB7: 2018 | EJC7: 2019 | EJD7: 2020 | EJE7: 2021 | EJF7: 2022 | EJG7: 2023 | EJH7: 2024 | EJI7: 2025 | EJJ7: 2026 | EJK7: 2027 | EJL7: 2028 | EJM7: 2029 | EJN7: 2030 | EJO7: 2031 | EJP7: 2032 | EJQ7: 2033 | EJR7: 2034 | EJS7: 2035 | EJT7: 2036 | EJU7: 2037 | EJV7: 2038 | EJW7: 2039 | EJX7: 2040 | EJY7: 2015 | EJZ7: 2016 | EKA7: 2017 | EKB7: 2018 | EKC7: 2019 | EKD7: 2020 | EKE7: 2021 | EKF7: 2022 | EKG7: 2023 | EKH7: 2024 | EKI7: 2025 | EKJ7: 2026 | EKK7: 2027 | EKL7: 2028 | EKM7: 2029 | EKN7: 2030 | EKO7: 2031 | EKP7: 2032 | EKQ7: 2033 | EKR7: 2034 | EKS7: 2035 | EKT7: 2036 | EKU7: 2037 | EKV7: 2038 | EKW7: 2039 | EKX7: 2040 | EKY7: 2015 | EKZ7: 2016 | ELA7: 2017 | ELB7: 2018 | ELC7: 2019 | ELD7: 2020 | ELE7: 2021 | ELF7: 2022 | ELG7: 2023 | ELH7: 2024 | ELI7: 2025 | ELJ7: 2026 | ELK7: 2027 | ELL7: 2028 | ELM7: 2029 | ELN7: 2030 | ELO7: 2031 | ELP7: 2032 | ELQ7: 2033 | ELR7: 2034 | ELS7: 2035 | ELT7: 2036 | ELU7: 2037 | ELV7: 2038 | ELW7: 2039 | ELX7: 2040 | ELY7: 2015 | ELZ7: 2016 | EMA7: 2017 | EMB7: 2018 | EMC7: 2019 | EMD7: 2020 | EME7: 2021 | EMF7: 2022 | EMG7: 2023 | EMH7: 2024 | EMI7: 2025 | EMJ7: 2026 | EMK7: 2027 | EML7: 2028 | EMM7: 2029 | EMN7: 2030 | EMO7: 2031 | EMP7: 2032 | EMQ7: 2033 | EMR7: 2034 | EMS7: 2035 | EMT7: 2036 | EMU7: 2037 | EMV7: 2038 | EMW7: 2039 | EMX7: 2040 | EMY7: 2015 | EMZ7: 2016 | ENA7: 2017 | ENB7: 2018 | ENC7: 2019 | END7: 2020 | ENE7: 2021 | ENF7: 2022 | ENG7: 2023 | ENH7: 2024 | ENI7: 2025 | ENJ7: 2026 | ENK7: 2027 | ENL7: 2028 | ENM7: 2029 | ENN7: 2030 | ENO7: 2031 | ENP7: 2032 | ENQ7: 2033 | ENR7: 2034 | ENS7: 2035 | ENT7: 2036 | ENU7: 2037 | ENV7: 2038 | ENW7: 2039 | ENX7: 2040 | ENY7: 2015 | ENZ7: 2016 | EOA7: 2017 | EOB7: 2018 | EOC7: 2019 | EOD7: 2020 | EOE7: 2021 | EOF7: 2022 | EOG7: 2023 | EOH7: 2024 | EOI7: 2025 | EOJ7: 2026 | EOK7: 2027 | EOL7: 2028 | EOM7: 2029 | EON7: 2030 | EOO7: 2031 | EOP7: 2032 | EOQ7: 2033 | EOR7: 2034 | EOS7: 2035 | EOT7: 2036 | EOU7: 2037 | EOV7: 2038 | EOW7: 2039 | EOX7: 2040 | EOY7: Total BAU 2018-30 | EOZ7: Total BAU 2018-40 | EPA7: Annual BAU 2018-30 | EPB7: Annual BAU 2018-40 | EPC7: Total BAU 2018-30 | EPD7: Total BAU 2018-40 | EPE7: Annual BAU 2018-30 | EPF7: Annual BAU 2018-40 | EPG7: Total BAU 2018-30 | EPH7: Total BAU 2018-40 | EPI7: Annual BAU 2018-30 | EPJ7: Annual BAU 2018-40 | EPK7: Total WASH 2018-30 | EPL7: Total WASH 2018-40 | EPM7: Annual WASH 2018-30 | EPN7: Annual WASH 2018-40 | EPO7: Total WASH 2018-30 | EPP7: Total WASH 2018-40 | EPQ7: Annual WASH 2018-30 | EPR7: Annual WASH 2018-40 | EPS7: Total WASH 2018-30 | EPT7: Total WASH 2018-40 | EPU7: Annual WASH 2018-30 | EPV7: Annual WASH 2018-40 | EPW7: Total averted 2018-30 | EPX7: Total averted 2018-40 | EPY7: Annual averted 2018-30 | EPZ7: Annual averted 2018-40 | EQA7: Total averted 2018-30 | EQB7: Total averted 2018-40 | EQC7: Annual averted 2018-30 | EQD7: Annual averted 2018-40 | EQE7: Total averted 2018-30 | EQF7: Total averted 2018-40 | EQG7: Annual averted 2018-30 | EQH7: Annual averted 2018-40 | EQI7: CRISIS COUNTRY?
A8: =IF(INDIRECT("'User Inputs'!" & A9)="",INDIRECT("'Country Data'!"&A$3&MATCH('Country Model'!$A$1,'Country Data'!$A$1:$A$60,FALSE)),INDIRECT("'User Inputs'!" & A9)) -> Malawi | B8: =IF(INDIRECT("'User Inputs'!" & B9)="",INDIRECT("'Country Data'!"&B$3&MATCH('Country Model'!$A$1,'Country Data'!$A$1:$A$60,FALSE)),INDIRECT("'User Inputs'!" & B9)) -> MWI | C8: =IF(INDIRECT("'User Inputs'!" & C9)="",INDIRECT("'Country Data'!"&C$3&MATCH('Country Model'!$A$1,'Country Data'!$A$1:$A$60,FALSE)),INDIRECT("'User Inputs'!" & C9)) -> 2 | D8: =IF(INDIRECT("'User Inputs'!" & D9)="",INDIRECT("'Country Data'!"&D$3&MATCH('Country Model'!$A$1,'Country Data'!$A$1:$A$60,FALSE)),INDIRECT("'User Inputs'!" & D9)) -> 1 | E8: =IF(INDIRECT("'User Inputs'!" & E9)="",INDIRECT("'Country Data'!"&E$3&MATCH('Country Model'!$A$1,'Country Data'!$A$1:$A$60,FALSE)),INDIRECT("'User Inputs'!" & E9)) -> Sub-Saharan Africa | F8: =IF(INDIRECT("'User Inputs'!" & F9)="",INDIRECT("'Country Data'!"&F$3&MATCH('Country Model'!$A$1,'Country Data'!$A$1:$A$60,FALSE)),INDIRECT("'User Inputs'!" & F9)) -> AFRO | G8: =IF(INDIRECT("'User Inputs'!" & G9)="",INDIRECT("'Country Data'!"&G$3&MATCH('Country Model'!$A$1,'Country Data'!$A$1:$A$60,FALSE)),INDIRECT("'User Inputs'!" & G9)) -> Low income | H8: =IF(INDIRECT("'User Inputs'!" & H9)="",INDIRECT("'Country Data'!"&H$3&MATCH('Country Model'!$A$1,'Country Data'!$A$1:$A$60,FALSE)),INDIRECT("'User Inputs'!" & H9)) -> Yes | ... EQI8: =IF(INDIRECT("'User Inputs'!" & EQI9)="",INDIRECT("'Country Data'!"&EQI$3&MATCH('Country Model'!$A$1,'Country Data'!$A$1:$A$60,FALSE)),INDIRECT("'User Inputs'!" & EQI9)) -> Stable
